Workbook

Sheet Raw Data
A1: Post ID | B1: University | C1: Post Date | D1: Month | E1: Year | F1: Instagram URL | G1: Post Type | H1: Recruitment-Oriented? | I1: Primary Theme | J1: Secondary Theme | K1: Marketing Approach | L1: CTA Present? | M1: Likes | N1: Comments | O1: Caption Summary
A2: UOT001 | B2: University of Toronto | C2: 45677 | D2: =IF(C2="","",TEXT(C2,"mmmm")) -> January | E2: =IF(C2="","",YEAR(C2)) -> 2025 | F2: https://www.instagram.com/reel/DFDbR9zSpaG/?utm_source=ig_web_copy_link&igsh=MzRlODBiNWFlZA== | G2: Reel | H2: Yes | I2: Student Experience | J2: Campus Life | K2: Emotional Storytelling | L2: Yes | M2: 574 | N2: 17 | O2: We’re asking @uoftmedicine & @uoftrunclub’s Emily Nguyen about her rapid fire faves at #UofT! Have you seen our first #MyUofT video? Be sure to check it out!
A3: UOT002 | B3: University of Toronto | C3: 45684 | D3: =IF(C3="","",TEXT(C3,"mmmm")) -> January | E3: =IF(C3="","",YEAR(C3)) -> 2025 | F3: https://www.instagram.com/p/DFV2mHuyw7n/?utm_source=ig_web_copy_link&igsh=MzRlODBiNWFlZA== | G3: Image | H3: Yes | I3: Rankings & Achievements | J3: Academic Programs | K3: Reputation Building | L3: Yes | M3: 1513 | N3: 17 | O3: #UofT ranked first in Canada in all 11 subjects tracked by Times Higher Education’s World University Rankings by Subject 2025 – and is one of only six universities in the world to rank in the top 30 across the board. 🍁
A4: UOT003 | B4: University of Toronto | C4: 45687 | D4: =IF(C4="","",TEXT(C4,"mmmm")) -> January | E4: =IF(C4="","",YEAR(C4)) -> 2025 | F4: https://www.instagram.com/reel/DFdo9ZNv8UA/?utm_source=ig_web_copy_link&igsh=MzRlODBiNWFlZA== | G4: Reel | H4: Yes | I4: Alumni Success | J4: Events | K4: Community Engagement | L4: Yes | M4: 248 | N4: 3 | O4: What if sharing your expertise could spark a positive change? With more than 23,000 #UofTalumni already stepping up as mentors and volunteers, our #UofT community is powered by the passion and dedication of our grads.
A5: UOT004 | B5: University of Toronto | C5: 45693 | D5: =IF(C5="","",TEXT(C5,"mmmm")) -> February | E5: =IF(C5="","",YEAR(C5)) -> 2025 | F5: https://www.instagram.com/p/DFtOatUykUC/?utm_source=ig_web_copy_link&igsh=MzRlODBiNWFlZA== | G5: Image | H5: Yes | I5: Research & Innovation | J5: Rankings & Achievements | K5: Reputation Building | L5: Yes | M5: 1031 | N5: 16 | O5: #UofT is among the world’s top 10 universities powering global innovation in critical areas like technology, health care, sustainability and economic development, according to international data analytics company Clarivate.
A6: UOT005 | B6: University of Toronto | C6: 45699 | D6: =IF(C6="","",TEXT(C6,"mmmm")) -> February | E6: =IF(C6="","",YEAR(C6)) -> 2025 | F6: https://www.instagram.com/reel/DF8FBerRF8m/?utm_source=ig_web_copy_link&igsh=MzRlODBiNWFlZA== | G6: Reel | H6: Yes | I6: Student Experience | J6: Campus Life | K6: Student Testimonial | L6: Yes | M6: 2628 | N6: 33 | O6: A day in the life of a @uoftims & #UofT PhD student, @sciencewithsajee!
A7: UOT006 | B7: University of Toronto | C7: 45702 | D7: =IF(C7="","",TEXT(C7,"mmmm")) -> February | E7: =IF(C7="","",YEAR(C7)) -> 2025 | F7: https://www.instagram.com/p/DGDu9TwRvKz/?utm_source=ig_web_copy_link&igsh=MzRlODBiNWFlZA== | G7: Carousel | H7: Yes | I7: Diversity & Inclusion | J7: Research & Innovation | K7: Emotional Storytelling | L7: Yes | M7: 1516 | N7: 9 | O7: Diagnosed with autism, he couldn’t speak or signal his thoughts. But everything changed when he learned to communicate through a letter board. What followed stunned his family. Now, he is helping #UofT neuroscientist Morgan Barense with her research @uoftpsychology using brain scans into non-speaking autism.
A8: UOT007 | B8: University of Toronto | C8: 45729 | D8: =IF(C8="","",TEXT(C8,"mmmm")) -> March | E8: =IF(C8="","",YEAR(C8)) -> 2025 | F8: https://www.instagram.com/reel/DHJab1PRh1X/?utm_source=ig_web_copy_link&igsh=MzRlODBiNWFlZA== | G8: Reel | H8: Yes | I8: Alumni Success | J8: Events | K8: Community Engagement | L8: Yes | M8: 1047 | N8: 73 | O8: This is @uoftstartup’s #UofTEntWeek, founder style! Follow #UofT alumna & Toothpod founder @vishar.y as she explores everything U of T Entrepreneurship has to offer, including her personal advice on getting started.
A9: UOT008 | B9: University of Toronto | C9: 45733 | D9: =IF(C9="","",TEXT(C9,"mmmm")) -> March | E9: =IF(C9="","",YEAR(C9)) -> 2025 | F9: https://www.instagram.com/reel/DHT7iTYxaMb/?utm_source=ig_web_copy_link&igsh=MzRlODBiNWFlZA== | G9: Reel | H9: Yes | I9: Diversity & Inclusion | J9: Alumni Success | K9: Inspirational | L9: No | M9: 2463 | N9: 59 | O9: 11 languages? 🤯 Recent #UofT alumni and hyperpolyglot @xinyi_limx shows us her appreciation for the diversity and rich culture that Toronto has to offer. #MyUofT
A10: UOT009 | B10: University of Toronto | C10: 45736 | D10: =IF(C10="","",TEXT(C10,"mmmm")) -> March | E10: =IF(C10="","",YEAR(C10)) -> 2025 | F10: https://www.instagram.com/reel/DHbOdPjyScp/?utm_source=ig_web_copy_link&igsh=MzRlODBiNWFlZA== | G10: Reel | H10: Yes | I10: Admissions | J10: Student Support Services | K10: Call-to-Action | L10: Yes | M10: 537 | N10: 11 | O10: Did you get an acceptance letter from #UofT? Congratulations! 🎉 We want to see your excitement to start your journey with us next year! DM us or post a video with #UofTBound tagging @futureuoft, @uoft and your campus @utsc or @uoftmississauga for your chance to be featured on our accounts!
A11: UOT010 | B11: University of Toronto | C11: 45748 | D11: =IF(C11="","",TEXT(C11,"mmmm")) -> April | E11: =IF(C11="","",YEAR(C11)) -> 2025 | F11: https://www.instagram.com/p/DH6YEVQOf-Z/?utm_source=ig_web_copy_link&igsh=MzRlODBiNWFlZA== | G11: Carousel | H11: Yes | I11: Admissions | J11: Academic Programs | K11: Promotional | L11: Yes | M11: 2233 | N11: 20 | O11: #UTM March Open House was a memorable day filled with opportunities! 💙 .
A12: UOT011 | B12: University of Toronto | C12: 45751 | D12: =IF(C12="","",TEXT(C12,"mmmm")) -> April | E12: =IF(C12="","",YEAR(C12)) -> 2025 | F12: https://www.instagram.com/reel/DIB-jGhRYlB/?utm_source=ig_web_copy_link&igsh=MzRlODBiNWFlZA== | G12: Reel | H12: Yes | I12: Campus Facilities | J12: Student Experience | K12: Emotional Storytelling | L12: Yes | M12: 1645 | N12: 14 | O12: After being named #UofT’s 17th president on March 26, Melanie Woodin met with students, staff, faculty and senior leaders across U of T’s three campuses during a whirlwind two-day tour. 💙
A13: UOT012 | B13: University of Toronto | C13: 45772 | D13: =IF(C13="","",TEXT(C13,"mmmm")) -> April | E13: =IF(C13="","",YEAR(C13)) -> 2025 | F13: https://www.instagram.com/reel/DI37WR7tdJv/?utm_source=ig_web_copy_link&igsh=MzRlODBiNWFlZA== | G13: Reel | H13: Yes | I13: Admissions | J13: Student Experience | K13: Emotional Storytelling | L13: No | M13: 3952 | N13: 56 | O13: his is the moment when @dentistrywithdal found out she was #UofTBound! 💙 She’ll be attending @uoftdentistry this fall. We’re so excited to have you at #UofT, @daliaprovad!
... A17: UOT016 | B17: University of Toronto | C17: 45809 | D17: =IF(C17="","",TEXT(C17,"mmmm")) -> June | E17: =IF(C17="","",YEAR(C17)) -> 2025 | F17: https://www.instagram.com/reel/DKXIit-OuyH/?utm_source=ig_web_copy_link&igsh=MzRlODBiNWFlZA== | G17: Reel | H17: Yes | I17: Alumni Success | J17: Campus Life | K17: Community Engagement | L17: Yes | M17: 606 | N17: 8 | O17: We asked, you answered. Your @UofT memories, old and new, gave us all the feels. 💙 This year at #UofTReunion, alumni across all three campuses celebrated every moment, big and small. Thank you to our alumni and friends for bringing the energy (and the stories)!
A18: UOT017 | B18: University of Toronto | C18: 45825 | D18: June | E18: 2025 | F18: https://www.instagram.com/p/DLAZUomgiBI/?utm_source=ig_web_copy_link&igsh=MzRlODBiNWFlZA== | G18: Image | H18: Yes | I18: Academic Programs | J18: Research & Innovation | K18: Promotional | L18: Yes | M18: 625 | N18: 8 | O18: Becoming ‘AI-ready’: #UofT’s task force on artificial intelligence releases recommendations. The task force’s report aims to establish U of T as a post-secondary leader in its implementation of AI across its operations. Learn more at our link in bio or at uoft.me/aitf.
A19: UOT018 | B19: University of Toronto | C19: 45832 | D19: =IF(C19="","",TEXT(C19,"mmmm")) -> June | E19: =IF(C19="","",YEAR(C19)) -> 2025 | F19: https://www.instagram.com/reel/DLSfp-YAoOW/?utm_source=ig_web_copy_link&igsh=MzRlODBiNWFlZA== | G19: Reel | H19: Yes | I19: Diversity & Inclusion | J19: Student Experience | K19: Informational | L19: No | M19: 366 | N19: 26 | O19: The Black Students’ Association celebrated #UofT’s Class of 2025 at @harthouseuoft earlier this month. The annual, student-run “Black Grad” celebration recognizes the resilience, diversity & academic accomplishments of Black students graduating from U of T’s three campuses. 🎉 #UofTGrad25
A20: UOT019 | B20: University of Toronto | C20: 45842 | D20: =IF(C20="","",TEXT(C20,"mmmm")) -> July | E20: =IF(C20="","",YEAR(C20)) -> 2025 | F20: https://www.instagram.com/reel/DLsRmpdA1zs/?utm_source=ig_web_copy_link&igsh=MzRlODBiNWFlZA== | G20: Reel | H20: Yes | I20: Events | J20: Other | K20: Promotional | L20: Yes | M20: 323 | N20: 7 | O20: #UofT took centre stage at the first ever Toronto Tech Week this year. Some of the most renowned names in AI and other cutting-edge fields, from Nobel laureate Geoffrey Hinton to self-driving whiz Raquel Urtasun, were featured in panel discussions, fireside chats, startup demos and other events from June 23-27.
A21: UOT020 | B21: University of Toronto | C21: 45847 | D21: =IF(C21="","",TEXT(C21,"mmmm")) -> July | E21: =IF(C21="","",YEAR(C21)) -> 2025 | F21: https://www.instagram.com/p/DL5NrRFNftG/?utm_source=ig_web_copy_link&igsh=MzRlODBiNWFlZA== | G21: Image | H21: Yes | I21: Student Experience | J21: Career Opportunities | K21: Promotional | L21: Yes | M21: 512 | N21: 10 | O21: What happens when passion meets purpose? @oiseuoft student Shezadi Khushal’s #UofT journey is driven by a deep commitment to equity in education. Now, she’s working to make the system better for everyone.
A22: UOT021 | B22: University of Toronto | C22: 45856 | D22: =IF(C22="","",TEXT(C22,"mmmm")) -> July | E22: =IF(C22="","",YEAR(C22)) -> 2025 | F22: https://www.instagram.com/reel/DMQN3rzucXD/?utm_source=ig_web_copy_link&igsh=MzRlODBiNWFlZA== | G22: Reel | H22: Yes | I22: Campus Facilities | J22: Rankings & Achievements | K22: Reputation Building | L22: Yes | M22: 1132 | N22: 14 | O22: What does the future of dental education look like? From analog tools to advanced tech, #UofT Dentistry’s training spaces have come a long way.
A23: UOT022 | B23: University of Toronto | C23: 45877 | D23: =IF(C23="","",TEXT(C23,"mmmm")) -> August | E23: =IF(C23="","",YEAR(C23)) -> 2025 | F23: https://www.instagram.com/p/DNGc3jhRA7u/?utm_source=ig_web_copy_link&igsh=MzRlODBiNWFlZA== | G23: Image | H23: Yes | I23: Campus Life | J23: Campus Facilities | K23: Informational | L23: Yes | M23: 3763 | N23: 29 | O23: New #UofT students – the countdown is on! 💙 There are tons of ways to get involved and kick off your university journey across all three campuses. Check out these resources as you start your new journey with confidence ⬇️
A24: UOT023 | B24: University of Toronto | C24: 45891 | D24: =IF(C24="","",TEXT(C24,"mmmm")) -> August | E24: =IF(C24="","",YEAR(C24)) -> 2025 | F24: https://www.instagram.com/reel/DNqgCcQx-uw/?utm_source=ig_web_copy_link&igsh=MzRlODBiNWFlZA== | G24: Reel | H24: Yes | I24: Student Experience | J24: Campus Life | K24: Promotional | L24: Yes | M24: 657 | N24: 8 | O24: PART 1 📚 We asked #UofT students to share some tips on things they wish they knew before starting university? 🤔💙 #MyUofT
A25: UOT024 | B25: University of Toronto | C25: 45895 | D25: =IF(C25="","",TEXT(C25,"mmmm")) -> August | E25: =IF(C25="","",YEAR(C25)) -> 2025 | F25: https://www.instagram.com/reel/DN1FAXx3g0g/?utm_source=ig_web_copy_link&igsh=MzRlODBiNWFlZA== | G25: Reel | H25: Yes | I25: Academic Programs | J25: Admissions | K25: Promotional | L25: Yes | M25: 2766 | N25: 23 | O25: Guess which nursing school is ranked first in Canada and fourth in the world? @uoftnursing is leading the way, from award-winning research and a state-of-the-art simulation lab to groundbreaking programs and placements at Canada’s top health-care institutions. Watch student Morayo Aladejana walk us through why Bloomberg Nursing is best in class.
A26: UOT025 | B26: University of Toronto | C26: 45539 | D26: =IF(C26="","",TEXT(C26,"mmmm")) -> September | E26: =IF(C26="","",YEAR(C26)) -> 2024 | F26: https://www.instagram.com/reel/C_gAY05uOuR/?utm_source=ig_web_copy_link&igsh=MzRlODBiNWFlZA== | G26: Reel | H26: Yes | I26: Alumni Success | J26: Campus Life | K26: Emotional Storytelling | L26: No | M26: 1134 | N26: 29 | O26: Who remembers their first day at #UofT like it was yesterday? It’s certainly top of mind for #UofTalumni Ali Kehl, @viccollege’s campus life coordinator, because it’s now her job to help undergrads settle in and get involved. As Vic celebrates 100 years of student engagement in 2024, we asked Ali to share her favourite spots around the college she still calls home.
A27: UOT026 | B27: University of Toronto | C27: 45558 | D27: =IF(C27="","",TEXT(C27,"mmmm")) -> September | E27: =IF(C27="","",YEAR(C27)) -> 2024 | F27: https://www.instagram.com/p/DARSyHePe8t/?utm_source=ig_web_copy_link&igsh=MzRlODBiNWFlZA== | G27: Image | H27: Yes | I27: Scholarships & Financial Aid | J27: Campus Facilities | K27: Informational | L27: Yes | M27: 2430 | N27: 9 | O27: A $25-million gift from Myron and Berna Garron will contribute to the construction of a new state-of-the-art facility at UTSC that will house the Scarborough Academy of Medicine and Integrated Health (SAMIH). @uoft will name the new building the Myron and Berna Garron Health Sciences Complex, in honour of the Garrons’ exceptional generosity.
A28: UOT027 | B28: University of Toronto | C28: 45561 | D28: =IF(C28="","",TEXT(C28,"mmmm")) -> September | E28: =IF(C28="","",YEAR(C28)) -> 2024 | F28: https://www.instagram.com/reel/DAYquplxdS_/?utm_source=ig_web_copy_link&igsh=MzRlODBiNWFlZA== | G28: Reel | H28: Yes | I28: Student Experience | J28: International Students | K28: Promotional | L28: Yes | M28: 2380 | N28: 33 | O28: From why they chose #UofT to making the most of your first year — international students share their experiences 💙 #UofTBackToSchool
A29: UOT028 | B29: University of Toronto | C29: 45567 | D29: =IF(C29="","",TEXT(C29,"mmmm")) -> October | E29: =IF(C29="","",YEAR(C29)) -> 2024 | F29: https://www.instagram.com/reel/DAoiZorSwTY/?utm_source=ig_web_copy_link&igsh=MzRlODBiNWFlZA== | G29: Reel | H29: Yes | I29: Student Experience | J29: International Students | K29: Promotional | L29: Yes | M29: 1095 | N29: 37 | O29: Screening across #UofT this fall is a documentary that highlights the journey of international students to our three campuses. International Students: First 48 Hours in Canada is a 22-minute film directed by Cal Campos, capturing the excitement and challenges of packing, traveling, and finally setting foot on each campus.
A30: UOT029 | B30: University of Toronto | C30: 45581 | D30: =IF(C30="","",TEXT(C30,"mmmm")) -> October | E30: =IF(C30="","",YEAR(C30)) -> 2024 | F30: https://www.instagram.com/p/DBMdpOWSbwV/?utm_source=ig_web_copy_link&igsh=MzRlODBiNWFlZA== | G30: Image | H30: Yes | I30: Rankings & Achievements | J30: Academic Programs | K30: Informational | L30: Yes | M30: 4695 | N30: 37 | O30: #UofT is once again first in Canada and 21st globally in the prestigious World Reputation Rankings by @timeshighered 🌎 The ranking assesses schools across five broad pillars: teaching, research environment, research quality, industry and international outlook.
... A87: YRK014 | B87: York University | C87: 45797 | D87: =IF(C87="","",TEXT(C87,"mmmm")) -> May | E87: =IF(C87="","",YEAR(C87)) -> 2025 | F87: https://www.instagram.com/reel/DJ4ynQPyisG/?utm_source=ig_web_copy_link&igsh=MzRlODBiNWFlZA== | G87: Reel | H87: Yes | I87: Student Experience | J87: Student Clubs & Organizations | K87: Community Engagement | L87: Yes | M87: 294 | N87: 6 | O87: York U Lions X @Raptors takeover and the IBM Practice Court 🏀
A88: YRK015 | B88: York University | C88: 45792 | D88: =IF(C88="","",TEXT(C88,"mmmm")) -> May | E88: =IF(C88="","",YEAR(C88)) -> 2025 | F88: https://www.instagram.com/reel/DJrwYjfR7po/?utm_source=ig_web_copy_link&igsh=MzRlODBiNWFlZA== | G88: Reel | H88: Yes | I88: Alumni Success | J88: Rankings & Achievements | K88: Inspirational | L88: No | M88: NA | N88: NA | O88: Congratulations to York’s 2025 Top 30 Alumni Under 30 recipients! This group of remarkable young alumni are making a global impact and inspiring the next generation of leaders. #YorkUTop30 #YorkU
A89: YRK016 | B89: York University | C89: 45825 | D89: =IF(C89="","",TEXT(C89,"mmmm")) -> June | E89: =IF(C89="","",YEAR(C89)) -> 2025 | F89: https://www.instagram.com/p/DLAfCO8R2aT/?utm_source=ig_web_copy_link&igsh=MzRlODBiNWFlZA== | G89: Image | H89: Yes | I89: Student Experience | J89: Events | K89: Inspirational | L89: No | M89: 1217 | N89: 10 | O89: Meet Aila Narimani, this year’s recipient of York U’s prestigious Murray G. Ross Award! From student governance to global advocacy, Aila’s impact has been profound, and now she’s setting her sights on a future in dentistry rooted in care and accessibility. |
A90: YRK017 | B90: York University | C90: 45827 | D90: =IF(C90="","",TEXT(C90,"mmmm")) -> June | E90: =IF(C90="","",YEAR(C90)) -> 2025 | F90: https://www.instagram.com/reel/DLFiIXNAgBU/?utm_source=ig_web_copy_link&igsh=MzRlODBiNWFlZA== | G90: Reel | H90: Yes | I90: Student Experience | J90: International Students | K90: Inspirational | L90: No | M90: 404 | N90: 26 | O90: From Congo to Canada, one father’s dream became a family legacy. Learn more about the Serufuli family and their shared journey of resilience and education. Since 2018, eight of the nine siblings have attended Glendon Campus at York U | #YorkUConvo
A91: YRK018 | B91: York University | C91: 45833 | D91: =IF(C91="","",TEXT(C91,"mmmm")) -> June | E91: =IF(C91="","",YEAR(C91)) -> 2025 | F91: https://www.instagram.com/reel/DLU1-pxg3ow/?utm_source=ig_web_copy_link&igsh=MzRlODBiNWFlZA== | G91: Reel | H91: Yes | I91: Student Experience | J91: Rankings & Achievements | K91: Emotional Storytelling | L91: No | M91: 1150 | N91: 13 | O91: Former Raptors head coach Nick Nurse received an honorary doctorate at convocation last week! Hear what he had to share with the class of 2025! | #YorkUConvo @thenicknurse
A92: YRK019 | B92: York University | C92: 45862 | D92: =IF(C92="","",TEXT(C92,"mmmm")) -> July | E92: =IF(C92="","",YEAR(C92)) -> 2025 | F92: https://www.instagram.com/p/DMfqtIdO7SA/?utm_source=ig_web_copy_link&igsh=MzRlODBiNWFlZA== | G92: Carousel | H92: Yes | I92: Campus Facilities | J92: Campus Life | K92: Emotional Storytelling | L92: No | M92: 1110 | N92: 5 | O92: ow It Started vs. How It's Going: Sobeys Stadium at York U is the home of Canada's top tennis tournament, the National Bank Open, which begins this weekend! The stadium was built to replace the old National Tennis Centre, which was located on the north east side of Keele Campus, and was demolished in 2003.
A93: YRK020 | B93: York University | C93: 45867 | D93: =IF(C93="","",TEXT(C93,"mmmm")) -> July | E93: =IF(C93="","",YEAR(C93)) -> 2025 | F93: https://www.instagram.com/reel/DMs8Xn-xUHs/?utm_source=ig_web_copy_link&igsh=MzRlODBiNWFlZA== | G93: Reel | H93: Yes | I93: Campus Facilities | J93: Academic Programs | K93: Promotional | L93: No | M93: 1370 | N93: 34 | O93: York U celebrates another milestone with the unveiling of a new sign for the future School of Medicine building next to Cortellucci Vaughan Hospital, and signed a partnership with the Ontario Centre of Innovation toward fostering health-care innovation. | #YorkUMedicine
A94: YRK021 | B94: York University | C94: 45868 | D94: =IF(C94="","",TEXT(C94,"mmmm")) -> July | E94: =IF(C94="","",YEAR(C94)) -> 2025 | F94: https://www.instagram.com/p/DMvOVgiOTNg/?utm_source=ig_web_copy_link&igsh=MzRlODBiNWFlZA== | G94: Image | H94: Yes | I94: Student Experience | J94: Campus Life | K94: Community Engagement | L94: Yes | M94: 713 | N94: 19 | O94: There’s something special about the bonds formed on campus, like an unlikely friendship between a lion and a raptor. Tag your York U bestie in the comments. | #InternationalFriendshipDay
A95: YRK022 | B95: York University | C95: 45895 | D95: =IF(C95="","",TEXT(C95,"mmmm")) -> August | E95: =IF(C95="","",YEAR(C95)) -> 2025 | F95: https://www.instagram.com/reel/DN0iBFT5BpY/?utm_source=ig_web_copy_link&igsh=MzRlODBiNWFlZA== | G95: Reel | H95: Yes | I95: Campus Life | J95: Student Experience | K95: Community Engagement | L95: Yes | M95: 342 | N95: 7 | O95: eady to meet like-minded individuals and get ready for campus life? Make the beginning of your year memorable by joining the many orientation events happening at York U this week!
A96: YRK023 | B96: York University | C96: 45897 | D96: =IF(C96="","",TEXT(C96,"mmmm")) -> August | E96: =IF(C96="","",YEAR(C96)) -> 2025 | F96: https://www.instagram.com/reel/DN6Uxvwipn-/?utm_source=ig_web_copy_link&igsh=MzRlODBiNWFlZA== | G96: Reel | H96: Yes | I96: Campus Life | J96: Campus Facilities | K96: Community Engagement | L96: Yes | M96: 1550 | N96: 14 | O96: Move-In Day at York University was a huge success! We welcomed over 1400 student residents across all three campuses. Thank you to the York U community for helping make our new lions feel safe, supported, and at home. 📦 | #StartStrongYU
A97: YRK024 | B97: York University | C97: 45876 | D97: =IF(C97="","",TEXT(C97,"mmmm")) -> August | E97: =IF(C97="","",YEAR(C97)) -> 2025 | F97: https://www.instagram.com/reel/DNDnHcTBTUm/?utm_source=ig_web_copy_link&igsh=MzRlODBiNWFlZA== | G97: Reel | H97: Yes | I97: Campus Life | J97: Student Experience | K97: Emotional Storytelling | L97: No | M97: 535 | N97: 13 | O97: Incoming students, we are excited to welcome you to our York U campuses this September. Until then, we hope you are enjoying the summer.
A98: YRK025 | B98: York University | C98: 45541 | D98: =IF(C98="","",TEXT(C98,"mmmm")) -> September | E98: =IF(C98="","",YEAR(C98)) -> 2024 | F98: https://www.instagram.com/reel/C_lcsTASsB0/?utm_source=ig_web_copy_link&igsh=MzRlODBiNWFlZA== | G98: Reel | H98: Yes | I98: Campus Life | J98: Events | K98: Community Engagement | L98: No | M98: 1824 | N98: 20 | O98: We had a fantastic time at our orientation week events alongside our incoming first year students! We can’t wait to make more memories together this school year, Lions! 🦁 📓 | #YorkU #StartStrongYU
A99: YRK026 | B99: York University | C99: 45548 | D99: =IF(C99="","",TEXT(C99,"mmmm")) -> September | E99: =IF(C99="","",YEAR(C99)) -> 2024 | F99: https://www.instagram.com/reel/C_3purKy9fS/?utm_source=ig_web_copy_link&igsh=MzRlODBiNWFlZA== | G99: Reel | H99: Yes | I99: Student Experience | J99: Academic Programs | K99: Student Testimonial | L99: Yes | M99: 1013 | N99: 32 | O99: We checked in with York U students to find out what programs they are taking and here are their choices! Let us know what program you are taking in the comments below. 📚💻 | #StartStrongYU #YorkU
A100: YRK027 | B100: York University | C100: 45554 | D100: =IF(C100="","",TEXT(C100,"mmmm")) -> September | E100: =IF(C100="","",YEAR(C100)) -> 2024 | F100: https://www.instagram.com/reel/DAG5_60RhGS/?utm_source=ig_web_copy_link&igsh=MzRlODBiNWFlZA== | G100: Reel | H100: Yes | I100: Student Experience | J100: Campus Life | K100: Student Testimonial | L100: Yes | M100: 420 | N100: 36 | O100: We asked the York student community: What are you looking forward to most this school year? Here’s what they had to say! How about you? Let us know in the comments below. 📚💻 | #StartStrongYU #YorkU
... A160: WAT015 | B160: University of Waterloo | C160: 45800 | D160: =IF(C160="","",TEXT(C160,"mmmm")) -> May | E160: =IF(C160="","",YEAR(C160)) -> 2025 | F160: https://www.instagram.com/reel/DJ_3Y_wO8sv/?utm_source=ig_web_copy_link&igsh=MzRlODBiNWFlZA== | G160: Reel | H160: Yes | I160: Academic Programs | J160: Research & Innovation | K160: Reputation Building | L160: Yes | M160: 189 | N160: 2 | O160: Now, researchers at the Institute for Quantum Computing (IQC) at the University of Waterloo and quantum software provider softwareQ Inc have developed one of the world’s first quantum resource estimation tools to calculate the realistic costs of quantum attacks and how to use quantum computers effectively.
A161: WAT016 | B161: University of Waterloo | C161: 45813 | D161: =IF(C161="","",TEXT(C161,"mmmm")) -> June | E161: =IF(C161="","",YEAR(C161)) -> 2025 | F161: https://www.instagram.com/p/DKh08q2xUoq/?utm_source=ig_web_copy_link&igsh=MzRlODBiNWFlZA== | G161: Carousel | H161: Yes | I161: Student Experience | J161: Student Clubs & Organizations | K161: Community Engagement | L161: Yes | M161: NA | N161: NA | O161: Twenty-five #UWaterlooSci students took part in a four-day Traditional Medicines Land-Based Field Course in Havelock, Ontario, near Alderville First Nation Reserve.⁣ Led entirely by Indigenous Elders and facilitators, the course offered a powerful opportunity to learn through land-based teachings, oral traditions, and cultural practices.⁣
A162: WAT017 | B162: University of Waterloo | C162: 45818 | D162: =IF(C162="","",TEXT(C162,"mmmm")) -> June | E162: =IF(C162="","",YEAR(C162)) -> 2025 | F162: https://www.instagram.com/reel/DKuUPnXOwWn/?utm_source=ig_web_copy_link&igsh=MzRlODBiNWFlZA== | G162: Reel | H162: Yes | I162: Student Experience | J162: Events | K162: Community Engagement | L162: No | M162: 683 | N162: 14 | O162: Our 14 valedictorians share words of advice ahead of Spring 2025 Convocation. Congratulations to these superb graduates and to all who are crossing the stage this week inside of the PAC. You made it!
A163: WAT018 | B163: University of Waterloo | C163: 45829 | D163: =IF(C163="","",TEXT(C163,"mmmm")) -> June | E163: =IF(C163="","",YEAR(C163)) -> 2025 | F163: https://www.instagram.com/p/DLKl2HHg3fa/?utm_source=ig_web_copy_link&igsh=MzRlODBiNWFlZA== | G163: Image | H163: Yes | I163: Student Experience | J163: Career Opportunities | K163: Emotional Storytelling | L163: Yes | M163: 395 | N163: 4 | O163: Meijie Lin joined the Faculty of Environment with experience in financial accounting and a growing interest in climate action. At Waterloo, she explored what drives emissions changes and whether they stem from real decarbonization or outside influences.
A164: WAT019 | B164: University of Waterloo | C164: 45840 | D164: =IF(C164="","",TEXT(C164,"mmmm")) -> July | E164: =IF(C164="","",YEAR(C164)) -> 2025 | F164: https://www.instagram.com/reel/DLm1Ow2u-mt/?utm_source=ig_web_copy_link&igsh=MzRlODBiNWFlZA== | G164: Reel | H164: Yes | I164: Research & Innovation | J164: Academic Programs | K164: Reputation Building | L164: Yes | M164: 287 | N164: 4 | O164: Waterloo researchers are developing a material that mimics the behaviour of human bone and is capable of being 3D printed with a high degree of accuracy.
A165: WAT020 | B165: University of Waterloo | C165: 45856 | D165: =IF(C165="","",TEXT(C165,"mmmm")) -> July | E165: =IF(C165="","",YEAR(C165)) -> 2025 | F165: https://www.instagram.com/p/DMQNhIguEFQ/?utm_source=ig_web_copy_link&igsh=MzRlODBiNWFlZA== | G165: Carousel | H165: Yes | I165: Campus Facilities | J165: Diversity & Inclusion | K165: Emotional Storytelling | L165: No | M165: 3451 | N165: 26 | O165: Taking a trip back in time to look at some iconic buildings and moments across campus at #UWaterloo. 🖤💛
A166: WAT021 | B166: University of Waterloo | C166: 45864 | D166: =IF(C166="","",TEXT(C166,"mmmm")) -> July | E166: =IF(C166="","",YEAR(C166)) -> 2025 | F166: https://www.instagram.com/p/DMkullhs2qW/?utm_source=ig_web_copy_link&igsh=MzRlODBiNWFlZA== | G166: Image | H166: Yes | I166: Student Experience | J166: Research & Innovation | K166: Student Testimonial | L166: Yes | M166: 507 | N166: 6 | O166: Now a master’s student in Systems Design Engineering, Kseniia is developing AI that improves action recognition in ice hockey broadcasts.
A167: WAT022 | B167: University of Waterloo | C167: 45884 | D167: =IF(C167="","",TEXT(C167,"mmmm")) -> August | E167: =IF(C167="","",YEAR(C167)) -> 2025 | F167: https://www.instagram.com/reel/DNYXTbXOUdr/?utm_source=ig_web_copy_link&igsh=MzRlODBiNWFlZA== | G167: Reel | H167: Yes | I167: Student Experience | J167: Career Opportunities | K167: Student Testimonial | L167: Yes | M167: 286 | N167: 5 | O167: After being turned away from 15 salons, Aileen Agada (BASc ‘21, MBET ‘24) co-founded @beblended.inc, an online marketplace connecting people with Afro-curly hair to trained stylists. 💇🏾‍♀️
A168: WAT023 | B168: University of Waterloo | C168: 45888 | D168: =IF(C168="","",TEXT(C168,"mmmm")) -> August | E168: =IF(C168="","",YEAR(C168)) -> 2025 | F168: https://www.instagram.com/reel/DNjCzoahx8e/?utm_source=ig_web_copy_link&igsh=MzRlODBiNWFlZA== | G168: Reel | H168: Yes | I168: Student Experience | J168: Campus Life | K168: Community Engagement | L168: Yes | M168: 750 | N168: 3 | O168: Recreation program registration opens September 3rd! Sign up for fitness classes, aquatics, intramurals, and more! Visit gowarriorsgo.ca/fall2025 for more info! Mark your calendars! 🖤💛 Black & Gold Day - Sep 6th 🏠 Open House - Sep 9th 🎉 Homecoming - Sep 20th
A169: WAT024 | B169: University of Waterloo | C169: 45894 | D169: =IF(C169="","",TEXT(C169,"mmmm")) -> August | E169: =IF(C169="","",YEAR(C169)) -> 2025 | F169: https://www.instagram.com/reel/DNx8SoUXNYT/?utm_source=ig_web_copy_link&igsh=MzRlODBiNWFlZA== | G169: Reel | H169: Yes | I169: Career Opportunities | J169: Scholarships & Financial Aid | K169: Reputation Building | L169: Yes | M169: 247 | N169: 4 | O169: Since 1958, #UWaterloo has distinguished itself with co-operative education. Today, more than 70% of our students gain up to two years of employment experience during their studies.
A170: WAT025 | B170: University of Waterloo | C170: 45542 | D170: =IF(C170="","",TEXT(C170,"mmmm")) -> September | E170: =IF(C170="","",YEAR(C170)) -> 2024 | F170: https://www.instagram.com/p/C_nnI1DAw6s/?utm_source=ig_web_copy_link&igsh=MzRlODBiNWFlZA== | G170: Image | H170: Yes | I170: Student Experience | J170: Academic Programs | K170: Student Testimonial | L170: Yes | M170: NA | N170: NA | O170: Nithin Aaron is a theorist at heart, currently studying quantum computing as a Master of Science in Physics (Quantum Information) student. After researching graduate programs around the world, it was ultimately the reputation of the Institute for Quantum Computing (IQC) and the excellent fit he found with his supervisor professor Pierre-Nicholas Roy (Tier 1 Canada Research Chair in Quantum Molecular Dynamics), that finalized his decision to come to Waterloo.
A171: WAT026 | B171: University of Waterloo | C171: 45544 | D171: =IF(C171="","",TEXT(C171,"mmmm")) -> September | E171: =IF(C171="","",YEAR(C171)) -> 2024 | F171: https://www.instagram.com/reel/C_symnqulBZ/?utm_source=ig_web_copy_link&igsh=MzRlODBiNWFlZA== | G171: Reel | H171: Yes | I171: Academic Programs | J171: Scholarships & Financial Aid | K171: Promotional | L171: Yes | M171: 463 | N171: 7 | O171: The University of Waterloo is proud to welcome a new cohort of science, technology, engineering and math (STEM) students through the Schulich Leader Scholarship program. 👏👏👏
A172: WAT027 | B172: University of Waterloo | C172: 45554 | D172: =IF(C172="","",TEXT(C172,"mmmm")) -> September | E172: =IF(C172="","",YEAR(C172)) -> 2024 | F172: https://www.instagram.com/p/DAGrt7qg9L-/?utm_source=ig_web_copy_link&igsh=MzRlODBiNWFlZA== | G172: Image | H172: Yes | I172: Research & Innovation | J172: Scholarships & Financial Aid | K172: Student Testimonial | L172: Yes | M172: 707 | N172: 5 | O172: uofwaterloo mechatronics engineering student Mulei Mao’s latest entrepreneurial venture promotes healthy snacking. He’s developing a protein-packed popcorn topping that’s nutritious, sustainable — and delicious! [@Likes]
A173: WAT028 | B173: University of Waterloo | C173: 45569 | D173: =IF(C173="","",TEXT(C173,"mmmm")) -> October | E173: =IF(C173="","",YEAR(C173)) -> 2024 | F173: https://www.instagram.com/p/DAt36OXvU6x/?utm_source=ig_web_copy_link&igsh=MzRlODBiNWFlZA== | G173: Carousel | H173: Yes | I173: Rankings & Achievements | J173: Research & Innovation | K173: Reputation Building | L173: No | M173: 1038 | N173: 6 | O173: 📈#UWaterloo has been ranked 25th in the world on the @fastcompany inaugural Ignition Schools list, recognizing the top 50 universities worldwide that are driving innovation and entrepreneurship. Waterloo is also the third-highest ranked Canadian university. 👏👏👏
A174: WAT029 | B174: University of Waterloo | C174: 45574 | D174: =IF(C174="","",TEXT(C174,"mmmm")) -> October | E174: =IF(C174="","",YEAR(C174)) -> 2024 | F174: https://www.instagram.com/p/DA6VFW6v9mj/?utm_source=ig_web_copy_link&igsh=MzRlODBiNWFlZA== | G174: Carousel | H174: Yes | I174: Career Opportunities | J174: International Students | K174: Promotional | L174: Yes | M174: 993 | N174: 10 | O174: his groundbreaking study provides a clearer view of how successful international students are once they complete their studies across Canadian post-secondary schools, notably in technology and engineering-focused programs where they enjoy and earnings advantage over their peers.
A175: WAT030 | B175: University of Waterloo | C175: 45586 | D175: =IF(C175="","",TEXT(C175,"mmmm")) -> October | E175: =IF(C175="","",YEAR(C175)) -> 2024 | F175: https://www.instagram.com/reel/DBZFVJoxaBX/?utm_source=ig_web_copy_link&igsh=MzRlODBiNWFlZA== | G175: Reel | H175: Yes | I175: Academic Programs | J175: Student Experience | K175: Promotional | L175: Yes | M175: 343 | N175: 4 | O175: Discover the elegance of Pure Mathematics at the University of Waterloo! Our Pure Mathematics major is perfect for those driven by a passion for exploring the depths of mathematics for its own sake. Immerse yourself in centuries of mathematical theory, and see how geometry, algebra, and functions intertwine. If you seek to experience the beauty of math in its purest form, this is the program for you.
A176: WAT031 | B176: University of Waterloo | C176: 45608 | D176: =IF(C176="","",TEXT(C176,"mmmm")) -> November | E176: =IF(C176="","",YEAR(C176)) -> 2024 | F176: https://www.instagram.com/reel/DCSEPUiRVWc/?utm_source=ig_web_copy_link&igsh=MzRlODBiNWFlZA== | G176: Reel | H176: Yes | I176: Admissions | J176: Events | K176: Promotional | L176: Yes | M176: 660 | N176: 11 | O176: Thank you to everyone who joined us for our Fall Open House! 🍂 We loved connecting with future Warriors and sharing what makes Waterloo special. Ready to take the next step? Learn how to apply through the link in our bio! 💼✨
A177: WAT032 | B177: University of Waterloo | C177: 45615 | D177: =IF(C177="","",TEXT(C177,"mmmm")) -> November | E177: =IF(C177="","",YEAR(C177)) -> 2024 | F177: https://www.instagram.com/p/DCj9NIivVzc/?utm_source=ig_web_copy_link&igsh=MzRlODBiNWFlZA== | G177: Carousel | H177: Yes | I177: Rankings & Achievements | J177: Research & Innovation | K177: Reputation Building | L177: No | M177: 4466 | N177: 17 | O177: e University of Waterloo has solidified its position as a global research leader in the 2024 Academic Ranking of World Universities (ARWU), with seven subjects ranking #1 in Canada and 19 subjects in the top 100 worldwide.
A178: WAT033 | B178: University of Waterloo | C178: 45622 | D178: =IF(C178="","",TEXT(C178,"mmmm")) -> November | E178: =IF(C178="","",YEAR(C178)) -> 2024 | F178: https://www.instagram.com/p/DC2THIIssR4/?utm_source=ig_web_copy_link&igsh=MzRlODBiNWFlZA== | G178: Image | H178: Yes | I178: Rankings & Achievements | J178: Student Experience | K178: Student Testimonial | L178: Yes | M178: 218 | N178: 2 | O178: Last Wednesday, @greenhouse held their 33rd Social Impact Showcase at United College, highlighting the impressive achievements of student-led ventures tackling some of the world’s most pressing social challenges.
A179: WAT034 | B179: University of Waterloo | C179: 45629 | D179: =IF(C179="","",TEXT(C179,"mmmm")) -> December | E179: =IF(C179="","",YEAR(C179)) -> 2024 | F179: https://www.instagram.com/reel/DDH-iWtxyaN/?utm_source=ig_web_copy_link&igsh=MzRlODBiNWFlZA== | G179: Reel | H179: Yes | I179: Admissions | J179: Academic Programs | K179: Promotional | L179: Yes | M179: 804 | N179: 7 | O179: Don’t be like David—don’t wait until it’s too late! ⏳ The application deadline is January 31st. (Engineering applicants, excluding Architecture, your deadline is January 15th!) Sprint to the link in our bio and apply today!
A180: WAT035 | B180: University of Waterloo | C180: 45642 | D180: =IF(C180="","",TEXT(C180,"mmmm")) -> December | E180: =IF(C180="","",YEAR(C180)) -> 2024 | F180: https://www.instagram.com/p/DDphNWTPtFH/?utm_source=ig_web_copy_link&igsh=MzRlODBiNWFlZA== | G180: Image | H180: Yes | I180: Rankings & Achievements | J180: Research & Innovation | K180: Reputation Building | L180: Yes | M180: 1602 | N180: 3 | O180: We’re thrilled to share that #UWaterloo has been ranked in the top 10% of universities worldwide and 5th in 🇨🇦 for brand recognition in the Global University Visibility rankings developed by @americancaldwell . 🙌
A181: WAT036 | B181: University of Waterloo | C181: 45643 | D181: =IF(C181="","",TEXT(C181,"mmmm")) -> December | E181: =IF(C181="","",YEAR(C181)) -> 2024 | F181: https://www.instagram.com/reel/DDr9iB5x87v/?utm_source=ig_web_copy_link&igsh=MzRlODBiNWFlZA== | G181: Reel | H181: Yes | I181: Academic Programs | J181: Admissions | K181: Promotional | L181: Yes | M181: 485 | N181: 37 | O181: Looking for a career in one of the business world’s most in-demand fields? Our Financial Analysis and Risk Management (FARM) degree equips you with the skills to manage credit, operational, market, and financial risks—opening doors to dynamic, high-profile roles. Hear from students and instructors about why this program might be the perfect fit for you!

Sheet Lists
A1: University of Toronto | B1: Image | C1: Yes | D1: Academic Programs | E1: Informational
A2: McMaster University | B2: Carousel | C2: No | D2: Admissions | E2: Promotional
A3: York University | B3: Reel | D3: Student Experience | E3: Emotional Storytelling
A4: Toronto Metropolitan University | B4: Video | D4: Campus Life | E4: Student Testimonial
A5: University of Waterloo | D5: Scholarships & Financial Aid | E5: Reputation Building
D6: Career Opportunities | E6: Community Engagement
D7: Research & Innovation | E7: Call-to-Action
D8: Student Support Services | E8: Inspirational
D9: Campus Facilities
D10: Diversity & Inclusion
D11: International Students
D12: Student Clubs & Organizations
D13: Events
D14: Rankings & Achievements
D15: Alumni Success

Sheet Analysis Data
A1: Post ID | B1: University | C1: Post Date | D1: Month | E1: Year | F1: Instagram URL | G1: Post Type | H1: Recruitment-Oriented? | I1: Primary Theme | J1: Secondary Theme | K1: Marketing Approach | L1: CTA Present? | M1: Likes | N1: Comments | O1: Caption Summary | P1: Primary Theme Group | Q1: Secondary Theme Group | R1: Approach Group | S1: Duplicate ID Check | T1: Duplicate URL Check | U1: Date Check | V1: Record Note
A2: UOT001 | B2: University of Toronto | C2: 45677 | D2: =IF(C2="","",TEXT(C2,"mmmm")) -> January | E2: =IF(C2="","",YEAR(C2)) -> 2025 | F2: https://www.instagram.com/reel/DFDbR9zSpaG/?utm_source=ig_web_copy_link&igsh=MzRlODBiNWFlZA== | G2: Reel | H2: Yes | I2: Student Experience | J2: Campus Life | K2: Emotional Storytelling | L2: Yes | M2: 574 | N2: 17 | O2: We’re asking @uoftmedicine & @uoftrunclub’s Emily Nguyen about her rapid fire faves at #UofT! Have you seen our first #MyUofT video? Be sure to check it out! | P2: =IF(OR(I2="Student Experience",I2="Campus Life",I2="Campus Facilities",I2="Student Clubs & Organizations",I2="Events",I2="Student Support Services",I2="Diversity & Inclusion",I2="International Students"),"Student Experience & Campus",IF(OR(I2="Academic Programs",I2="Admissions",I2="Scholarships & Financial Aid"),"Academic & Admissions",IF(OR(I2="Career Opportunities",I2="Alumni Success"),"Career & Alumni",IF(I2="Research & Innovation","Research & Innovation",IF(I2="Rankings & Achievements","Institutional Reputation","Other"))))) -> Student Experience & Campus | Q2: =IF(OR(J2="Student Experience",J2="Campus Life",J2="Campus Facilities",J2="Student Clubs & Organizations",J2="Events",J2="Student Support Services",J2="Diversity & Inclusion",J2="International Students"),"Student Experience & Campus",IF(OR(J2="Academic Programs",J2="Admissions",J2="Scholarships & Financial Aid"),"Academic & Admissions",IF(OR(J2="Career Opportunities",J2="Alumni Success"),"Career & Alumni",IF(J2="Research & Innovation","Research & Innovation",IF(J2="Rankings & Achievements","Institutional Reputation","Other"))))) -> Student Experience & Campus | R2: =IF(K2="Informational","Informational",IF(OR(K2="Promotional",K2="Call-to-Action"),"Promotional/Conversion",IF(K2="Reputation Building","Reputation-focused","Engagement/Relationship"))) -> Engagement/Relationship | S2: =IF(COUNTIF($A$2:$A$181,A2)>1,"Duplicate","OK") -> OK | T2: =IF(COUNTIF($F$2:$F$181,F2)>1,"Duplicate","OK") -> OK | U2: =IF(AND(TEXT(C2,"mmmm")=D2,YEAR(C2)=E2),"OK","Mismatch") -> OK | V2: =IF(OR(M2="NA",N2="NA"),"Likes/comments unavailable",IF(I2=J2,"Primary and secondary themes identical","OK")) -> OK
A3: UOT002 | B3: University of Toronto | C3: 45684 | D3: January | E3: =IF(C3="","",YEAR(C3)) -> 2025 | F3: https://www.instagram.com/p/DFV2mHuyw7n/?utm_source=ig_web_copy_link&igsh=MzRlODBiNWFlZA== | G3: Image | H3: Yes | I3: Rankings & Achievements | J3: Academic Programs | K3: Reputation Building | L3: Yes | M3: 1513 | N3: 17 | O3: #UofT ranked first in Canada in all 11 subjects tracked by Times Higher Education’s World University Rankings by Subject 2025 – and is one of only six universities in the world to rank in the top 30 across the board. 🍁 | P3: =IF(OR(I3="Student Experience",I3="Campus Life",I3="Campus Facilities",I3="Student Clubs & Organizations",I3="Events",I3="Student Support Services",I3="Diversity & Inclusion",I3="International Students"),"Student Experience & Campus",IF(OR(I3="Academic Programs",I3="Admissions",I3="Scholarships & Financial Aid"),"Academic & Admissions",IF(OR(I3="Career Opportunities",I3="Alumni Success"),"Career & Alumni",IF(I3="Research & Innovation","Research & Innovation",IF(I3="Rankings & Achievements","Institutional Reputation","Other"))))) -> Institutional Reputation | Q3: =IF(OR(J3="Student Experience",J3="Campus Life",J3="Campus Facilities",J3="Student Clubs & Organizations",J3="Events",J3="Student Support Services",J3="Diversity & Inclusion",J3="International Students"),"Student Experience & Campus",IF(OR(J3="Academic Programs",J3="Admissions",J3="Scholarships & Financial Aid"),"Academic & Admissions",IF(OR(J3="Career Opportunities",J3="Alumni Success"),"Career & Alumni",IF(J3="Research & Innovation","Research & Innovation",IF(J3="Rankings & Achievements","Institutional Reputation","Other"))))) -> Academic & Admissions | R3: =IF(K3="Informational","Informational",IF(OR(K3="Promotional",K3="Call-to-Action"),"Promotional/Conversion",IF(K3="Reputation Building","Reputation-focused","Engagement/Relationship"))) -> Reputation-focused | S3: =IF(COUNTIF($A$2:$A$181,A3)>1,"Duplicate","OK") -> OK | T3: =IF(COUNTIF($F$2:$F$181,F3)>1,"Duplicate","OK") -> OK | U3: =IF(AND(TEXT(C3,"mmmm")=D3,YEAR(C3)=E3),"OK","Mismatch") -> OK | V3: =IF(OR(M3="NA",N3="NA"),"Likes/comments unavailable",IF(I3=J3,"Primary and secondary themes identical","OK")) -> OK
A4: UOT003 | B4: University of Toronto | C4: 45687 | D4: January | E4: 2025 | F4: https://www.instagram.com/reel/DFdo9ZNv8UA/?utm_source=ig_web_copy_link&igsh=MzRlODBiNWFlZA== | G4: Reel | H4: Yes | I4: Alumni Success | J4: Events | K4: Community Engagement | L4: Yes | M4: 248 | N4: 3 | O4: What if sharing your expertise could spark a positive change? With more than 23,000 #UofTalumni already stepping up as mentors and volunteers, our #UofT community is powered by the passion and dedication of our grads. | P4: =IF(OR(I4="Student Experience",I4="Campus Life",I4="Campus Facilities",I4="Student Clubs & Organizations",I4="Events",I4="Student Support Services",I4="Diversity & Inclusion",I4="International Students"),"Student Experience & Campus",IF(OR(I4="Academic Programs",I4="Admissions",I4="Scholarships & Financial Aid"),"Academic & Admissions",IF(OR(I4="Career Opportunities",I4="Alumni Success"),"Career & Alumni",IF(I4="Research & Innovation","Research & Innovation",IF(I4="Rankings & Achievements","Institutional Reputation","Other"))))) -> Career & Alumni | Q4: =IF(OR(J4="Student Experience",J4="Campus Life",J4="Campus Facilities",J4="Student Clubs & Organizations",J4="Events",J4="Student Support Services",J4="Diversity & Inclusion",J4="International Students"),"Student Experience & Campus",IF(OR(J4="Academic Programs",J4="Admissions",J4="Scholarships & Financial Aid"),"Academic & Admissions",IF(OR(J4="Career Opportunities",J4="Alumni Success"),"Career & Alumni",IF(J4="Research & Innovation","Research & Innovation",IF(J4="Rankings & Achievements","Institutional Reputation","Other"))))) -> Student Experience & Campus | R4: =IF(K4="Informational","Informational",IF(OR(K4="Promotional",K4="Call-to-Action"),"Promotional/Conversion",IF(K4="Reputation Building","Reputation-focused","Engagement/Relationship"))) -> Engagement/Relationship | S4: =IF(COUNTIF($A$2:$A$181,A4)>1,"Duplicate","OK") -> OK | T4: =IF(COUNTIF($F$2:$F$181,F4)>1,"Duplicate","OK") -> OK | U4: =IF(AND(TEXT(C4,"mmmm")=D4,YEAR(C4)=E4),"OK","Mismatch") -> OK | V4: =IF(OR(M4="NA",N4="NA"),"Likes/comments unavailable",IF(I4=J4,"Primary and secondary themes identical","OK")) -> OK
A5: UOT004 | B5: University of Toronto | C5: 45693 | D5: February | E5: 2025 | F5: https://www.instagram.com/p/DFtOatUykUC/?utm_source=ig_web_copy_link&igsh=MzRlODBiNWFlZA== | G5: Image | H5: Yes | I5: Research & Innovation | J5: Rankings & Achievements | K5: Reputation Building | L5: Yes | M5: 1031 | N5: 16 | O5: #UofT is among the world’s top 10 universities powering global innovation in critical areas like technology, health care, sustainability and economic development, according to international data analytics company Clarivate. | P5: =IF(OR(I5="Student Experience",I5="Campus Life",I5="Campus Facilities",I5="Student Clubs & Organizations",I5="Events",I5="Student Support Services",I5="Diversity & Inclusion",I5="International Students"),"Student Experience & Campus",IF(OR(I5="Academic Programs",I5="Admissions",I5="Scholarships & Financial Aid"),"Academic & Admissions",IF(OR(I5="Career Opportunities",I5="Alumni Success"),"Career & Alumni",IF(I5="Research & Innovation","Research & Innovation",IF(I5="Rankings & Achievements","Institutional Reputation","Other"))))) -> Research & Innovation | Q5: =IF(OR(J5="Student Experience",J5="Campus Life",J5="Campus Facilities",J5="Student Clubs & Organizations",J5="Events",J5="Student Support Services",J5="Diversity & Inclusion",J5="International Students"),"Student Experience & Campus",IF(OR(J5="Academic Programs",J5="Admissions",J5="Scholarships & Financial Aid"),"Academic & Admissions",IF(OR(J5="Career Opportunities",J5="Alumni Success"),"Career & Alumni",IF(J5="Research & Innovation","Research & Innovation",IF(J5="Rankings & Achievements","Institutional Reputation","Other"))))) -> Institutional Reputation | R5: =IF(K5="Informational","Informational",IF(OR(K5="Promotional",K5="Call-to-Action"),"Promotional/Conversion",IF(K5="Reputation Building","Reputation-focused","Engagement/Relationship"))) -> Reputation-focused | S5: =IF(COUNTIF($A$2:$A$181,A5)>1,"Duplicate","OK") -> OK | T5: =IF(COUNTIF($F$2:$F$181,F5)>1,"Duplicate","OK") -> OK | U5: =IF(AND(TEXT(C5,"mmmm")=D5,YEAR(C5)=E5),"OK","Mismatch") -> OK | V5: =IF(OR(M5="NA",N5="NA"),"Likes/comments unavailable",IF(I5=J5,"Primary and secondary themes identical","OK")) -> OK
A6: UOT005 | B6: University of Toronto | C6: 45699 | D6: February | E6: 2025 | F6: https://www.instagram.com/reel/DF8FBerRF8m/?utm_source=ig_web_copy_link&igsh=MzRlODBiNWFlZA== | G6: Reel | H6: Yes | I6: Student Experience | J6: Campus Life | K6: Student Testimonial | L6: Yes | M6: 2628 | N6: 33 | O6: A day in the life of a @uoftims & #UofT PhD student, @sciencewithsajee! | P6: =IF(OR(I6="Student Experience",I6="Campus Life",I6="Campus Facilities",I6="Student Clubs & Organizations",I6="Events",I6="Student Support Services",I6="Diversity & Inclusion",I6="International Students"),"Student Experience & Campus",IF(OR(I6="Academic Programs",I6="Admissions",I6="Scholarships & Financial Aid"),"Academic & Admissions",IF(OR(I6="Career Opportunities",I6="Alumni Success"),"Career & Alumni",IF(I6="Research & Innovation","Research & Innovation",IF(I6="Rankings & Achievements","Institutional Reputation","Other"))))) -> Student Experience & Campus | Q6: =IF(OR(J6="Student Experience",J6="Campus Life",J6="Campus Facilities",J6="Student Clubs & Organizations",J6="Events",J6="Student Support Services",J6="Diversity & Inclusion",J6="International Students"),"Student Experience & Campus",IF(OR(J6="Academic Programs",J6="Admissions",J6="Scholarships & Financial Aid"),"Academic & Admissions",IF(OR(J6="Career Opportunities",J6="Alumni Success"),"Career & Alumni",IF(J6="Research & Innovation","Research & Innovation",IF(J6="Rankings & Achievements","Institutional Reputation","Other"))))) -> Student Experience & Campus | R6: =IF(K6="Informational","Informational",IF(OR(K6="Promotional",K6="Call-to-Action"),"Promotional/Conversion",IF(K6="Reputation Building","Reputation-focused","Engagement/Relationship"))) -> Engagement/Relationship | S6: =IF(COUNTIF($A$2:$A$181,A6)>1,"Duplicate","OK") -> OK | T6: =IF(COUNTIF($F$2:$F$181,F6)>1,"Duplicate","OK") -> OK | U6: =IF(AND(TEXT(C6,"mmmm")=D6,YEAR(C6)=E6),"OK","Mismatch") -> OK | V6: =IF(OR(M6="NA",N6="NA"),"Likes/comments unavailable",IF(I6=J6,"Primary and secondary themes identical","OK")) -> OK
A7: UOT006 | B7: University of Toronto | C7: 45702 | D7: February | E7: 2025 | F7: https://www.instagram.com/p/DGDu9TwRvKz/?utm_source=ig_web_copy_link&igsh=MzRlODBiNWFlZA== | G7: Carousel | H7: Yes | I7: Diversity & Inclusion | J7: Research & Innovation | K7: Emotional Storytelling | L7: Yes | M7: 1516 | N7: 9 | O7: Diagnosed with autism, he couldn’t speak or signal his thoughts. But everything changed when he learned to communicate through a letter board. What followed stunned his family. Now, he is helping #UofT neuroscientist Morgan Barense with her research @uoftpsychology using brain scans into non-speaking autism. | P7: =IF(OR(I7="Student Experience",I7="Campus Life",I7="Campus Facilities",I7="Student Clubs & Organizations",I7="Events",I7="Student Support Services",I7="Diversity & Inclusion",I7="International Students"),"Student Experience & Campus",IF(OR(I7="Academic Programs",I7="Admissions",I7="Scholarships & Financial Aid"),"Academic & Admissions",IF(OR(I7="Career Opportunities",I7="Alumni Success"),"Career & Alumni",IF(I7="Research & Innovation","Research & Innovation",IF(I7="Rankings & Achievements","Institutional Reputation","Other"))))) -> Student Experience & Campus | Q7: =IF(OR(J7="Student Experience",J7="Campus Life",J7="Campus Facilities",J7="Student Clubs & Organizations",J7="Events",J7="Student Support Services",J7="Diversity & Inclusion",J7="International Students"),"Student Experience & Campus",IF(OR(J7="Academic Programs",J7="Admissions",J7="Scholarships & Financial Aid"),"Academic & Admissions",IF(OR(J7="Career Opportunities",J7="Alumni Success"),"Career & Alumni",IF(J7="Research & Innovation","Research & Innovation",IF(J7="Rankings & Achievements","Institutional Reputation","Other"))))) -> Research & Innovation | R7: =IF(K7="Informational","Informational",IF(OR(K7="Promotional",K7="Call-to-Action"),"Promotional/Conversion",IF(K7="Reputation Building","Reputation-focused","Engagement/Relationship"))) -> Engagement/Relationship | S7: =IF(COUNTIF($A$2:$A$181,A7)>1,"Duplicate","OK") -> OK | T7: =IF(COUNTIF($F$2:$F$181,F7)>1,"Duplicate","OK") -> OK | U7: =IF(AND(TEXT(C7,"mmmm")=D7,YEAR(C7)=E7),"OK","Mismatch") -> OK | V7: =IF(OR(M7="NA",N7="NA"),"Likes/comments unavailable",IF(I7=J7,"Primary and secondary themes identical","OK")) -> OK
A8: UOT007 | B8: University of Toronto | C8: 45729 | D8: March | E8: 2025 | F8: https://www.instagram.com/reel/DHJab1PRh1X/?utm_source=ig_web_copy_link&igsh=MzRlODBiNWFlZA== | G8: Reel | H8: Yes | I8: Alumni Success | J8: Events | K8: Community Engagement | L8: Yes | M8: 1047 | N8: 73 | O8: This is @uoftstartup’s #UofTEntWeek, founder style! Follow #UofT alumna & Toothpod founder @vishar.y as she explores everything U of T Entrepreneurship has to offer, including her personal advice on getting started. | P8: =IF(OR(I8="Student Experience",I8="Campus Life",I8="Campus Facilities",I8="Student Clubs & Organizations",I8="Events",I8="Student Support Services",I8="Diversity & Inclusion",I8="International Students"),"Student Experience & Campus",IF(OR(I8="Academic Programs",I8="Admissions",I8="Scholarships & Financial Aid"),"Academic & Admissions",IF(OR(I8="Career Opportunities",I8="Alumni Success"),"Career & Alumni",IF(I8="Research & Innovation","Research & Innovation",IF(I8="Rankings & Achievements","Institutional Reputation","Other"))))) -> Career & Alumni | Q8: =IF(OR(J8="Student Experience",J8="Campus Life",J8="Campus Facilities",J8="Student Clubs & Organizations",J8="Events",J8="Student Support Services",J8="Diversity & Inclusion",J8="International Students"),"Student Experience & Campus",IF(OR(J8="Academic Programs",J8="Admissions",J8="Scholarships & Financial Aid"),"Academic & Admissions",IF(OR(J8="Career Opportunities",J8="Alumni Success"),"Career & Alumni",IF(J8="Research & Innovation","Research & Innovation",IF(J8="Rankings & Achievements","Institutional Reputation","Other"))))) -> Student Experience & Campus | R8: =IF(K8="Informational","Informational",IF(OR(K8="Promotional",K8="Call-to-Action"),"Promotional/Conversion",IF(K8="Reputation Building","Reputation-focused","Engagement/Relationship"))) -> Engagement/Relationship | S8: =IF(COUNTIF($A$2:$A$181,A8)>1,"Duplicate","OK") -> OK | T8: =IF(COUNTIF($F$2:$F$181,F8)>1,"Duplicate","OK") -> OK | U8: =IF(AND(TEXT(C8,"mmmm")=D8,YEAR(C8)=E8),"OK","Mismatch") -> OK | V8: =IF(OR(M8="NA",N8="NA"),"Likes/comments unavailable",IF(I8=J8,"Primary and secondary themes identical","OK")) -> OK
A9: UOT008 | B9: University of Toronto | C9: 45733 | D9: March | E9: 2025 | F9: https://www.instagram.com/reel/DHT7iTYxaMb/?utm_source=ig_web_copy_link&igsh=MzRlODBiNWFlZA== | G9: Reel | H9: Yes | I9: Diversity & Inclusion | J9: Alumni Success | K9: Inspirational | L9: No | M9: 2463 | N9: 59 | O9: 11 languages? 🤯 Recent #UofT alumni and hyperpolyglot @xinyi_limx shows us her appreciation for the diversity and rich culture that Toronto has to offer. #MyUofT | P9: =IF(OR(I9="Student Experience",I9="Campus Life",I9="Campus Facilities",I9="Student Clubs & Organizations",I9="Events",I9="Student Support Services",I9="Diversity & Inclusion",I9="International Students"),"Student Experience & Campus",IF(OR(I9="Academic Programs",I9="Admissions",I9="Scholarships & Financial Aid"),"Academic & Admissions",IF(OR(I9="Career Opportunities",I9="Alumni Success"),"Career & Alumni",IF(I9="Research & Innovation","Research & Innovation",IF(I9="Rankings & Achievements","Institutional Reputation","Other"))))) -> Student Experience & Campus | Q9: =IF(OR(J9="Student Experience",J9="Campus Life",J9="Campus Facilities",J9="Student Clubs & Organizations",J9="Events",J9="Student Support Services",J9="Diversity & Inclusion",J9="International Students"),"Student Experience & Campus",IF(OR(J9="Academic Programs",J9="Admissions",J9="Scholarships & Financial Aid"),"Academic & Admissions",IF(OR(J9="Career Opportunities",J9="Alumni Success"),"Career & Alumni",IF(J9="Research & Innovation","Research & Innovation",IF(J9="Rankings & Achievements","Institutional Reputation","Other"))))) -> Career & Alumni | R9: =IF(K9="Informational","Informational",IF(OR(K9="Promotional",K9="Call-to-Action"),"Promotional/Conversion",IF(K9="Reputation Building","Reputation-focused","Engagement/Relationship"))) -> Engagement/Relationship | S9: =IF(COUNTIF($A$2:$A$181,A9)>1,"Duplicate","OK") -> OK | T9: =IF(COUNTIF($F$2:$F$181,F9)>1,"Duplicate","OK") -> OK | U9: =IF(AND(TEXT(C9,"mmmm")=D9,YEAR(C9)=E9),"OK","Mismatch") -> OK | V9: =IF(OR(M9="NA",N9="NA"),"Likes/comments unavailable",IF(I9=J9,"Primary and secondary themes identical","OK")) -> OK
A10: UOT009 | B10: University of Toronto | C10: 45736 | D10: March | E10: 2025 | F10: https://www.instagram.com/reel/DHbOdPjyScp/?utm_source=ig_web_copy_link&igsh=MzRlODBiNWFlZA== | G10: Reel | H10: Yes | I10: Admissions | J10: Student Support Services | K10: Call-to-Action | L10: Yes | M10: 537 | N10: 11 | O10: Did you get an acceptance letter from #UofT? Congratulations! 🎉 We want to see your excitement to start your journey with us next year! DM us or post a video with #UofTBound tagging @futureuoft, @uoft and your campus @utsc or @uoftmississauga for your chance to be featured on our accounts! | P10: =IF(OR(I10="Student Experience",I10="Campus Life",I10="Campus Facilities",I10="Student Clubs & Organizations",I10="Events",I10="Student Support Services",I10="Diversity & Inclusion",I10="International Students"),"Student Experience & Campus",IF(OR(I10="Academic Programs",I10="Admissions",I10="Scholarships & Financial Aid"),"Academic & Admissions",IF(OR(I10="Career Opportunities",I10="Alumni Success"),"Career & Alumni",IF(I10="Research & Innovation","Research & Innovation",IF(I10="Rankings & Achievements","Institutional Reputation","Other"))))) -> Academic & Admissions | Q10: =IF(OR(J10="Student Experience",J10="Campus Life",J10="Campus Facilities",J10="Student Clubs & Organizations",J10="Events",J10="Student Support Services",J10="Diversity & Inclusion",J10="International Students"),"Student Experience & Campus",IF(OR(J10="Academic Programs",J10="Admissions",J10="Scholarships & Financial Aid"),"Academic & Admissions",IF(OR(J10="Career Opportunities",J10="Alumni Success"),"Career & Alumni",IF(J10="Research & Innovation","Research & Innovation",IF(J10="Rankings & Achievements","Institutional Reputation","Other"))))) -> Student Experience & Campus | R10: =IF(K10="Informational","Informational",IF(OR(K10="Promotional",K10="Call-to-Action"),"Promotional/Conversion",IF(K10="Reputation Building","Reputation-focused","Engagement/Relationship"))) -> Promotional/Conversion | S10: =IF(COUNTIF($A$2:$A$181,A10)>1,"Duplicate","OK") -> OK | T10: =IF(COUNTIF($F$2:$F$181,F10)>1,"Duplicate","OK") -> OK | U10: =IF(AND(TEXT(C10,"mmmm")=D10,YEAR(C10)=E10),"OK","Mismatch") -> OK | V10: =IF(OR(M10="NA",N10="NA"),"Likes/comments unavailable",IF(I10=J10,"Primary and secondary themes identical","OK")) -> OK
A11: UOT010 | B11: University of Toronto | C11: 45748 | D11: April | E11: 2025 | F11: https://www.instagram.com/p/DH6YEVQOf-Z/?utm_source=ig_web_copy_link&igsh=MzRlODBiNWFlZA== | G11: Carousel | H11: Yes | I11: Admissions | J11: Academic Programs | K11: Promotional | L11: Yes | M11: 2233 | N11: 20 | O11: #UTM March Open House was a memorable day filled with opportunities! 💙 . | P11: =IF(OR(I11="Student Experience",I11="Campus Life",I11="Campus Facilities",I11="Student Clubs & Organizations",I11="Events",I11="Student Support Services",I11="Diversity & Inclusion",I11="International Students"),"Student Experience & Campus",IF(OR(I11="Academic Programs",I11="Admissions",I11="Scholarships & Financial Aid"),"Academic & Admissions",IF(OR(I11="Career Opportunities",I11="Alumni Success"),"Career & Alumni",IF(I11="Research & Innovation","Research & Innovation",IF(I11="Rankings & Achievements","Institutional Reputation","Other"))))) -> Academic & Admissions | Q11: =IF(OR(J11="Student Experience",J11="Campus Life",J11="Campus Facilities",J11="Student Clubs & Organizations",J11="Events",J11="Student Support Services",J11="Diversity & Inclusion",J11="International Students"),"Student Experience & Campus",IF(OR(J11="Academic Programs",J11="Admissions",J11="Scholarships & Financial Aid"),"Academic & Admissions",IF(OR(J11="Career Opportunities",J11="Alumni Success"),"Career & Alumni",IF(J11="Research & Innovation","Research & Innovation",IF(J11="Rankings & Achievements","Institutional Reputation","Other"))))) -> Academic & Admissions | R11: =IF(K11="Informational","Informational",IF(OR(K11="Promotional",K11="Call-to-Action"),"Promotional/Conversion",IF(K11="Reputation Building","Reputation-focused","Engagement/Relationship"))) -> Promotional/Conversion | S11: =IF(COUNTIF($A$2:$A$181,A11)>1,"Duplicate","OK") -> OK | T11: =IF(COUNTIF($F$2:$F$181,F11)>1,"Duplicate","OK") -> OK | U11: =IF(AND(TEXT(C11,"mmmm")=D11,YEAR(C11)=E11),"OK","Mismatch") -> OK | V11: =IF(OR(M11="NA",N11="NA"),"Likes/comments unavailable",IF(I11=J11,"Primary and secondary themes identical","OK")) -> OK
A12: UOT011 | B12: University of Toronto | C12: 45751 | D12: =IF(C12="","",TEXT(C12,"mmmm")) -> April | E12: =IF(C12="","",YEAR(C12)) -> 2025 | F12: https://www.instagram.com/reel/DIB-jGhRYlB/?utm_source=ig_web_copy_link&igsh=MzRlODBiNWFlZA== | G12: Reel | H12: Yes | I12: Campus Facilities | J12: Student Experience | K12: Emotional Storytelling | L12: Yes | M12: 1645 | N12: 14 | O12: After being named #UofT’s 17th president on March 26, Melanie Woodin met with students, staff, faculty and senior leaders across U of T’s three campuses during a whirlwind two-day tour. 💙 | P12: =IF(OR(I12="Student Experience",I12="Campus Life",I12="Campus Facilities",I12="Student Clubs & Organizations",I12="Events",I12="Student Support Services",I12="Diversity & Inclusion",I12="International Students"),"Student Experience & Campus",IF(OR(I12="Academic Programs",I12="Admissions",I12="Scholarships & Financial Aid"),"Academic & Admissions",IF(OR(I12="Career Opportunities",I12="Alumni Success"),"Career & Alumni",IF(I12="Research & Innovation","Research & Innovation",IF(I12="Rankings & Achievements","Institutional Reputation","Other"))))) -> Student Experience & Campus | Q12: =IF(OR(J12="Student Experience",J12="Campus Life",J12="Campus Facilities",J12="Student Clubs & Organizations",J12="Events",J12="Student Support Services",J12="Diversity & Inclusion",J12="International Students"),"Student Experience & Campus",IF(OR(J12="Academic Programs",J12="Admissions",J12="Scholarships & Financial Aid"),"Academic & Admissions",IF(OR(J12="Career Opportunities",J12="Alumni Success"),"Career & Alumni",IF(J12="Research & Innovation","Research & Innovation",IF(J12="Rankings & Achievements","Institutional Reputation","Other"))))) -> Student Experience & Campus | R12: =IF(K12="Informational","Informational",IF(OR(K12="Promotional",K12="Call-to-Action"),"Promotional/Conversion",IF(K12="Reputation Building","Reputation-focused","Engagement/Relationship"))) -> Engagement/Relationship | S12: =IF(COUNTIF($A$2:$A$181,A12)>1,"Duplicate","OK") -> OK | T12: =IF(COUNTIF($F$2:$F$181,F12)>1,"Duplicate","OK") -> OK | U12: =IF(AND(TEXT(C12,"mmmm")=D12,YEAR(C12)=E12),"OK","Mismatch") -> OK | V12: =IF(OR(M12="NA",N12="NA"),"Likes/comments unavailable",IF(I12=J12,"Primary and secondary themes identical","OK")) -> OK
A13: UOT012 | B13: University of Toronto | C13: 45772 | D13: April | E13: 2025 | F13: https://www.instagram.com/reel/DI37WR7tdJv/?utm_source=ig_web_copy_link&igsh=MzRlODBiNWFlZA== | G13: Reel | H13: Yes | I13: Admissions | J13: Student Experience | K13: Emotional Storytelling | L13: No | M13: 3952 | N13: 56 | O13: his is the moment when @dentistrywithdal found out she was #UofTBound! 💙 She’ll be attending @uoftdentistry this fall. We’re so excited to have you at #UofT, @daliaprovad! | P13: =IF(OR(I13="Student Experience",I13="Campus Life",I13="Campus Facilities",I13="Student Clubs & Organizations",I13="Events",I13="Student Support Services",I13="Diversity & Inclusion",I13="International Students"),"Student Experience & Campus",IF(OR(I13="Academic Programs",I13="Admissions",I13="Scholarships & Financial Aid"),"Academic & Admissions",IF(OR(I13="Career Opportunities",I13="Alumni Success"),"Career & Alumni",IF(I13="Research & Innovation","Research & Innovation",IF(I13="Rankings & Achievements","Institutional Reputation","Other"))))) -> Academic & Admissions | Q13: =IF(OR(J13="Student Experience",J13="Campus Life",J13="Campus Facilities",J13="Student Clubs & Organizations",J13="Events",J13="Student Support Services",J13="Diversity & Inclusion",J13="International Students"),"Student Experience & Campus",IF(OR(J13="Academic Programs",J13="Admissions",J13="Scholarships & Financial Aid"),"Academic & Admissions",IF(OR(J13="Career Opportunities",J13="Alumni Success"),"Career & Alumni",IF(J13="Research & Innovation","Research & Innovation",IF(J13="Rankings & Achievements","Institutional Reputation","Other"))))) -> Student Experience & Campus | R13: =IF(K13="Informational","Informational",IF(OR(K13="Promotional",K13="Call-to-Action"),"Promotional/Conversion",IF(K13="Reputation Building","Reputation-focused","Engagement/Relationship"))) -> Engagement/Relationship | S13: =IF(COUNTIF($A$2:$A$181,A13)>1,"Duplicate","OK") -> OK | T13: =IF(COUNTIF($F$2:$F$181,F13)>1,"Duplicate","OK") -> OK | U13: =IF(AND(TEXT(C13,"mmmm")=D13,YEAR(C13)=E13),"OK","Mismatch") -> OK | V13: =IF(OR(M13="NA",N13="NA"),"Likes/comments unavailable",IF(I13=J13,"Primary and secondary themes identical","OK")) -> OK
A14: UOT013 | B14: University of Toronto | C14: 45783 | D14: May | E14: 2025 | F14: https://www.instagram.com/reel/DJUeIo4Jy8I/?utm_source=ig_web_copy_link&igsh=MzRlODBiNWFlZA== | G14: Reel | H14: Yes | I14: Events | J14: Student Experience | K14: Emotional Storytelling | L14: Yes | M14: 3672 | N14: 59 | O14: s spring begins to bloom in southern Ontario, thousands of students from across #UofT’s three campuses are preparing to close their laptops, don gowns and hoods – and walk across the #UofTGrad25 stage in Convocation Hall. 📜 Read the story via our link in bio or at uoft.me/sc25 | P14: =IF(OR(I14="Student Experience",I14="Campus Life",I14="Campus Facilities",I14="Student Clubs & Organizations",I14="Events",I14="Student Support Services",I14="Diversity & Inclusion",I14="International Students"),"Student Experience & Campus",IF(OR(I14="Academic Programs",I14="Admissions",I14="Scholarships & Financial Aid"),"Academic & Admissions",IF(OR(I14="Career Opportunities",I14="Alumni Success"),"Career & Alumni",IF(I14="Research & Innovation","Research & Innovation",IF(I14="Rankings & Achievements","Institutional Reputation","Other"))))) -> Student Experience & Campus | Q14: =IF(OR(J14="Student Experience",J14="Campus Life",J14="Campus Facilities",J14="Student Clubs & Organizations",J14="Events",J14="Student Support Services",J14="Diversity & Inclusion",J14="International Students"),"Student Experience & Campus",IF(OR(J14="Academic Programs",J14="Admissions",J14="Scholarships & Financial Aid"),"Academic & Admissions",IF(OR(J14="Career Opportunities",J14="Alumni Success"),"Career & Alumni",IF(J14="Research & Innovation","Research & Innovation",IF(J14="Rankings & Achievements","Institutional Reputation","Other"))))) -> Student Experience & Campus | R14: =IF(K14="Informational","Informational",IF(OR(K14="Promotional",K14="Call-to-Action"),"Promotional/Conversion",IF(K14="Reputation Building","Reputation-focused","Engagement/Relationship"))) -> Engagement/Relationship | S14: =IF(COUNTIF($A$2:$A$181,A14)>1,"Duplicate","OK") -> OK | T14: =IF(COUNTIF($F$2:$F$181,F14)>1,"Duplicate","OK") -> OK | U14: =IF(AND(TEXT(C14,"mmmm")=D14,YEAR(C14)=E14),"OK","Mismatch") -> OK | V14: =IF(OR(M14="NA",N14="NA"),"Likes/comments unavailable",IF(I14=J14,"Primary and secondary themes identical","OK")) -> OK
A15: UOT014 | B15: University of Toronto | C15: 45792 | D15: May | E15: 2025 | F15: https://www.instagram.com/reel/DJrhRH1t1wM/?utm_source=ig_web_copy_link&igsh=MzRlODBiNWFlZA== | G15: Reel | H15: Yes | I15: Student Experience | J15: Campus Life | K15: Student Testimonial | L15: Yes | M15: 971 | N15: 27 | O15: In this #MyUofT, follow @gabriel_vargas.glz through a day in the life as a 2nd year BBA Co-op Management student at @utsc! As an international student from Mexico, Gabriel shows us his home at Harmony Commons and around #UTSC. 🇲🇽 #UofT | P15: =IF(OR(I15="Student Experience",I15="Campus Life",I15="Campus Facilities",I15="Student Clubs & Organizations",I15="Events",I15="Student Support Services",I15="Diversity & Inclusion",I15="International Students"),"Student Experience & Campus",IF(OR(I15="Academic Programs",I15="Admissions",I15="Scholarships & Financial Aid"),"Academic & Admissions",IF(OR(I15="Career Opportunities",I15="Alumni Success"),"Career & Alumni",IF(I15="Research & Innovation","Research & Innovation",IF(I15="Rankings & Achievements","Institutional Reputation","Other"))))) -> Student Experience & Campus | Q15: =IF(OR(J15="Student Experience",J15="Campus Life",J15="Campus Facilities",J15="Student Clubs & Organizations",J15="Events",J15="Student Support Services",J15="Diversity & Inclusion",J15="International Students"),"Student Experience & Campus",IF(OR(J15="Academic Programs",J15="Admissions",J15="Scholarships & Financial Aid"),"Academic & Admissions",IF(OR(J15="Career Opportunities",J15="Alumni Success"),"Career & Alumni",IF(J15="Research & Innovation","Research & Innovation",IF(J15="Rankings & Achievements","Institutional Reputation","Other"))))) -> Student Experience & Campus | R15: =IF(K15="Informational","Informational",IF(OR(K15="Promotional",K15="Call-to-Action"),"Promotional/Conversion",IF(K15="Reputation Building","Reputation-focused","Engagement/Relationship"))) -> Engagement/Relationship | S15: =IF(COUNTIF($A$2:$A$181,A15)>1,"Duplicate","OK") -> OK | T15: =IF(COUNTIF($F$2:$F$181,F15)>1,"Duplicate","OK") -> OK | U15: =IF(AND(TEXT(C15,"mmmm")=D15,YEAR(C15)=E15),"OK","Mismatch") -> OK | V15: =IF(OR(M15="NA",N15="NA"),"Likes/comments unavailable",IF(I15=J15,"Primary and secondary themes identical","OK")) -> OK
A16: UOT015 | B16: University of Toronto | C16: 45804 | D16: May | E16: 2025 | F16: https://www.instagram.com/p/DKKXdHbtaSE/?utm_source=ig_web_copy_link&igsh=MzRlODBiNWFlZA== | G16: Image | H16: Yes | I16: Student Experience | J16: Academic Programs | K16: Student Testimonial | L16: Yes | M16: 1006 | N16: 9 | O16: Having made the difficult decision to drop out of high school several years earlier, Moosewaypayo entered U of T through the Millie Rotman Shime Academic Bridging Program at @woodsworth.college @uoftartsci, which was recommended to her by a friend. The program allows students who wouldn’t otherwise meet U of T’s admission requirements to qualify for honours bachelor of arts and bachelor of science programs. | P16: =IF(OR(I16="Student Experience",I16="Campus Life",I16="Campus Facilities",I16="Student Clubs & Organizations",I16="Events",I16="Student Support Services",I16="Diversity & Inclusion",I16="International Students"),"Student Experience & Campus",IF(OR(I16="Academic Programs",I16="Admissions",I16="Scholarships & Financial Aid"),"Academic & Admissions",IF(OR(I16="Career Opportunities",I16="Alumni Success"),"Career & Alumni",IF(I16="Research & Innovation","Research & Innovation",IF(I16="Rankings & Achievements","Institutional Reputation","Other"))))) -> Student Experience & Campus | Q16: =IF(OR(J16="Student Experience",J16="Campus Life",J16="Campus Facilities",J16="Student Clubs & Organizations",J16="Events",J16="Student Support Services",J16="Diversity & Inclusion",J16="International Students"),"Student Experience & Campus",IF(OR(J16="Academic Programs",J16="Admissions",J16="Scholarships & Financial Aid"),"Academic & Admissions",IF(OR(J16="Career Opportunities",J16="Alumni Success"),"Career & Alumni",IF(J16="Research & Innovation","Research & Innovation",IF(J16="Rankings & Achievements","Institutional Reputation","Other"))))) -> Academic & Admissions | R16: =IF(K16="Informational","Informational",IF(OR(K16="Promotional",K16="Call-to-Action"),"Promotional/Conversion",IF(K16="Reputation Building","Reputation-focused","Engagement/Relationship"))) -> Engagement/Relationship | S16: =IF(COUNTIF($A$2:$A$181,A16)>1,"Duplicate","OK") -> OK | T16: =IF(COUNTIF($F$2:$F$181,F16)>1,"Duplicate","OK") -> OK | U16: =IF(AND(TEXT(C16,"mmmm")=D16,YEAR(C16)=E16),"OK","Mismatch") -> OK | V16: =IF(OR(M16="NA",N16="NA"),"Likes/comments unavailable",IF(I16=J16,"Primary and secondary themes identical","OK")) -> OK
A17: UOT016 | B17: University of Toronto | C17: 45809 | D17: June | E17: 2025 | F17: https://www.instagram.com/reel/DKXIit-OuyH/?utm_source=ig_web_copy_link&igsh=MzRlODBiNWFlZA== | G17: Reel | H17: Yes | I17: Alumni Success | J17: Campus Life | K17: Community Engagement | L17: Yes | M17: 606 | N17: 8 | O17: We asked, you answered. Your @UofT memories, old and new, gave us all the feels. 💙 This year at #UofTReunion, alumni across all three campuses celebrated every moment, big and small. Thank you to our alumni and friends for bringing the energy (and the stories)! | P17: =IF(OR(I17="Student Experience",I17="Campus Life",I17="Campus Facilities",I17="Student Clubs & Organizations",I17="Events",I17="Student Support Services",I17="Diversity & Inclusion",I17="International Students"),"Student Experience & Campus",IF(OR(I17="Academic Programs",I17="Admissions",I17="Scholarships & Financial Aid"),"Academic & Admissions",IF(OR(I17="Career Opportunities",I17="Alumni Success"),"Career & Alumni",IF(I17="Research & Innovation","Research & Innovation",IF(I17="Rankings & Achievements","Institutional Reputation","Other"))))) -> Career & Alumni | Q17: =IF(OR(J17="Student Experience",J17="Campus Life",J17="Campus Facilities",J17="Student Clubs & Organizations",J17="Events",J17="Student Support Services",J17="Diversity & Inclusion",J17="International Students"),"Student Experience & Campus",IF(OR(J17="Academic Programs",J17="Admissions",J17="Scholarships & Financial Aid"),"Academic & Admissions",IF(OR(J17="Career Opportunities",J17="Alumni Success"),"Career & Alumni",IF(J17="Research & Innovation","Research & Innovation",IF(J17="Rankings & Achievements","Institutional Reputation","Other"))))) -> Student Experience & Campus | R17: =IF(K17="Informational","Informational",IF(OR(K17="Promotional",K17="Call-to-Action"),"Promotional/Conversion",IF(K17="Reputation Building","Reputation-focused","Engagement/Relationship"))) -> Engagement/Relationship | S17: =IF(COUNTIF($A$2:$A$181,A17)>1,"Duplicate","OK") -> OK | T17: =IF(COUNTIF($F$2:$F$181,F17)>1,"Duplicate","OK") -> OK | U17: =IF(AND(TEXT(C17,"mmmm")=D17,YEAR(C17)=E17),"OK","Mismatch") -> OK | V17: =IF(OR(M17="NA",N17="NA"),"Likes/comments unavailable",IF(I17=J17,"Primary and secondary themes identical","OK")) -> OK
A18: UOT017 | B18: University of Toronto | C18: 45825 | D18: June | E18: 2025 | F18: https://www.instagram.com/p/DLAZUomgiBI/?utm_source=ig_web_copy_link&igsh=MzRlODBiNWFlZA== | G18: Image | H18: Yes | I18: Academic Programs | J18: Research & Innovation | K18: Promotional | L18: Yes | M18: 625 | N18: 8 | O18: Becoming ‘AI-ready’: #UofT’s task force on artificial intelligence releases recommendations. The task force’s report aims to establish U of T as a post-secondary leader in its implementation of AI across its operations. Learn more at our link in bio or at uoft.me/aitf. | P18: =IF(OR(I18="Student Experience",I18="Campus Life",I18="Campus Facilities",I18="Student Clubs & Organizations",I18="Events",I18="Student Support Services",I18="Diversity & Inclusion",I18="International Students"),"Student Experience & Campus",IF(OR(I18="Academic Programs",I18="Admissions",I18="Scholarships & Financial Aid"),"Academic & Admissions",IF(OR(I18="Career Opportunities",I18="Alumni Success"),"Career & Alumni",IF(I18="Research & Innovation","Research & Innovation",IF(I18="Rankings & Achievements","Institutional Reputation","Other"))))) -> Academic & Admissions | Q18: =IF(OR(J18="Student Experience",J18="Campus Life",J18="Campus Facilities",J18="Student Clubs & Organizations",J18="Events",J18="Student Support Services",J18="Diversity & Inclusion",J18="International Students"),"Student Experience & Campus",IF(OR(J18="Academic Programs",J18="Admissions",J18="Scholarships & Financial Aid"),"Academic & Admissions",IF(OR(J18="Career Opportunities",J18="Alumni Success"),"Career & Alumni",IF(J18="Research & Innovation","Research & Innovation",IF(J18="Rankings & Achievements","Institutional Reputation","Other"))))) -> Research & Innovation | R18: =IF(K18="Informational","Informational",IF(OR(K18="Promotional",K18="Call-to-Action"),"Promotional/Conversion",IF(K18="Reputation Building","Reputation-focused","Engagement/Relationship"))) -> Promotional/Conversion | S18: =IF(COUNTIF($A$2:$A$181,A18)>1,"Duplicate","OK") -> OK | T18: =IF(COUNTIF($F$2:$F$181,F18)>1,"Duplicate","OK") -> OK | U18: =IF(AND(TEXT(C18,"mmmm")=D18,YEAR(C18)=E18),"OK","Mismatch") -> OK | V18: =IF(OR(M18="NA",N18="NA"),"Likes/comments unavailable",IF(I18=J18,"Primary and secondary themes identical","OK")) -> OK
A19: UOT018 | B19: University of Toronto | C19: 45832 | D19: June | E19: =IF(C19="","",YEAR(C19)) -> 2025 | F19: https://www.instagram.com/reel/DLSfp-YAoOW/?utm_source=ig_web_copy_link&igsh=MzRlODBiNWFlZA== | G19: Reel | H19: Yes | I19: Diversity & Inclusion | J19: Student Experience | K19: Informational | L19: No | M19: 366 | N19: 26 | O19: The Black Students’ Association celebrated #UofT’s Class of 2025 at @harthouseuoft earlier this month. The annual, student-run “Black Grad” celebration recognizes the resilience, diversity & academic accomplishments of Black students graduating from U of T’s three campuses. 🎉 #UofTGrad25 | P19: =IF(OR(I19="Student Experience",I19="Campus Life",I19="Campus Facilities",I19="Student Clubs & Organizations",I19="Events",I19="Student Support Services",I19="Diversity & Inclusion",I19="International Students"),"Student Experience & Campus",IF(OR(I19="Academic Programs",I19="Admissions",I19="Scholarships & Financial Aid"),"Academic & Admissions",IF(OR(I19="Career Opportunities",I19="Alumni Success"),"Career & Alumni",IF(I19="Research & Innovation","Research & Innovation",IF(I19="Rankings & Achievements","Institutional Reputation","Other"))))) -> Student Experience & Campus | Q19: =IF(OR(J19="Student Experience",J19="Campus Life",J19="Campus Facilities",J19="Student Clubs & Organizations",J19="Events",J19="Student Support Services",J19="Diversity & Inclusion",J19="International Students"),"Student Experience & Campus",IF(OR(J19="Academic Programs",J19="Admissions",J19="Scholarships & Financial Aid"),"Academic & Admissions",IF(OR(J19="Career Opportunities",J19="Alumni Success"),"Career & Alumni",IF(J19="Research & Innovation","Research & Innovation",IF(J19="Rankings & Achievements","Institutional Reputation","Other"))))) -> Student Experience & Campus | R19: =IF(K19="Informational","Informational",IF(OR(K19="Promotional",K19="Call-to-Action"),"Promotional/Conversion",IF(K19="Reputation Building","Reputation-focused","Engagement/Relationship"))) -> Informational | S19: =IF(COUNTIF($A$2:$A$181,A19)>1,"Duplicate","OK") -> OK | T19: =IF(COUNTIF($F$2:$F$181,F19)>1,"Duplicate","OK") -> OK | U19: =IF(AND(TEXT(C19,"mmmm")=D19,YEAR(C19)=E19),"OK","Mismatch") -> OK | V19: =IF(OR(M19="NA",N19="NA"),"Likes/comments unavailable",IF(I19=J19,"Primary and secondary themes identical","OK")) -> OK
A20: UOT019 | B20: University of Toronto | C20: 45842 | D20: July | E20: 2025 | F20: https://www.instagram.com/reel/DLsRmpdA1zs/?utm_source=ig_web_copy_link&igsh=MzRlODBiNWFlZA== | G20: Reel | H20: Yes | I20: Events | J20: Other | K20: Promotional | L20: Yes | M20: 323 | N20: 7 | O20: #UofT took centre stage at the first ever Toronto Tech Week this year. Some of the most renowned names in AI and other cutting-edge fields, from Nobel laureate Geoffrey Hinton to self-driving whiz Raquel Urtasun, were featured in panel discussions, fireside chats, startup demos and other events from June 23-27. | P20: =IF(OR(I20="Student Experience",I20="Campus Life",I20="Campus Facilities",I20="Student Clubs & Organizations",I20="Events",I20="Student Support Services",I20="Diversity & Inclusion",I20="International Students"),"Student Experience & Campus",IF(OR(I20="Academic Programs",I20="Admissions",I20="Scholarships & Financial Aid"),"Academic & Admissions",IF(OR(I20="Career Opportunities",I20="Alumni Success"),"Career & Alumni",IF(I20="Research & Innovation","Research & Innovation",IF(I20="Rankings & Achievements","Institutional Reputation","Other"))))) -> Student Experience & Campus | Q20: =IF(OR(J20="Student Experience",J20="Campus Life",J20="Campus Facilities",J20="Student Clubs & Organizations",J20="Events",J20="Student Support Services",J20="Diversity & Inclusion",J20="International Students"),"Student Experience & Campus",IF(OR(J20="Academic Programs",J20="Admissions",J20="Scholarships & Financial Aid"),"Academic & Admissions",IF(OR(J20="Career Opportunities",J20="Alumni Success"),"Career & Alumni",IF(J20="Research & Innovation","Research & Innovation",IF(J20="Rankings & Achievements","Institutional Reputation","Other"))))) -> Other | R20: =IF(K20="Informational","Informational",IF(OR(K20="Promotional",K20="Call-to-Action"),"Promotional/Conversion",IF(K20="Reputation Building","Reputation-focused","Engagement/Relationship"))) -> Promotional/Conversion | S20: =IF(COUNTIF($A$2:$A$181,A20)>1,"Duplicate","OK") -> OK | T20: =IF(COUNTIF($F$2:$F$181,F20)>1,"Duplicate","OK") -> OK | U20: =IF(AND(TEXT(C20,"mmmm")=D20,YEAR(C20)=E20),"OK","Mismatch") -> OK | V20: =IF(OR(M20="NA",N20="NA"),"Likes/comments unavailable",IF(I20=J20,"Primary and secondary themes identical","OK")) -> OK
A21: UOT020 | B21: University of Toronto | C21: 45847 | D21: July | E21: 2025 | F21: https://www.instagram.com/p/DL5NrRFNftG/?utm_source=ig_web_copy_link&igsh=MzRlODBiNWFlZA== | G21: Image | H21: Yes | I21: Student Experience | J21: Career Opportunities | K21: Promotional | L21: Yes | M21: 512 | N21: 10 | O21: What happens when passion meets purpose? @oiseuoft student Shezadi Khushal’s #UofT journey is driven by a deep commitment to equity in education. Now, she’s working to make the system better for everyone. | P21: =IF(OR(I21="Student Experience",I21="Campus Life",I21="Campus Facilities",I21="Student Clubs & Organizations",I21="Events",I21="Student Support Services",I21="Diversity & Inclusion",I21="International Students"),"Student Experience & Campus",IF(OR(I21="Academic Programs",I21="Admissions",I21="Scholarships & Financial Aid"),"Academic & Admissions",IF(OR(I21="Career Opportunities",I21="Alumni Success"),"Career & Alumni",IF(I21="Research & Innovation","Research & Innovation",IF(I21="Rankings & Achievements","Institutional Reputation","Other"))))) -> Student Experience & Campus | Q21: =IF(OR(J21="Student Experience",J21="Campus Life",J21="Campus Facilities",J21="Student Clubs & Organizations",J21="Events",J21="Student Support Services",J21="Diversity & Inclusion",J21="International Students"),"Student Experience & Campus",IF(OR(J21="Academic Programs",J21="Admissions",J21="Scholarships & Financial Aid"),"Academic & Admissions",IF(OR(J21="Career Opportunities",J21="Alumni Success"),"Career & Alumni",IF(J21="Research & Innovation","Research & Innovation",IF(J21="Rankings & Achievements","Institutional Reputation","Other"))))) -> Career & Alumni | R21: =IF(K21="Informational","Informational",IF(OR(K21="Promotional",K21="Call-to-Action"),"Promotional/Conversion",IF(K21="Reputation Building","Reputation-focused","Engagement/Relationship"))) -> Promotional/Conversion | S21: =IF(COUNTIF($A$2:$A$181,A21)>1,"Duplicate","OK") -> OK | T21: =IF(COUNTIF($F$2:$F$181,F21)>1,"Duplicate","OK") -> OK | U21: =IF(AND(TEXT(C21,"mmmm")=D21,YEAR(C21)=E21),"OK","Mismatch") -> OK | V21: =IF(OR(M21="NA",N21="NA"),"Likes/comments unavailable",IF(I21=J21,"Primary and secondary themes identical","OK")) -> OK
A22: UOT021 | B22: University of Toronto | C22: 45856 | D22: July | E22: 2025 | F22: https://www.instagram.com/reel/DMQN3rzucXD/?utm_source=ig_web_copy_link&igsh=MzRlODBiNWFlZA== | G22: Reel | H22: Yes | I22: Campus Facilities | J22: Rankings & Achievements | K22: Reputation Building | L22: Yes | M22: 1132 | N22: 14 | O22: What does the future of dental education look like? From analog tools to advanced tech, #UofT Dentistry’s training spaces have come a long way. | P22: =IF(OR(I22="Student Experience",I22="Campus Life",I22="Campus Facilities",I22="Student Clubs & Organizations",I22="Events",I22="Student Support Services",I22="Diversity & Inclusion",I22="International Students"),"Student Experience & Campus",IF(OR(I22="Academic Programs",I22="Admissions",I22="Scholarships & Financial Aid"),"Academic & Admissions",IF(OR(I22="Career Opportunities",I22="Alumni Success"),"Career & Alumni",IF(I22="Research & Innovation","Research & Innovation",IF(I22="Rankings & Achievements","Institutional Reputation","Other"))))) -> Student Experience & Campus | Q22: =IF(OR(J22="Student Experience",J22="Campus Life",J22="Campus Facilities",J22="Student Clubs & Organizations",J22="Events",J22="Student Support Services",J22="Diversity & Inclusion",J22="International Students"),"Student Experience & Campus",IF(OR(J22="Academic Programs",J22="Admissions",J22="Scholarships & Financial Aid"),"Academic & Admissions",IF(OR(J22="Career Opportunities",J22="Alumni Success"),"Career & Alumni",IF(J22="Research & Innovation","Research & Innovation",IF(J22="Rankings & Achievements","Institutional Reputation","Other"))))) -> Institutional Reputation | R22: =IF(K22="Informational","Informational",IF(OR(K22="Promotional",K22="Call-to-Action"),"Promotional/Conversion",IF(K22="Reputation Building","Reputation-focused","Engagement/Relationship"))) -> Reputation-focused | S22: =IF(COUNTIF($A$2:$A$181,A22)>1,"Duplicate","OK") -> OK | T22: =IF(COUNTIF($F$2:$F$181,F22)>1,"Duplicate","OK") -> OK | U22: =IF(AND(TEXT(C22,"mmmm")=D22,YEAR(C22)=E22),"OK","Mismatch") -> OK | V22: =IF(OR(M22="NA",N22="NA"),"Likes/comments unavailable",IF(I22=J22,"Primary and secondary themes identical","OK")) -> OK
A23: UOT022 | B23: University of Toronto | C23: 45877 | D23: August | E23: 2025 | F23: https://www.instagram.com/p/DNGc3jhRA7u/?utm_source=ig_web_copy_link&igsh=MzRlODBiNWFlZA== | G23: Image | H23: Yes | I23: Campus Life | J23: Campus Facilities | K23: Informational | L23: Yes | M23: 3763 | N23: 29 | O23: New #UofT students – the countdown is on! 💙 There are tons of ways to get involved and kick off your university journey across all three campuses. Check out these resources as you start your new journey with confidence ⬇️ | P23: =IF(OR(I23="Student Experience",I23="Campus Life",I23="Campus Facilities",I23="Student Clubs & Organizations",I23="Events",I23="Student Support Services",I23="Diversity & Inclusion",I23="International Students"),"Student Experience & Campus",IF(OR(I23="Academic Programs",I23="Admissions",I23="Scholarships & Financial Aid"),"Academic & Admissions",IF(OR(I23="Career Opportunities",I23="Alumni Success"),"Career & Alumni",IF(I23="Research & Innovation","Research & Innovation",IF(I23="Rankings & Achievements","Institutional Reputation","Other"))))) -> Student Experience & Campus | Q23: =IF(OR(J23="Student Experience",J23="Campus Life",J23="Campus Facilities",J23="Student Clubs & Organizations",J23="Events",J23="Student Support Services",J23="Diversity & Inclusion",J23="International Students"),"Student Experience & Campus",IF(OR(J23="Academic Programs",J23="Admissions",J23="Scholarships & Financial Aid"),"Academic & Admissions",IF(OR(J23="Career Opportunities",J23="Alumni Success"),"Career & Alumni",IF(J23="Research & Innovation","Research & Innovation",IF(J23="Rankings & Achievements","Institutional Reputation","Other"))))) -> Student Experience & Campus | R23: =IF(K23="Informational","Informational",IF(OR(K23="Promotional",K23="Call-to-Action"),"Promotional/Conversion",IF(K23="Reputation Building","Reputation-focused","Engagement/Relationship"))) -> Informational | S23: =IF(COUNTIF($A$2:$A$181,A23)>1,"Duplicate","OK") -> OK | T23: =IF(COUNTIF($F$2:$F$181,F23)>1,"Duplicate","OK") -> OK | U23: =IF(AND(TEXT(C23,"mmmm")=D23,YEAR(C23)=E23),"OK","Mismatch") -> OK | V23: =IF(OR(M23="NA",N23="NA"),"Likes/comments unavailable",IF(I23=J23,"Primary and secondary themes identical","OK")) -> OK
A24: UOT023 | B24: University of Toronto | C24: 45891 | D24: August | E24: 2025 | F24: https://www.instagram.com/reel/DNqgCcQx-uw/?utm_source=ig_web_copy_link&igsh=MzRlODBiNWFlZA== | G24: Reel | H24: Yes | I24: Student Experience | J24: Campus Life | K24: Promotional | L24: Yes | M24: 657 | N24: 8 | O24: PART 1 📚 We asked #UofT students to share some tips on things they wish they knew before starting university? 🤔💙 #MyUofT | P24: =IF(OR(I24="Student Experience",I24="Campus Life",I24="Campus Facilities",I24="Student Clubs & Organizations",I24="Events",I24="Student Support Services",I24="Diversity & Inclusion",I24="International Students"),"Student Experience & Campus",IF(OR(I24="Academic Programs",I24="Admissions",I24="Scholarships & Financial Aid"),"Academic & Admissions",IF(OR(I24="Career Opportunities",I24="Alumni Success"),"Career & Alumni",IF(I24="Research & Innovation","Research & Innovation",IF(I24="Rankings & Achievements","Institutional Reputation","Other"))))) -> Student Experience & Campus | Q24: =IF(OR(J24="Student Experience",J24="Campus Life",J24="Campus Facilities",J24="Student Clubs & Organizations",J24="Events",J24="Student Support Services",J24="Diversity & Inclusion",J24="International Students"),"Student Experience & Campus",IF(OR(J24="Academic Programs",J24="Admissions",J24="Scholarships & Financial Aid"),"Academic & Admissions",IF(OR(J24="Career Opportunities",J24="Alumni Success"),"Career & Alumni",IF(J24="Research & Innovation","Research & Innovation",IF(J24="Rankings & Achievements","Institutional Reputation","Other"))))) -> Student Experience & Campus | R24: =IF(K24="Informational","Informational",IF(OR(K24="Promotional",K24="Call-to-Action"),"Promotional/Conversion",IF(K24="Reputation Building","Reputation-focused","Engagement/Relationship"))) -> Promotional/Conversion | S24: =IF(COUNTIF($A$2:$A$181,A24)>1,"Duplicate","OK") -> OK | T24: =IF(COUNTIF($F$2:$F$181,F24)>1,"Duplicate","OK") -> OK | U24: =IF(AND(TEXT(C24,"mmmm")=D24,YEAR(C24)=E24),"OK","Mismatch") -> OK | V24: =IF(OR(M24="NA",N24="NA"),"Likes/comments unavailable",IF(I24=J24,"Primary and secondary themes identical","OK")) -> OK
A25: UOT024 | B25: University of Toronto | C25: 45895 | D25: August | E25: 2025 | F25: https://www.instagram.com/reel/DN1FAXx3g0g/?utm_source=ig_web_copy_link&igsh=MzRlODBiNWFlZA== | G25: Reel | H25: Yes | I25: Academic Programs | J25: Admissions | K25: Promotional | L25: Yes | M25: 2766 | N25: 23 | O25: Guess which nursing school is ranked first in Canada and fourth in the world? @uoftnursing is leading the way, from award-winning research and a state-of-the-art simulation lab to groundbreaking programs and placements at Canada’s top health-care institutions. Watch student Morayo Aladejana walk us through why Bloomberg Nursing is best in class. | P25: =IF(OR(I25="Student Experience",I25="Campus Life",I25="Campus Facilities",I25="Student Clubs & Organizations",I25="Events",I25="Student Support Services",I25="Diversity & Inclusion",I25="International Students"),"Student Experience & Campus",IF(OR(I25="Academic Programs",I25="Admissions",I25="Scholarships & Financial Aid"),"Academic & Admissions",IF(OR(I25="Career Opportunities",I25="Alumni Success"),"Career & Alumni",IF(I25="Research & Innovation","Research & Innovation",IF(I25="Rankings & Achievements","Institutional Reputation","Other"))))) -> Academic & Admissions | Q25: =IF(OR(J25="Student Experience",J25="Campus Life",J25="Campus Facilities",J25="Student Clubs & Organizations",J25="Events",J25="Student Support Services",J25="Diversity & Inclusion",J25="International Students"),"Student Experience & Campus",IF(OR(J25="Academic Programs",J25="Admissions",J25="Scholarships & Financial Aid"),"Academic & Admissions",IF(OR(J25="Career Opportunities",J25="Alumni Success"),"Career & Alumni",IF(J25="Research & Innovation","Research & Innovation",IF(J25="Rankings & Achievements","Institutional Reputation","Other"))))) -> Academic & Admissions | R25: =IF(K25="Informational","Informational",IF(OR(K25="Promotional",K25="Call-to-Action"),"Promotional/Conversion",IF(K25="Reputation Building","Reputation-focused","Engagement/Relationship"))) -> Promotional/Conversion | S25: =IF(COUNTIF($A$2:$A$181,A25)>1,"Duplicate","OK") -> OK | T25: =IF(COUNTIF($F$2:$F$181,F25)>1,"Duplicate","OK") -> OK | U25: =IF(AND(TEXT(C25,"mmmm")=D25,YEAR(C25)=E25),"OK","Mismatch") -> OK | V25: =IF(OR(M25="NA",N25="NA"),"Likes/comments unavailable",IF(I25=J25,"Primary and secondary themes identical","OK")) -> OK
A26: UOT025 | B26: University of Toronto | C26: 45539 | D26: =IF(C26="","",TEXT(C26,"mmmm")) -> September | E26: =IF(C26="","",YEAR(C26)) -> 2024 | F26: https://www.instagram.com/reel/C_gAY05uOuR/?utm_source=ig_web_copy_link&igsh=MzRlODBiNWFlZA== | G26: Reel | H26: Yes | I26: Alumni Success | J26: Campus Life | K26: Emotional Storytelling | L26: No | M26: 1134 | N26: 29 | O26: Who remembers their first day at #UofT like it was yesterday? It’s certainly top of mind for #UofTalumni Ali Kehl, @viccollege’s campus life coordinator, because it’s now her job to help undergrads settle in and get involved. As Vic celebrates 100 years of student engagement in 2024, we asked Ali to share her favourite spots around the college she still calls home. | P26: =IF(OR(I26="Student Experience",I26="Campus Life",I26="Campus Facilities",I26="Student Clubs & Organizations",I26="Events",I26="Student Support Services",I26="Diversity & Inclusion",I26="International Students"),"Student Experience & Campus",IF(OR(I26="Academic Programs",I26="Admissions",I26="Scholarships & Financial Aid"),"Academic & Admissions",IF(OR(I26="Career Opportunities",I26="Alumni Success"),"Career & Alumni",IF(I26="Research & Innovation","Research & Innovation",IF(I26="Rankings & Achievements","Institutional Reputation","Other"))))) -> Career & Alumni | Q26: =IF(OR(J26="Student Experience",J26="Campus Life",J26="Campus Facilities",J26="Student Clubs & Organizations",J26="Events",J26="Student Support Services",J26="Diversity & Inclusion",J26="International Students"),"Student Experience & Campus",IF(OR(J26="Academic Programs",J26="Admissions",J26="Scholarships & Financial Aid"),"Academic & Admissions",IF(OR(J26="Career Opportunities",J26="Alumni Success"),"Career & Alumni",IF(J26="Research & Innovation","Research & Innovation",IF(J26="Rankings & Achievements","Institutional Reputation","Other"))))) -> Student Experience & Campus | R26: =IF(K26="Informational","Informational",IF(OR(K26="Promotional",K26="Call-to-Action"),"Promotional/Conversion",IF(K26="Reputation Building","Reputation-focused","Engagement/Relationship"))) -> Engagement/Relationship | S26: =IF(COUNTIF($A$2:$A$181,A26)>1,"Duplicate","OK") -> OK | T26: =IF(COUNTIF($F$2:$F$181,F26)>1,"Duplicate","OK") -> OK | U26: =IF(AND(TEXT(C26,"mmmm")=D26,YEAR(C26)=E26),"OK","Mismatch") -> OK | V26: =IF(OR(M26="NA",N26="NA"),"Likes/comments unavailable",IF(I26=J26,"Primary and secondary themes identical","OK")) -> OK
A27: UOT026 | B27: University of Toronto | C27: 45558 | D27: September | E27: 2024 | F27: https://www.instagram.com/p/DARSyHePe8t/?utm_source=ig_web_copy_link&igsh=MzRlODBiNWFlZA== | G27: Image | H27: Yes | I27: Scholarships & Financial Aid | J27: Campus Facilities | K27: Informational | L27: Yes | M27: 2430 | N27: 9 | O27: A $25-million gift from Myron and Berna Garron will contribute to the construction of a new state-of-the-art facility at UTSC that will house the Scarborough Academy of Medicine and Integrated Health (SAMIH). @uoft will name the new building the Myron and Berna Garron Health Sciences Complex, in honour of the Garrons’ exceptional generosity. | P27: =IF(OR(I27="Student Experience",I27="Campus Life",I27="Campus Facilities",I27="Student Clubs & Organizations",I27="Events",I27="Student Support Services",I27="Diversity & Inclusion",I27="International Students"),"Student Experience & Campus",IF(OR(I27="Academic Programs",I27="Admissions",I27="Scholarships & Financial Aid"),"Academic & Admissions",IF(OR(I27="Career Opportunities",I27="Alumni Success"),"Career & Alumni",IF(I27="Research & Innovation","Research & Innovation",IF(I27="Rankings & Achievements","Institutional Reputation","Other"))))) -> Academic & Admissions | Q27: =IF(OR(J27="Student Experience",J27="Campus Life",J27="Campus Facilities",J27="Student Clubs & Organizations",J27="Events",J27="Student Support Services",J27="Diversity & Inclusion",J27="International Students"),"Student Experience & Campus",IF(OR(J27="Academic Programs",J27="Admissions",J27="Scholarships & Financial Aid"),"Academic & Admissions",IF(OR(J27="Career Opportunities",J27="Alumni Success"),"Career & Alumni",IF(J27="Research & Innovation","Research & Innovation",IF(J27="Rankings & Achievements","Institutional Reputation","Other"))))) -> Student Experience & Campus | R27: =IF(K27="Informational","Informational",IF(OR(K27="Promotional",K27="Call-to-Action"),"Promotional/Conversion",IF(K27="Reputation Building","Reputation-focused","Engagement/Relationship"))) -> Informational | S27: =IF(COUNTIF($A$2:$A$181,A27)>1,"Duplicate","OK") -> OK | T27: =IF(COUNTIF($F$2:$F$181,F27)>1,"Duplicate","OK") -> OK | U27: =IF(AND(TEXT(C27,"mmmm")=D27,YEAR(C27)=E27),"OK","Mismatch") -> OK | V27: =IF(OR(M27="NA",N27="NA"),"Likes/comments unavailable",IF(I27=J27,"Primary and secondary themes identical","OK")) -> OK
A28: UOT027 | B28: University of Toronto | C28: 45561 | D28: =IF(C28="","",TEXT(C28,"mmmm")) -> September | E28: =IF(C28="","",YEAR(C28)) -> 2024 | F28: https://www.instagram.com/reel/DAYquplxdS_/?utm_source=ig_web_copy_link&igsh=MzRlODBiNWFlZA== | G28: Reel | H28: Yes | I28: Student Experience | J28: International Students | K28: Promotional | L28: Yes | M28: 2380 | N28: 33 | O28: From why they chose #UofT to making the most of your first year — international students share their experiences 💙 #UofTBackToSchool | P28: =IF(OR(I28="Student Experience",I28="Campus Life",I28="Campus Facilities",I28="Student Clubs & Organizations",I28="Events",I28="Student Support Services",I28="Diversity & Inclusion",I28="International Students"),"Student Experience & Campus",IF(OR(I28="Academic Programs",I28="Admissions",I28="Scholarships & Financial Aid"),"Academic & Admissions",IF(OR(I28="Career Opportunities",I28="Alumni Success"),"Career & Alumni",IF(I28="Research & Innovation","Research & Innovation",IF(I28="Rankings & Achievements","Institutional Reputation","Other"))))) -> Student Experience & Campus | Q28: =IF(OR(J28="Student Experience",J28="Campus Life",J28="Campus Facilities",J28="Student Clubs & Organizations",J28="Events",J28="Student Support Services",J28="Diversity & Inclusion",J28="International Students"),"Student Experience & Campus",IF(OR(J28="Academic Programs",J28="Admissions",J28="Scholarships & Financial Aid"),"Academic & Admissions",IF(OR(J28="Career Opportunities",J28="Alumni Success"),"Career & Alumni",IF(J28="Research & Innovation","Research & Innovation",IF(J28="Rankings & Achievements","Institutional Reputation","Other"))))) -> Student Experience & Campus | R28: =IF(K28="Informational","Informational",IF(OR(K28="Promotional",K28="Call-to-Action"),"Promotional/Conversion",IF(K28="Reputation Building","Reputation-focused","Engagement/Relationship"))) -> Promotional/Conversion | S28: =IF(COUNTIF($A$2:$A$181,A28)>1,"Duplicate","OK") -> OK | T28: =IF(COUNTIF($F$2:$F$181,F28)>1,"Duplicate","OK") -> OK | U28: =IF(AND(TEXT(C28,"mmmm")=D28,YEAR(C28)=E28),"OK","Mismatch") -> OK | V28: =IF(OR(M28="NA",N28="NA"),"Likes/comments unavailable",IF(I28=J28,"Primary and secondary themes identical","OK")) -> OK
A29: UOT028 | B29: University of Toronto | C29: 45567 | D29: =IF(C29="","",TEXT(C29,"mmmm")) -> October | E29: =IF(C29="","",YEAR(C29)) -> 2024 | F29: https://www.instagram.com/reel/DAoiZorSwTY/?utm_source=ig_web_copy_link&igsh=MzRlODBiNWFlZA== | G29: Reel | H29: Yes | I29: Student Experience | J29: International Students | K29: Promotional | L29: Yes | M29: 1095 | N29: 37 | O29: Screening across #UofT this fall is a documentary that highlights the journey of international students to our three campuses. International Students: First 48 Hours in Canada is a 22-minute film directed by Cal Campos, capturing the excitement and challenges of packing, traveling, and finally setting foot on each campus. | P29: =IF(OR(I29="Student Experience",I29="Campus Life",I29="Campus Facilities",I29="Student Clubs & Organizations",I29="Events",I29="Student Support Services",I29="Diversity & Inclusion",I29="International Students"),"Student Experience & Campus",IF(OR(I29="Academic Programs",I29="Admissions",I29="Scholarships & Financial Aid"),"Academic & Admissions",IF(OR(I29="Career Opportunities",I29="Alumni Success"),"Career & Alumni",IF(I29="Research & Innovation","Research & Innovation",IF(I29="Rankings & Achievements","Institutional Reputation","Other"))))) -> Student Experience & Campus | Q29: =IF(OR(J29="Student Experience",J29="Campus Life",J29="Campus Facilities",J29="Student Clubs & Organizations",J29="Events",J29="Student Support Services",J29="Diversity & Inclusion",J29="International Students"),"Student Experience & Campus",IF(OR(J29="Academic Programs",J29="Admissions",J29="Scholarships & Financial Aid"),"Academic & Admissions",IF(OR(J29="Career Opportunities",J29="Alumni Success"),"Career & Alumni",IF(J29="Research & Innovation","Research & Innovation",IF(J29="Rankings & Achievements","Institutional Reputation","Other"))))) -> Student Experience & Campus | R29: =IF(K29="Informational","Informational",IF(OR(K29="Promotional",K29="Call-to-Action"),"Promotional/Conversion",IF(K29="Reputation Building","Reputation-focused","Engagement/Relationship"))) -> Promotional/Conversion | S29: =IF(COUNTIF($A$2:$A$181,A29)>1,"Duplicate","OK") -> OK | T29: =IF(COUNTIF($F$2:$F$181,F29)>1,"Duplicate","OK") -> OK | U29: =IF(AND(TEXT(C29,"mmmm")=D29,YEAR(C29)=E29),"OK","Mismatch") -> OK | V29: =IF(OR(M29="NA",N29="NA"),"Likes/comments unavailable",IF(I29=J29,"Primary and secondary themes identical","OK")) -> OK
A30: UOT029 | B30: University of Toronto | C30: 45581 | D30: October | E30: 2024 | F30: https://www.instagram.com/p/DBMdpOWSbwV/?utm_source=ig_web_copy_link&igsh=MzRlODBiNWFlZA== | G30: Image | H30: Yes | I30: Rankings & Achievements | J30: Academic Programs | K30: Informational | L30: Yes | M30: 4695 | N30: 37 | O30: #UofT is once again first in Canada and 21st globally in the prestigious World Reputation Rankings by @timeshighered 🌎 The ranking assesses schools across five broad pillars: teaching, research environment, research quality, industry and international outlook. | P30: =IF(OR(I30="Student Experience",I30="Campus Life",I30="Campus Facilities",I30="Student Clubs & Organizations",I30="Events",I30="Student Support Services",I30="Diversity & Inclusion",I30="International Students"),"Student Experience & Campus",IF(OR(I30="Academic Programs",I30="Admissions",I30="Scholarships & Financial Aid"),"Academic & Admissions",IF(OR(I30="Career Opportunities",I30="Alumni Success"),"Career & Alumni",IF(I30="Research & Innovation","Research & Innovation",IF(I30="Rankings & Achievements","Institutional Reputation","Other"))))) -> Institutional Reputation | Q30: =IF(OR(J30="Student Experience",J30="Campus Life",J30="Campus Facilities",J30="Student Clubs & Organizations",J30="Events",J30="Student Support Services",J30="Diversity & Inclusion",J30="International Students"),"Student Experience & Campus",IF(OR(J30="Academic Programs",J30="Admissions",J30="Scholarships & Financial Aid"),"Academic & Admissions",IF(OR(J30="Career Opportunities",J30="Alumni Success"),"Career & Alumni",IF(J30="Research & Innovation","Research & Innovation",IF(J30="Rankings & Achievements","Institutional Reputation","Other"))))) -> Academic & Admissions | R30: =IF(K30="Informational","Informational",IF(OR(K30="Promotional",K30="Call-to-Action"),"Promotional/Conversion",IF(K30="Reputation Building","Reputation-focused","Engagement/Relationship"))) -> Informational | S30: =IF(COUNTIF($A$2:$A$181,A30)>1,"Duplicate","OK") -> OK | T30: =IF(COUNTIF($F$2:$F$181,F30)>1,"Duplicate","OK") -> OK | U30: =IF(AND(TEXT(C30,"mmmm")=D30,YEAR(C30)=E30),"OK","Mismatch") -> OK | V30: =IF(OR(M30="NA",N30="NA"),"Likes/comments unavailable",IF(I30=J30,"Primary and secondary themes identical","OK")) -> OK
A31: UOT030 | B31: University of Toronto | C31: 45596 | D31: October | E31: 2024 | F31: https://www.instagram.com/reel/DBzXmj1S2on/?utm_source=ig_web_copy_link&igsh=MzRlODBiNWFlZA== | G31: Reel | H31: Yes | I31: Student Experience | J31: International Students | K31: Student Testimonial | L31: Yes | M31: 3277 | N31: 72 | O31: Lim is set to graduate this week with a master’s in Hispanic linguistics with a collaborative specialization in diaspora and transnational studies from the department of Spanish and Portuguese in @uoftartsci. | P31: =IF(OR(I31="Student Experience",I31="Campus Life",I31="Campus Facilities",I31="Student Clubs & Organizations",I31="Events",I31="Student Support Services",I31="Diversity & Inclusion",I31="International Students"),"Student Experience & Campus",IF(OR(I31="Academic Programs",I31="Admissions",I31="Scholarships & Financial Aid"),"Academic & Admissions",IF(OR(I31="Career Opportunities",I31="Alumni Success"),"Career & Alumni",IF(I31="Research & Innovation","Research & Innovation",IF(I31="Rankings & Achievements","Institutional Reputation","Other"))))) -> Student Experience & Campus | Q31: =IF(OR(J31="Student Experience",J31="Campus Life",J31="Campus Facilities",J31="Student Clubs & Organizations",J31="Events",J31="Student Support Services",J31="Diversity & Inclusion",J31="International Students"),"Student Experience & Campus",IF(OR(J31="Academic Programs",J31="Admissions",J31="Scholarships & Financial Aid"),"Academic & Admissions",IF(OR(J31="Career Opportunities",J31="Alumni Success"),"Career & Alumni",IF(J31="Research & Innovation","Research & Innovation",IF(J31="Rankings & Achievements","Institutional Reputation","Other"))))) -> Student Experience & Campus | R31: =IF(K31="Informational","Informational",IF(OR(K31="Promotional",K31="Call-to-Action"),"Promotional/Conversion",IF(K31="Reputation Building","Reputation-focused","Engagement/Relationship"))) -> Engagement/Relationship | S31: =IF(COUNTIF($A$2:$A$181,A31)>1,"Duplicate","OK") -> OK | T31: =IF(COUNTIF($F$2:$F$181,F31)>1,"Duplicate","OK") -> OK | U31: =IF(AND(TEXT(C31,"mmmm")=D31,YEAR(C31)=E31),"OK","Mismatch") -> OK | V31: =IF(OR(M31="NA",N31="NA"),"Likes/comments unavailable",IF(I31=J31,"Primary and secondary themes identical","OK")) -> OK
A32: UOT031 | B32: University of Toronto | C32: 45601 | D32: November | E32: 2024 | F32: https://www.instagram.com/reel/DCATQHVvYtC/?utm_source=ig_web_copy_link&igsh=MzRlODBiNWFlZA== | G32: Reel | H32: Yes | I32: Alumni Success | J32: Diversity & Inclusion | K32: Emotional Storytelling | L32: No | M32: 672 | N32: 16 | O32: We asked our newest #UofTGrad24 grads what was the best thing you have taken from your time at #UTM. 💙🍂 . Congratulations to all our #UTM grads on officially joining the @uoftmississaugaalumni / @UofTAlumni family! | P32: =IF(OR(I32="Student Experience",I32="Campus Life",I32="Campus Facilities",I32="Student Clubs & Organizations",I32="Events",I32="Student Support Services",I32="Diversity & Inclusion",I32="International Students"),"Student Experience & Campus",IF(OR(I32="Academic Programs",I32="Admissions",I32="Scholarships & Financial Aid"),"Academic & Admissions",IF(OR(I32="Career Opportunities",I32="Alumni Success"),"Career & Alumni",IF(I32="Research & Innovation","Research & Innovation",IF(I32="Rankings & Achievements","Institutional Reputation","Other"))))) -> Career & Alumni | Q32: =IF(OR(J32="Student Experience",J32="Campus Life",J32="Campus Facilities",J32="Student Clubs & Organizations",J32="Events",J32="Student Support Services",J32="Diversity & Inclusion",J32="International Students"),"Student Experience & Campus",IF(OR(J32="Academic Programs",J32="Admissions",J32="Scholarships & Financial Aid"),"Academic & Admissions",IF(OR(J32="Career Opportunities",J32="Alumni Success"),"Career & Alumni",IF(J32="Research & Innovation","Research & Innovation",IF(J32="Rankings & Achievements","Institutional Reputation","Other"))))) -> Student Experience & Campus | R32: =IF(K32="Informational","Informational",IF(OR(K32="Promotional",K32="Call-to-Action"),"Promotional/Conversion",IF(K32="Reputation Building","Reputation-focused","Engagement/Relationship"))) -> Engagement/Relationship | S32: =IF(COUNTIF($A$2:$A$181,A32)>1,"Duplicate","OK") -> OK | T32: =IF(COUNTIF($F$2:$F$181,F32)>1,"Duplicate","OK") -> OK | U32: =IF(AND(TEXT(C32,"mmmm")=D32,YEAR(C32)=E32),"OK","Mismatch") -> OK | V32: =IF(OR(M32="NA",N32="NA"),"Likes/comments unavailable",IF(I32=J32,"Primary and secondary themes identical","OK")) -> OK
A33: UOT032 | B33: University of Toronto | C33: 45608 | D33: November | E33: 2024 | F33: https://www.instagram.com/p/DCSHxJnJNet/?utm_source=ig_web_copy_link&igsh=MzRlODBiNWFlZA== | G33: Image | H33: Yes | I33: Scholarships & Financial Aid | J33: Student Experience | K33: Reputation Building | L33: Yes | M33: 2933 | N33: 61 | O33: Beginning next fall, all current and incoming students in the funded cohort (the first four or five years) of PhD and SJD programs will be guaranteed an annual base funding package of $40,000 including tuition – one of the highest base funding packages in Canada. | P33: =IF(OR(I33="Student Experience",I33="Campus Life",I33="Campus Facilities",I33="Student Clubs & Organizations",I33="Events",I33="Student Support Services",I33="Diversity & Inclusion",I33="International Students"),"Student Experience & Campus",IF(OR(I33="Academic Programs",I33="Admissions",I33="Scholarships & Financial Aid"),"Academic & Admissions",IF(OR(I33="Career Opportunities",I33="Alumni Success"),"Career & Alumni",IF(I33="Research & Innovation","Research & Innovation",IF(I33="Rankings & Achievements","Institutional Reputation","Other"))))) -> Academic & Admissions | Q33: =IF(OR(J33="Student Experience",J33="Campus Life",J33="Campus Facilities",J33="Student Clubs & Organizations",J33="Events",J33="Student Support Services",J33="Diversity & Inclusion",J33="International Students"),"Student Experience & Campus",IF(OR(J33="Academic Programs",J33="Admissions",J33="Scholarships & Financial Aid"),"Academic & Admissions",IF(OR(J33="Career Opportunities",J33="Alumni Success"),"Career & Alumni",IF(J33="Research & Innovation","Research & Innovation",IF(J33="Rankings & Achievements","Institutional Reputation","Other"))))) -> Student Experience & Campus | R33: =IF(K33="Informational","Informational",IF(OR(K33="Promotional",K33="Call-to-Action"),"Promotional/Conversion",IF(K33="Reputation Building","Reputation-focused","Engagement/Relationship"))) -> Reputation-focused | S33: =IF(COUNTIF($A$2:$A$181,A33)>1,"Duplicate","OK") -> OK | T33: =IF(COUNTIF($F$2:$F$181,F33)>1,"Duplicate","OK") -> OK | U33: =IF(AND(TEXT(C33,"mmmm")=D33,YEAR(C33)=E33),"OK","Mismatch") -> OK | V33: =IF(OR(M33="NA",N33="NA"),"Likes/comments unavailable",IF(I33=J33,"Primary and secondary themes identical","OK")) -> OK
A34: UOT033 | B34: University of Toronto | C34: 45617 | D34: November | E34: 2024 | F34: https://www.instagram.com/p/DCpX9yNS_2L/?utm_source=ig_web_copy_link&igsh=MzRlODBiNWFlZA== | G34: Image | H34: Yes | I34: Rankings & Achievements | J34: Career Opportunities | K34: Promotional | L34: Yes | M34: 1779 | N34: 18 | O34: #UofT is among the top 15 universities globally for graduate employability in the latest ranking from @timeshighered. 🌎 The Global University Employability Ranking 2025 is based on survey data and reflects the opinions of large employers. | P34: =IF(OR(I34="Student Experience",I34="Campus Life",I34="Campus Facilities",I34="Student Clubs & Organizations",I34="Events",I34="Student Support Services",I34="Diversity & Inclusion",I34="International Students"),"Student Experience & Campus",IF(OR(I34="Academic Programs",I34="Admissions",I34="Scholarships & Financial Aid"),"Academic & Admissions",IF(OR(I34="Career Opportunities",I34="Alumni Success"),"Career & Alumni",IF(I34="Research & Innovation","Research & Innovation",IF(I34="Rankings & Achievements","Institutional Reputation","Other"))))) -> Institutional Reputation | Q34: =IF(OR(J34="Student Experience",J34="Campus Life",J34="Campus Facilities",J34="Student Clubs & Organizations",J34="Events",J34="Student Support Services",J34="Diversity & Inclusion",J34="International Students"),"Student Experience & Campus",IF(OR(J34="Academic Programs",J34="Admissions",J34="Scholarships & Financial Aid"),"Academic & Admissions",IF(OR(J34="Career Opportunities",J34="Alumni Success"),"Career & Alumni",IF(J34="Research & Innovation","Research & Innovation",IF(J34="Rankings & Achievements","Institutional Reputation","Other"))))) -> Career & Alumni | R34: =IF(K34="Informational","Informational",IF(OR(K34="Promotional",K34="Call-to-Action"),"Promotional/Conversion",IF(K34="Reputation Building","Reputation-focused","Engagement/Relationship"))) -> Promotional/Conversion | S34: =IF(COUNTIF($A$2:$A$181,A34)>1,"Duplicate","OK") -> OK | T34: =IF(COUNTIF($F$2:$F$181,F34)>1,"Duplicate","OK") -> OK | U34: =IF(AND(TEXT(C34,"mmmm")=D34,YEAR(C34)=E34),"OK","Mismatch") -> OK | V34: =IF(OR(M34="NA",N34="NA"),"Likes/comments unavailable",IF(I34=J34,"Primary and secondary themes identical","OK")) -> OK
A35: UOT034 | B35: University of Toronto | C35: 45639 | D35: December | E35: 2024 | F35: https://www.instagram.com/reel/DDhy0kPyu20/?utm_source=ig_web_copy_link&igsh=MzRlODBiNWFlZA== | G35: Reel | H35: Yes | I35: Rankings & Achievements | J35: Research & Innovation | K35: Inspirational | L35: Yes | M35: 878 | N35: 11 | O35: Celebrating the new Nobel laureate 💙 As #UofT’s Geoffrey Hinton received his #NobelPrize in Stockholm, our community gathered across all three campuses for watch parties to witness this historic moment. Visit our link in bio or uoft.me/b8E for the full story. | P35: =IF(OR(I35="Student Experience",I35="Campus Life",I35="Campus Facilities",I35="Student Clubs & Organizations",I35="Events",I35="Student Support Services",I35="Diversity & Inclusion",I35="International Students"),"Student Experience & Campus",IF(OR(I35="Academic Programs",I35="Admissions",I35="Scholarships & Financial Aid"),"Academic & Admissions",IF(OR(I35="Career Opportunities",I35="Alumni Success"),"Career & Alumni",IF(I35="Research & Innovation","Research & Innovation",IF(I35="Rankings & Achievements","Institutional Reputation","Other"))))) -> Institutional Reputation | Q35: =IF(OR(J35="Student Experience",J35="Campus Life",J35="Campus Facilities",J35="Student Clubs & Organizations",J35="Events",J35="Student Support Services",J35="Diversity & Inclusion",J35="International Students"),"Student Experience & Campus",IF(OR(J35="Academic Programs",J35="Admissions",J35="Scholarships & Financial Aid"),"Academic & Admissions",IF(OR(J35="Career Opportunities",J35="Alumni Success"),"Career & Alumni",IF(J35="Research & Innovation","Research & Innovation",IF(J35="Rankings & Achievements","Institutional Reputation","Other"))))) -> Research & Innovation | R35: =IF(K35="Informational","Informational",IF(OR(K35="Promotional",K35="Call-to-Action"),"Promotional/Conversion",IF(K35="Reputation Building","Reputation-focused","Engagement/Relationship"))) -> Engagement/Relationship | S35: =IF(COUNTIF($A$2:$A$181,A35)>1,"Duplicate","OK") -> OK | T35: =IF(COUNTIF($F$2:$F$181,F35)>1,"Duplicate","OK") -> OK | U35: =IF(AND(TEXT(C35,"mmmm")=D35,YEAR(C35)=E35),"OK","Mismatch") -> OK | V35: =IF(OR(M35="NA",N35="NA"),"Likes/comments unavailable",IF(I35=J35,"Primary and secondary themes identical","OK")) -> OK
A36: UOT035 | B36: University of Toronto | C36: 45642 | D36: December | E36: 2024 | F36: https://www.instagram.com/reel/DDpX2VwxuaG/?utm_source=ig_web_copy_link&igsh=MzRlODBiNWFlZA== | G36: Reel | H36: Yes | I36: Campus Facilities | J36: Alumni Success | K36: Informational | L36: Yes | M36: 798 | N36: 9 | O36: Step inside The Faculty Club at 41 Willcocks St, a hidden gem on the St. George campus with a storied past. In 1959, artist and @UofT prof Barker Fairley and his wife, activist Margaret Fairley, offered the club a collection of Group of Seven art on the condition that women be admitted. You can see the paintings today in the Fairley Lounge, including works by Lawren Harris, A.J. Casson and J.E.H. Macdonald. | P36: =IF(OR(I36="Student Experience",I36="Campus Life",I36="Campus Facilities",I36="Student Clubs & Organizations",I36="Events",I36="Student Support Services",I36="Diversity & Inclusion",I36="International Students"),"Student Experience & Campus",IF(OR(I36="Academic Programs",I36="Admissions",I36="Scholarships & Financial Aid"),"Academic & Admissions",IF(OR(I36="Career Opportunities",I36="Alumni Success"),"Career & Alumni",IF(I36="Research & Innovation","Research & Innovation",IF(I36="Rankings & Achievements","Institutional Reputation","Other"))))) -> Student Experience & Campus | Q36: =IF(OR(J36="Student Experience",J36="Campus Life",J36="Campus Facilities",J36="Student Clubs & Organizations",J36="Events",J36="Student Support Services",J36="Diversity & Inclusion",J36="International Students"),"Student Experience & Campus",IF(OR(J36="Academic Programs",J36="Admissions",J36="Scholarships & Financial Aid"),"Academic & Admissions",IF(OR(J36="Career Opportunities",J36="Alumni Success"),"Career & Alumni",IF(J36="Research & Innovation","Research & Innovation",IF(J36="Rankings & Achievements","Institutional Reputation","Other"))))) -> Career & Alumni | R36: =IF(K36="Informational","Informational",IF(OR(K36="Promotional",K36="Call-to-Action"),"Promotional/Conversion",IF(K36="Reputation Building","Reputation-focused","Engagement/Relationship"))) -> Informational | S36: =IF(COUNTIF($A$2:$A$181,A36)>1,"Duplicate","OK") -> OK | T36: =IF(COUNTIF($F$2:$F$181,F36)>1,"Duplicate","OK") -> OK | U36: =IF(AND(TEXT(C36,"mmmm")=D36,YEAR(C36)=E36),"OK","Mismatch") -> OK | V36: =IF(OR(M36="NA",N36="NA"),"Likes/comments unavailable",IF(I36=J36,"Primary and secondary themes identical","OK")) -> OK
A37: UOT036 | B37: University of Toronto | C37: 45645 | D37: =IF(C37="","",TEXT(C37,"mmmm")) -> December | E37: =IF(C37="","",YEAR(C37)) -> 2024 | F37: https://www.instagram.com/p/DDw6qyUv2xA/?utm_source=ig_web_copy_link&igsh=MzRlODBiNWFlZA== | G37: Image | H37: Yes | I37: Student Support Services | J37: Student Experience | K37: Informational | L37: Yes | M37: 1768 | N37: 5 | O37: Reminder: There are many mental health resources available to you at U of T, wherever you are. For easy access to mental health support at Health & Wellness, please visit uoft.me/mentalhealthcare (link in bio) | P37: =IF(OR(I37="Student Experience",I37="Campus Life",I37="Campus Facilities",I37="Student Clubs & Organizations",I37="Events",I37="Student Support Services",I37="Diversity & Inclusion",I37="International Students"),"Student Experience & Campus",IF(OR(I37="Academic Programs",I37="Admissions",I37="Scholarships & Financial Aid"),"Academic & Admissions",IF(OR(I37="Career Opportunities",I37="Alumni Success"),"Career & Alumni",IF(I37="Research & Innovation","Research & Innovation",IF(I37="Rankings & Achievements","Institutional Reputation","Other"))))) -> Student Experience & Campus | Q37: =IF(OR(J37="Student Experience",J37="Campus Life",J37="Campus Facilities",J37="Student Clubs & Organizations",J37="Events",J37="Student Support Services",J37="Diversity & Inclusion",J37="International Students"),"Student Experience & Campus",IF(OR(J37="Academic Programs",J37="Admissions",J37="Scholarships & Financial Aid"),"Academic & Admissions",IF(OR(J37="Career Opportunities",J37="Alumni Success"),"Career & Alumni",IF(J37="Research & Innovation","Research & Innovation",IF(J37="Rankings & Achievements","Institutional Reputation","Other"))))) -> Student Experience & Campus | R37: =IF(K37="Informational","Informational",IF(OR(K37="Promotional",K37="Call-to-Action"),"Promotional/Conversion",IF(K37="Reputation Building","Reputation-focused","Engagement/Relationship"))) -> Informational | S37: =IF(COUNTIF($A$2:$A$181,A37)>1,"Duplicate","OK") -> OK | T37: =IF(COUNTIF($F$2:$F$181,F37)>1,"Duplicate","OK") -> OK | U37: =IF(AND(TEXT(C37,"mmmm")=D37,YEAR(C37)=E37),"OK","Mismatch") -> OK | V37: =IF(OR(M37="NA",N37="NA"),"Likes/comments unavailable",IF(I37=J37,"Primary and secondary themes identical","OK")) -> OK
A38: MAC001 | B38: McMaster University | C38: 45673 | D38: =IF(C38="","",TEXT(C38,"mmmm")) -> January | E38: =IF(C38="","",YEAR(C38)) -> 2025 | F38: https://www.instagram.com/p/DE5AYDnR5bj/?utm_source=ig_web_copy_link&igsh=MzRlODBiNWFlZA== | G38: Carousel | H38: Yes | I38: Rankings & Achievements | J38: Other | K38: Emotional Storytelling | L38: Yes | M38: 971 | N38: 2 | O38: Mark Walton, vice-dean of Faculty of Affairs with McMaster’s Faculty of Health Sciences, has accomplished a feat few have done: running a marathon on all seven continents. | P38: =IF(OR(I38="Student Experience",I38="Campus Life",I38="Campus Facilities",I38="Student Clubs & Organizations",I38="Events",I38="Student Support Services",I38="Diversity & Inclusion",I38="International Students"),"Student Experience & Campus",IF(OR(I38="Academic Programs",I38="Admissions",I38="Scholarships & Financial Aid"),"Academic & Admissions",IF(OR(I38="Career Opportunities",I38="Alumni Success"),"Career & Alumni",IF(I38="Research & Innovation","Research & Innovation",IF(I38="Rankings & Achievements","Institutional Reputation","Other"))))) -> Institutional Reputation | Q38: =IF(OR(J38="Student Experience",J38="Campus Life",J38="Campus Facilities",J38="Student Clubs & Organizations",J38="Events",J38="Student Support Services",J38="Diversity & Inclusion",J38="International Students"),"Student Experience & Campus",IF(OR(J38="Academic Programs",J38="Admissions",J38="Scholarships & Financial Aid"),"Academic & Admissions",IF(OR(J38="Career Opportunities",J38="Alumni Success"),"Career & Alumni",IF(J38="Research & Innovation","Research & Innovation",IF(J38="Rankings & Achievements","Institutional Reputation","Other"))))) -> Other | R38: =IF(K38="Informational","Informational",IF(OR(K38="Promotional",K38="Call-to-Action"),"Promotional/Conversion",IF(K38="Reputation Building","Reputation-focused","Engagement/Relationship"))) -> Engagement/Relationship | S38: =IF(COUNTIF($A$2:$A$181,A38)>1,"Duplicate","OK") -> OK | T38: =IF(COUNTIF($F$2:$F$181,F38)>1,"Duplicate","OK") -> OK | U38: =IF(AND(TEXT(C38,"mmmm")=D38,YEAR(C38)=E38),"OK","Mismatch") -> OK | V38: =IF(OR(M38="NA",N38="NA"),"Likes/comments unavailable",IF(I38=J38,"Primary and secondary themes identical","OK")) -> OK
A39: MAC002 | B39: McMaster University | C39: 45687 | D39: January | E39: 2025 | F39: https://www.instagram.com/reel/DFdsXUXvuIf/?utm_source=ig_web_copy_link&igsh=MzRlODBiNWFlZA== | G39: Reel | H39: Yes | I39: Student Experience | J39: Career Opportunities | K39: Student Testimonial | L39: Yes | M39: 477 | N39: 11 | O39: When I started at McMaster, I wasn’t sure what career I wanted to pursue. Here’s 3 things that helped me figure that out. | P39: =IF(OR(I39="Student Experience",I39="Campus Life",I39="Campus Facilities",I39="Student Clubs & Organizations",I39="Events",I39="Student Support Services",I39="Diversity & Inclusion",I39="International Students"),"Student Experience & Campus",IF(OR(I39="Academic Programs",I39="Admissions",I39="Scholarships & Financial Aid"),"Academic & Admissions",IF(OR(I39="Career Opportunities",I39="Alumni Success"),"Career & Alumni",IF(I39="Research & Innovation","Research & Innovation",IF(I39="Rankings & Achievements","Institutional Reputation","Other"))))) -> Student Experience & Campus | Q39: =IF(OR(J39="Student Experience",J39="Campus Life",J39="Campus Facilities",J39="Student Clubs & Organizations",J39="Events",J39="Student Support Services",J39="Diversity & Inclusion",J39="International Students"),"Student Experience & Campus",IF(OR(J39="Academic Programs",J39="Admissions",J39="Scholarships & Financial Aid"),"Academic & Admissions",IF(OR(J39="Career Opportunities",J39="Alumni Success"),"Career & Alumni",IF(J39="Research & Innovation","Research & Innovation",IF(J39="Rankings & Achievements","Institutional Reputation","Other"))))) -> Career & Alumni | R39: =IF(K39="Informational","Informational",IF(OR(K39="Promotional",K39="Call-to-Action"),"Promotional/Conversion",IF(K39="Reputation Building","Reputation-focused","Engagement/Relationship"))) -> Engagement/Relationship | S39: =IF(COUNTIF($A$2:$A$181,A39)>1,"Duplicate","OK") -> OK | T39: =IF(COUNTIF($F$2:$F$181,F39)>1,"Duplicate","OK") -> OK | U39: =IF(AND(TEXT(C39,"mmmm")=D39,YEAR(C39)=E39),"OK","Mismatch") -> OK | V39: =IF(OR(M39="NA",N39="NA"),"Likes/comments unavailable",IF(I39=J39,"Primary and secondary themes identical","OK")) -> OK
A40: MAC003 | B40: McMaster University | C40: 45675 | D40: =IF(C40="","",TEXT(C40,"mmmm")) -> January | E40: =IF(C40="","",YEAR(C40)) -> 2025 | F40: https://www.instagram.com/p/DFoEtHbPabK/?utm_source=ig_web_copy_link&igsh=MzRlODBiNWFlZA== | G40: Carousel | H40: Yes | I40: Student Clubs & Organizations | J40: Events | K40: Emotional Storytelling | L40: Yes | M40: 878 | N40: 3 | O40: Powerful spoken word performances and joyful music rang out in MUSC today, as our community gathered to celebrate the launch of Black History Month at McMaster. Today’s event marks the start of a month-long series of events, programming and celebration. | P40: =IF(OR(I40="Student Experience",I40="Campus Life",I40="Campus Facilities",I40="Student Clubs & Organizations",I40="Events",I40="Student Support Services",I40="Diversity & Inclusion",I40="International Students"),"Student Experience & Campus",IF(OR(I40="Academic Programs",I40="Admissions",I40="Scholarships & Financial Aid"),"Academic & Admissions",IF(OR(I40="Career Opportunities",I40="Alumni Success"),"Career & Alumni",IF(I40="Research & Innovation","Research & Innovation",IF(I40="Rankings & Achievements","Institutional Reputation","Other"))))) -> Student Experience & Campus | Q40: =IF(OR(J40="Student Experience",J40="Campus Life",J40="Campus Facilities",J40="Student Clubs & Organizations",J40="Events",J40="Student Support Services",J40="Diversity & Inclusion",J40="International Students"),"Student Experience & Campus",IF(OR(J40="Academic Programs",J40="Admissions",J40="Scholarships & Financial Aid"),"Academic & Admissions",IF(OR(J40="Career Opportunities",J40="Alumni Success"),"Career & Alumni",IF(J40="Research & Innovation","Research & Innovation",IF(J40="Rankings & Achievements","Institutional Reputation","Other"))))) -> Student Experience & Campus | R40: =IF(K40="Informational","Informational",IF(OR(K40="Promotional",K40="Call-to-Action"),"Promotional/Conversion",IF(K40="Reputation Building","Reputation-focused","Engagement/Relationship"))) -> Engagement/Relationship | S40: =IF(COUNTIF($A$2:$A$181,A40)>1,"Duplicate","OK") -> OK | T40: =IF(COUNTIF($F$2:$F$181,F40)>1,"Duplicate","OK") -> OK | U40: =IF(AND(TEXT(C40,"mmmm")=D40,YEAR(C40)=E40),"OK","Mismatch") -> OK | V40: =IF(OR(M40="NA",N40="NA"),"Likes/comments unavailable",IF(I40=J40,"Primary and secondary themes identical","OK")) -> OK
A41: MAC004 | B41: McMaster University | C41: 45714 | D41: February | E41: 2025 | F41: https://www.instagram.com/reel/DGjEPZ-yTRx/?utm_source=ig_web_copy_link&igsh=MzRlODBiNWFlZA== | G41: Reel | H41: Yes | I41: Campus Facilities | J41: Student Experience | K41: Informational | L41: Yes | M41: 443 | N41: 0 | O41: ehind the scenes at the McLean Centre for Collaborative Discovery 🚧. This bright space on the third floor will be the new home of Innis Library when the MCCD opens its doors in fall 2025. | P41: =IF(OR(I41="Student Experience",I41="Campus Life",I41="Campus Facilities",I41="Student Clubs & Organizations",I41="Events",I41="Student Support Services",I41="Diversity & Inclusion",I41="International Students"),"Student Experience & Campus",IF(OR(I41="Academic Programs",I41="Admissions",I41="Scholarships & Financial Aid"),"Academic & Admissions",IF(OR(I41="Career Opportunities",I41="Alumni Success"),"Career & Alumni",IF(I41="Research & Innovation","Research & Innovation",IF(I41="Rankings & Achievements","Institutional Reputation","Other"))))) -> Student Experience & Campus | Q41: =IF(OR(J41="Student Experience",J41="Campus Life",J41="Campus Facilities",J41="Student Clubs & Organizations",J41="Events",J41="Student Support Services",J41="Diversity & Inclusion",J41="International Students"),"Student Experience & Campus",IF(OR(J41="Academic Programs",J41="Admissions",J41="Scholarships & Financial Aid"),"Academic & Admissions",IF(OR(J41="Career Opportunities",J41="Alumni Success"),"Career & Alumni",IF(J41="Research & Innovation","Research & Innovation",IF(J41="Rankings & Achievements","Institutional Reputation","Other"))))) -> Student Experience & Campus | R41: =IF(K41="Informational","Informational",IF(OR(K41="Promotional",K41="Call-to-Action"),"Promotional/Conversion",IF(K41="Reputation Building","Reputation-focused","Engagement/Relationship"))) -> Informational | S41: =IF(COUNTIF($A$2:$A$181,A41)>1,"Duplicate","OK") -> OK | T41: =IF(COUNTIF($F$2:$F$181,F41)>1,"Duplicate","OK") -> OK | U41: =IF(AND(TEXT(C41,"mmmm")=D41,YEAR(C41)=E41),"OK","Mismatch") -> OK | V41: =IF(OR(M41="NA",N41="NA"),"Likes/comments unavailable",IF(I41=J41,"Primary and secondary themes identical","OK")) -> OK
A42: MAC005 | B42: McMaster University | C42: 45716 | D42: February | E42: 2025 | F42: https://www.instagram.com/p/DGoKCC_SUfA/?utm_source=ig_web_copy_link&igsh=MzRlODBiNWFlZA== | G42: Image | H42: Yes | I42: Academic Programs | J42: Admissions | K42: Promotional | L42: Yes | M42: 524 | N42: 0 | O42: Announcing an exciting new academic option available to all McMaster students: the Minor in Nuclear Studies & Society! As Canada’s Nuclear University, we know how important it is to prepare students in all disciplines for careers in the growing nuclear industry. | P42: =IF(OR(I42="Student Experience",I42="Campus Life",I42="Campus Facilities",I42="Student Clubs & Organizations",I42="Events",I42="Student Support Services",I42="Diversity & Inclusion",I42="International Students"),"Student Experience & Campus",IF(OR(I42="Academic Programs",I42="Admissions",I42="Scholarships & Financial Aid"),"Academic & Admissions",IF(OR(I42="Career Opportunities",I42="Alumni Success"),"Career & Alumni",IF(I42="Research & Innovation","Research & Innovation",IF(I42="Rankings & Achievements","Institutional Reputation","Other"))))) -> Academic & Admissions | Q42: =IF(OR(J42="Student Experience",J42="Campus Life",J42="Campus Facilities",J42="Student Clubs & Organizations",J42="Events",J42="Student Support Services",J42="Diversity & Inclusion",J42="International Students"),"Student Experience & Campus",IF(OR(J42="Academic Programs",J42="Admissions",J42="Scholarships & Financial Aid"),"Academic & Admissions",IF(OR(J42="Career Opportunities",J42="Alumni Success"),"Career & Alumni",IF(J42="Research & Innovation","Research & Innovation",IF(J42="Rankings & Achievements","Institutional Reputation","Other"))))) -> Academic & Admissions | R42: =IF(K42="Informational","Informational",IF(OR(K42="Promotional",K42="Call-to-Action"),"Promotional/Conversion",IF(K42="Reputation Building","Reputation-focused","Engagement/Relationship"))) -> Promotional/Conversion | S42: =IF(COUNTIF($A$2:$A$181,A42)>1,"Duplicate","OK") -> OK | T42: =IF(COUNTIF($F$2:$F$181,F42)>1,"Duplicate","OK") -> OK | U42: =IF(AND(TEXT(C42,"mmmm")=D42,YEAR(C42)=E42),"OK","Mismatch") -> OK | V42: =IF(OR(M42="NA",N42="NA"),"Likes/comments unavailable",IF(I42=J42,"Primary and secondary themes identical","OK")) -> OK
A43: MAC006 | B43: McMaster University | C43: 45716 | D43: =IF(C43="","",TEXT(C43,"mmmm")) -> February | E43: =IF(C43="","",YEAR(C43)) -> 2025 | F43: https://www.instagram.com/reel/DGqhEb7JDU8/?utm_source=ig_web_copy_link&igsh=MzRlODBiNWFlZA== | G43: Reel | H43: Yes | I43: Career Opportunities | J43: Student Experience | K43: Inspirational | L43: No | M43: 572 | N43: 8 | O43: What’s the most unique experience on your resume? March is National Co-op and Work-Integrated Learning Month. We know that some students have a harder time understanding the value of skills they’ve picked up while volunteering, pursuing a co-op, or even through their hobbies. This month, we’re sharing student stories and resources that will encourage you to find value in all your experiences! It all adds up ⭐️ | P43: =IF(OR(I43="Student Experience",I43="Campus Life",I43="Campus Facilities",I43="Student Clubs & Organizations",I43="Events",I43="Student Support Services",I43="Diversity & Inclusion",I43="International Students"),"Student Experience & Campus",IF(OR(I43="Academic Programs",I43="Admissions",I43="Scholarships & Financial Aid"),"Academic & Admissions",IF(OR(I43="Career Opportunities",I43="Alumni Success"),"Career & Alumni",IF(I43="Research & Innovation","Research & Innovation",IF(I43="Rankings & Achievements","Institutional Reputation","Other"))))) -> Career & Alumni | Q43: =IF(OR(J43="Student Experience",J43="Campus Life",J43="Campus Facilities",J43="Student Clubs & Organizations",J43="Events",J43="Student Support Services",J43="Diversity & Inclusion",J43="International Students"),"Student Experience & Campus",IF(OR(J43="Academic Programs",J43="Admissions",J43="Scholarships & Financial Aid"),"Academic & Admissions",IF(OR(J43="Career Opportunities",J43="Alumni Success"),"Career & Alumni",IF(J43="Research & Innovation","Research & Innovation",IF(J43="Rankings & Achievements","Institutional Reputation","Other"))))) -> Student Experience & Campus | R43: =IF(K43="Informational","Informational",IF(OR(K43="Promotional",K43="Call-to-Action"),"Promotional/Conversion",IF(K43="Reputation Building","Reputation-focused","Engagement/Relationship"))) -> Engagement/Relationship | S43: =IF(COUNTIF($A$2:$A$181,A43)>1,"Duplicate","OK") -> OK | T43: =IF(COUNTIF($F$2:$F$181,F43)>1,"Duplicate","OK") -> OK | U43: =IF(AND(TEXT(C43,"mmmm")=D43,YEAR(C43)=E43),"OK","Mismatch") -> OK | V43: =IF(OR(M43="NA",N43="NA"),"Likes/comments unavailable",IF(I43=J43,"Primary and secondary themes identical","OK")) -> OK
A44: MAC007 | B44: McMaster University | C44: 45720 | D44: March | E44: 2025 | F44: https://www.instagram.com/reel/DGy3HbsSkYy/?utm_source=ig_web_copy_link&igsh=MzRlODBiNWFlZA== | G44: Reel | H44: Yes | I44: Student Experience | J44: Academic Programs | K44: Promotional | L44: Yes | M44: 2040 | N44: 9 | O44: Today, we celebrate the incredible achievements of our #medschool learners who have completed their clerkship and those who have matched to a residency program! | P44: =IF(OR(I44="Student Experience",I44="Campus Life",I44="Campus Facilities",I44="Student Clubs & Organizations",I44="Events",I44="Student Support Services",I44="Diversity & Inclusion",I44="International Students"),"Student Experience & Campus",IF(OR(I44="Academic Programs",I44="Admissions",I44="Scholarships & Financial Aid"),"Academic & Admissions",IF(OR(I44="Career Opportunities",I44="Alumni Success"),"Career & Alumni",IF(I44="Research & Innovation","Research & Innovation",IF(I44="Rankings & Achievements","Institutional Reputation","Other"))))) -> Student Experience & Campus | Q44: =IF(OR(J44="Student Experience",J44="Campus Life",J44="Campus Facilities",J44="Student Clubs & Organizations",J44="Events",J44="Student Support Services",J44="Diversity & Inclusion",J44="International Students"),"Student Experience & Campus",IF(OR(J44="Academic Programs",J44="Admissions",J44="Scholarships & Financial Aid"),"Academic & Admissions",IF(OR(J44="Career Opportunities",J44="Alumni Success"),"Career & Alumni",IF(J44="Research & Innovation","Research & Innovation",IF(J44="Rankings & Achievements","Institutional Reputation","Other"))))) -> Academic & Admissions | R44: =IF(K44="Informational","Informational",IF(OR(K44="Promotional",K44="Call-to-Action"),"Promotional/Conversion",IF(K44="Reputation Building","Reputation-focused","Engagement/Relationship"))) -> Promotional/Conversion | S44: =IF(COUNTIF($A$2:$A$181,A44)>1,"Duplicate","OK") -> OK | T44: =IF(COUNTIF($F$2:$F$181,F44)>1,"Duplicate","OK") -> OK | U44: =IF(AND(TEXT(C44,"mmmm")=D44,YEAR(C44)=E44),"OK","Mismatch") -> OK | V44: =IF(OR(M44="NA",N44="NA"),"Likes/comments unavailable",IF(I44=J44,"Primary and secondary themes identical","OK")) -> OK
A45: MAC008 | B45: McMaster University | C45: 45729 | D45: March | E45: 2025 | F45: https://www.instagram.com/p/DHJqawAvuwl/?utm_source=ig_web_copy_link&igsh=MzRlODBiNWFlZA== | G45: Image | H45: Yes | I45: Rankings & Achievements | J45: Academic Programs | K45: Informational | L45: Yes | M45: 1650 | N45: 14 | O45: e are proud to be one of the world’s best universities at which to study life sciences and medicine McMaster has been ranked 59th internationally, according to the 2025 QS World University Rankings by subject | P45: =IF(OR(I45="Student Experience",I45="Campus Life",I45="Campus Facilities",I45="Student Clubs & Organizations",I45="Events",I45="Student Support Services",I45="Diversity & Inclusion",I45="International Students"),"Student Experience & Campus",IF(OR(I45="Academic Programs",I45="Admissions",I45="Scholarships & Financial Aid"),"Academic & Admissions",IF(OR(I45="Career Opportunities",I45="Alumni Success"),"Career & Alumni",IF(I45="Research & Innovation","Research & Innovation",IF(I45="Rankings & Achievements","Institutional Reputation","Other"))))) -> Institutional Reputation | Q45: =IF(OR(J45="Student Experience",J45="Campus Life",J45="Campus Facilities",J45="Student Clubs & Organizations",J45="Events",J45="Student Support Services",J45="Diversity & Inclusion",J45="International Students"),"Student Experience & Campus",IF(OR(J45="Academic Programs",J45="Admissions",J45="Scholarships & Financial Aid"),"Academic & Admissions",IF(OR(J45="Career Opportunities",J45="Alumni Success"),"Career & Alumni",IF(J45="Research & Innovation","Research & Innovation",IF(J45="Rankings & Achievements","Institutional Reputation","Other"))))) -> Academic & Admissions | R45: =IF(K45="Informational","Informational",IF(OR(K45="Promotional",K45="Call-to-Action"),"Promotional/Conversion",IF(K45="Reputation Building","Reputation-focused","Engagement/Relationship"))) -> Informational | S45: =IF(COUNTIF($A$2:$A$181,A45)>1,"Duplicate","OK") -> OK | T45: =IF(COUNTIF($F$2:$F$181,F45)>1,"Duplicate","OK") -> OK | U45: =IF(AND(TEXT(C45,"mmmm")=D45,YEAR(C45)=E45),"OK","Mismatch") -> OK | V45: =IF(OR(M45="NA",N45="NA"),"Likes/comments unavailable",IF(I45=J45,"Primary and secondary themes identical","OK")) -> OK
A46: MAC009 | B46: McMaster University | C46: 45747 | D46: March | E46: 2025 | F46: https://www.instagram.com/reel/DH4BvXVPbB0/?utm_source=ig_web_copy_link&igsh=MzRlODBiNWFlZA== | G46: Reel | H46: Yes | I46: Student Experience | J46: Academic Programs | K46: Promotional | L46: No | M46: 348 | N46: 16 | O46: Nicole Malette knows a thing or two — or three! — about co-op and hands-on learning The fifth-year Chemical Biology student shares three big takeaways from her co-op and experiential learning opportunities | P46: =IF(OR(I46="Student Experience",I46="Campus Life",I46="Campus Facilities",I46="Student Clubs & Organizations",I46="Events",I46="Student Support Services",I46="Diversity & Inclusion",I46="International Students"),"Student Experience & Campus",IF(OR(I46="Academic Programs",I46="Admissions",I46="Scholarships & Financial Aid"),"Academic & Admissions",IF(OR(I46="Career Opportunities",I46="Alumni Success"),"Career & Alumni",IF(I46="Research & Innovation","Research & Innovation",IF(I46="Rankings & Achievements","Institutional Reputation","Other"))))) -> Student Experience & Campus | Q46: =IF(OR(J46="Student Experience",J46="Campus Life",J46="Campus Facilities",J46="Student Clubs & Organizations",J46="Events",J46="Student Support Services",J46="Diversity & Inclusion",J46="International Students"),"Student Experience & Campus",IF(OR(J46="Academic Programs",J46="Admissions",J46="Scholarships & Financial Aid"),"Academic & Admissions",IF(OR(J46="Career Opportunities",J46="Alumni Success"),"Career & Alumni",IF(J46="Research & Innovation","Research & Innovation",IF(J46="Rankings & Achievements","Institutional Reputation","Other"))))) -> Academic & Admissions | R46: =IF(K46="Informational","Informational",IF(OR(K46="Promotional",K46="Call-to-Action"),"Promotional/Conversion",IF(K46="Reputation Building","Reputation-focused","Engagement/Relationship"))) -> Promotional/Conversion | S46: =IF(COUNTIF($A$2:$A$181,A46)>1,"Duplicate","OK") -> OK | T46: =IF(COUNTIF($F$2:$F$181,F46)>1,"Duplicate","OK") -> OK | U46: =IF(AND(TEXT(C46,"mmmm")=D46,YEAR(C46)=E46),"OK","Mismatch") -> OK | V46: =IF(OR(M46="NA",N46="NA"),"Likes/comments unavailable",IF(I46=J46,"Primary and secondary themes identical","OK")) -> OK
A47: MAC010 | B47: McMaster University | C47: 45749 | D47: April | E47: 2025 | F47: https://www.instagram.com/reel/DH8sUefgXF8/?utm_source=ig_web_copy_link&igsh=MzRlODBiNWFlZA== | G47: Reel | H47: Yes | I47: Student Experience | J47: Academic Programs | K47: Promotional | L47: No | M47: 442 | N47: 12 | O47: Meet Curran, a first-year political science student. He says a high school co-op helped him figure out what he wanted to study at McMaster. And now, as he gets set to wrap up his first year, he shares how his L1 experience has helped him get set for what’s next. | P47: =IF(OR(I47="Student Experience",I47="Campus Life",I47="Campus Facilities",I47="Student Clubs & Organizations",I47="Events",I47="Student Support Services",I47="Diversity & Inclusion",I47="International Students"),"Student Experience & Campus",IF(OR(I47="Academic Programs",I47="Admissions",I47="Scholarships & Financial Aid"),"Academic & Admissions",IF(OR(I47="Career Opportunities",I47="Alumni Success"),"Career & Alumni",IF(I47="Research & Innovation","Research & Innovation",IF(I47="Rankings & Achievements","Institutional Reputation","Other"))))) -> Student Experience & Campus | Q47: =IF(OR(J47="Student Experience",J47="Campus Life",J47="Campus Facilities",J47="Student Clubs & Organizations",J47="Events",J47="Student Support Services",J47="Diversity & Inclusion",J47="International Students"),"Student Experience & Campus",IF(OR(J47="Academic Programs",J47="Admissions",J47="Scholarships & Financial Aid"),"Academic & Admissions",IF(OR(J47="Career Opportunities",J47="Alumni Success"),"Career & Alumni",IF(J47="Research & Innovation","Research & Innovation",IF(J47="Rankings & Achievements","Institutional Reputation","Other"))))) -> Academic & Admissions | R47: =IF(K47="Informational","Informational",IF(OR(K47="Promotional",K47="Call-to-Action"),"Promotional/Conversion",IF(K47="Reputation Building","Reputation-focused","Engagement/Relationship"))) -> Promotional/Conversion | S47: =IF(COUNTIF($A$2:$A$181,A47)>1,"Duplicate","OK") -> OK | T47: =IF(COUNTIF($F$2:$F$181,F47)>1,"Duplicate","OK") -> OK | U47: =IF(AND(TEXT(C47,"mmmm")=D47,YEAR(C47)=E47),"OK","Mismatch") -> OK | V47: =IF(OR(M47="NA",N47="NA"),"Likes/comments unavailable",IF(I47=J47,"Primary and secondary themes identical","OK")) -> OK
A48: MAC011 | B48: McMaster University | C48: 45769 | D48: April | E48: 2025 | F48: https://www.instagram.com/p/DIwy8wiPma-/?utm_source=ig_web_copy_link&igsh=MzRlODBiNWFlZA== | G48: Carousel | H48: Yes | I48: Scholarships & Financial Aid | J48: Academic Programs | K48: Community Engagement | L48: Yes | M48: 735 | N48: 2 | O48: Our success story began in a university lab, and with support like this, more Ontario students can bring life-changing solutions to impact the lives of others.” @mcmastereng grad Lianna Genovese and CEO of @imaginable.solutions on announcement of $750M in provincial funding for STEM students across the province. | P48: =IF(OR(I48="Student Experience",I48="Campus Life",I48="Campus Facilities",I48="Student Clubs & Organizations",I48="Events",I48="Student Support Services",I48="Diversity & Inclusion",I48="International Students"),"Student Experience & Campus",IF(OR(I48="Academic Programs",I48="Admissions",I48="Scholarships & Financial Aid"),"Academic & Admissions",IF(OR(I48="Career Opportunities",I48="Alumni Success"),"Career & Alumni",IF(I48="Research & Innovation","Research & Innovation",IF(I48="Rankings & Achievements","Institutional Reputation","Other"))))) -> Academic & Admissions | Q48: =IF(OR(J48="Student Experience",J48="Campus Life",J48="Campus Facilities",J48="Student Clubs & Organizations",J48="Events",J48="Student Support Services",J48="Diversity & Inclusion",J48="International Students"),"Student Experience & Campus",IF(OR(J48="Academic Programs",J48="Admissions",J48="Scholarships & Financial Aid"),"Academic & Admissions",IF(OR(J48="Career Opportunities",J48="Alumni Success"),"Career & Alumni",IF(J48="Research & Innovation","Research & Innovation",IF(J48="Rankings & Achievements","Institutional Reputation","Other"))))) -> Academic & Admissions | R48: =IF(K48="Informational","Informational",IF(OR(K48="Promotional",K48="Call-to-Action"),"Promotional/Conversion",IF(K48="Reputation Building","Reputation-focused","Engagement/Relationship"))) -> Engagement/Relationship | S48: =IF(COUNTIF($A$2:$A$181,A48)>1,"Duplicate","OK") -> OK | T48: =IF(COUNTIF($F$2:$F$181,F48)>1,"Duplicate","OK") -> OK | U48: =IF(AND(TEXT(C48,"mmmm")=D48,YEAR(C48)=E48),"OK","Mismatch") -> OK | V48: =IF(OR(M48="NA",N48="NA"),"Likes/comments unavailable",IF(I48=J48,"Primary and secondary themes identical","OK")) -> OK
A49: MAC012 | B49: McMaster University | C49: 45777 | D49: April | E49: 2025 | F49: https://www.instagram.com/p/DJEsJqhP6Y-/?utm_source=ig_web_copy_link&igsh=MzRlODBiNWFlZA== | G49: Carousel | H49: Yes | I49: International Students | J49: Student Experience | K49: Student Testimonial | L49: Yes | M49: 757 | N49: 1 | O49: Laura Jurgeleviciute jokes that she could write a book for the incoming McMaster students she met as a volunteer for @macssc’s International Student Buddy Program. She had to navigate immigrations, housing and student supports when she arrived at McMaster from Lithuania, so she knew how to help incoming international students. | P49: =IF(OR(I49="Student Experience",I49="Campus Life",I49="Campus Facilities",I49="Student Clubs & Organizations",I49="Events",I49="Student Support Services",I49="Diversity & Inclusion",I49="International Students"),"Student Experience & Campus",IF(OR(I49="Academic Programs",I49="Admissions",I49="Scholarships & Financial Aid"),"Academic & Admissions",IF(OR(I49="Career Opportunities",I49="Alumni Success"),"Career & Alumni",IF(I49="Research & Innovation","Research & Innovation",IF(I49="Rankings & Achievements","Institutional Reputation","Other"))))) -> Student Experience & Campus | Q49: =IF(OR(J49="Student Experience",J49="Campus Life",J49="Campus Facilities",J49="Student Clubs & Organizations",J49="Events",J49="Student Support Services",J49="Diversity & Inclusion",J49="International Students"),"Student Experience & Campus",IF(OR(J49="Academic Programs",J49="Admissions",J49="Scholarships & Financial Aid"),"Academic & Admissions",IF(OR(J49="Career Opportunities",J49="Alumni Success"),"Career & Alumni",IF(J49="Research & Innovation","Research & Innovation",IF(J49="Rankings & Achievements","Institutional Reputation","Other"))))) -> Student Experience & Campus | R49: =IF(K49="Informational","Informational",IF(OR(K49="Promotional",K49="Call-to-Action"),"Promotional/Conversion",IF(K49="Reputation Building","Reputation-focused","Engagement/Relationship"))) -> Engagement/Relationship | S49: =IF(COUNTIF($A$2:$A$181,A49)>1,"Duplicate","OK") -> OK | T49: =IF(COUNTIF($F$2:$F$181,F49)>1,"Duplicate","OK") -> OK | U49: =IF(AND(TEXT(C49,"mmmm")=D49,YEAR(C49)=E49),"OK","Mismatch") -> OK | V49: =IF(OR(M49="NA",N49="NA"),"Likes/comments unavailable",IF(I49=J49,"Primary and secondary themes identical","OK")) -> OK
A50: MAC013 | B50: McMaster University | C50: 45790 | D50: May | E50: 2025 | F50: https://www.instagram.com/reel/DJmL_z0N1U4/?utm_source=ig_web_copy_link&igsh=MzRlODBiNWFlZA== | G50: Reel | H50: Yes | I50: Admissions | J50: Student Experience | K50: Promotional | L50: No | M50: 975 | N50: 3 | O50: To everyone who joined us—thank you for bringing your energy, your questions and your curiosity. From tours and info sessions to casual campus strolls, it was amazing to see future Marauders imagining their next chapter at McMaster. 💼 | P50: =IF(OR(I50="Student Experience",I50="Campus Life",I50="Campus Facilities",I50="Student Clubs & Organizations",I50="Events",I50="Student Support Services",I50="Diversity & Inclusion",I50="International Students"),"Student Experience & Campus",IF(OR(I50="Academic Programs",I50="Admissions",I50="Scholarships & Financial Aid"),"Academic & Admissions",IF(OR(I50="Career Opportunities",I50="Alumni Success"),"Career & Alumni",IF(I50="Research & Innovation","Research & Innovation",IF(I50="Rankings & Achievements","Institutional Reputation","Other"))))) -> Academic & Admissions | Q50: =IF(OR(J50="Student Experience",J50="Campus Life",J50="Campus Facilities",J50="Student Clubs & Organizations",J50="Events",J50="Student Support Services",J50="Diversity & Inclusion",J50="International Students"),"Student Experience & Campus",IF(OR(J50="Academic Programs",J50="Admissions",J50="Scholarships & Financial Aid"),"Academic & Admissions",IF(OR(J50="Career Opportunities",J50="Alumni Success"),"Career & Alumni",IF(J50="Research & Innovation","Research & Innovation",IF(J50="Rankings & Achievements","Institutional Reputation","Other"))))) -> Student Experience & Campus | R50: =IF(K50="Informational","Informational",IF(OR(K50="Promotional",K50="Call-to-Action"),"Promotional/Conversion",IF(K50="Reputation Building","Reputation-focused","Engagement/Relationship"))) -> Promotional/Conversion | S50: =IF(COUNTIF($A$2:$A$181,A50)>1,"Duplicate","OK") -> OK | T50: =IF(COUNTIF($F$2:$F$181,F50)>1,"Duplicate","OK") -> OK | U50: =IF(AND(TEXT(C50,"mmmm")=D50,YEAR(C50)=E50),"OK","Mismatch") -> OK | V50: =IF(OR(M50="NA",N50="NA"),"Likes/comments unavailable",IF(I50=J50,"Primary and secondary themes identical","OK")) -> OK
A51: MAC014 | B51: McMaster University | C51: 45805 | D51: May | E51: 2025 | F51: https://www.instagram.com/reel/DKNE8j9xy1l/?utm_source=ig_web_copy_link&igsh=MzRlODBiNWFlZA== | G51: Reel | H51: Yes | I51: Student Experience | J51: Events | K51: Community Engagement | L51: No | M51: 5393 | N51: 84 | O51: More than 1,000 Health Sciences graduates crossed the stage during the Spring 2025 Convocation ceremonies, representing 32 undergraduate and graduate programs. Valedictorian Alador Bereketab shared an inspiring message about resilience and how small acts can lead to meaningful change. | P51: =IF(OR(I51="Student Experience",I51="Campus Life",I51="Campus Facilities",I51="Student Clubs & Organizations",I51="Events",I51="Student Support Services",I51="Diversity & Inclusion",I51="International Students"),"Student Experience & Campus",IF(OR(I51="Academic Programs",I51="Admissions",I51="Scholarships & Financial Aid"),"Academic & Admissions",IF(OR(I51="Career Opportunities",I51="Alumni Success"),"Career & Alumni",IF(I51="Research & Innovation","Research & Innovation",IF(I51="Rankings & Achievements","Institutional Reputation","Other"))))) -> Student Experience & Campus | Q51: =IF(OR(J51="Student Experience",J51="Campus Life",J51="Campus Facilities",J51="Student Clubs & Organizations",J51="Events",J51="Student Support Services",J51="Diversity & Inclusion",J51="International Students"),"Student Experience & Campus",IF(OR(J51="Academic Programs",J51="Admissions",J51="Scholarships & Financial Aid"),"Academic & Admissions",IF(OR(J51="Career Opportunities",J51="Alumni Success"),"Career & Alumni",IF(J51="Research & Innovation","Research & Innovation",IF(J51="Rankings & Achievements","Institutional Reputation","Other"))))) -> Student Experience & Campus | R51: =IF(K51="Informational","Informational",IF(OR(K51="Promotional",K51="Call-to-Action"),"Promotional/Conversion",IF(K51="Reputation Building","Reputation-focused","Engagement/Relationship"))) -> Engagement/Relationship | S51: =IF(COUNTIF($A$2:$A$181,A51)>1,"Duplicate","OK") -> OK | T51: =IF(COUNTIF($F$2:$F$181,F51)>1,"Duplicate","OK") -> OK | U51: =IF(AND(TEXT(C51,"mmmm")=D51,YEAR(C51)=E51),"OK","Mismatch") -> OK | V51: =IF(OR(M51="NA",N51="NA"),"Likes/comments unavailable",IF(I51=J51,"Primary and secondary themes identical","OK")) -> OK
A52: MAC015 | B52: McMaster University | C52: 45778 | D52: =IF(C52="","",TEXT(C52,"mmmm")) -> May | E52: =IF(C52="","",YEAR(C52)) -> 2025 | F52: https://www.instagram.com/p/DJHOkZpAGXj/?utm_source=ig_web_copy_link&igsh=MzRlODBiNWFlZA== | G52: Carousel | H52: Yes | I52: Career Opportunities | J52: Student Experience | K52: Inspirational | L52: No | M52: 238 | N52: 7 | O52: randon English’s volunteering journey has been one of self-discovery, confidence building and forging meaningful connections. The @mcmastereng student, mentor and dedicated National Society of Black Engineers (NSBE) leader has created spaces where others feel seen, supported and inspired. | P52: =IF(OR(I52="Student Experience",I52="Campus Life",I52="Campus Facilities",I52="Student Clubs & Organizations",I52="Events",I52="Student Support Services",I52="Diversity & Inclusion",I52="International Students"),"Student Experience & Campus",IF(OR(I52="Academic Programs",I52="Admissions",I52="Scholarships & Financial Aid"),"Academic & Admissions",IF(OR(I52="Career Opportunities",I52="Alumni Success"),"Career & Alumni",IF(I52="Research & Innovation","Research & Innovation",IF(I52="Rankings & Achievements","Institutional Reputation","Other"))))) -> Career & Alumni | Q52: =IF(OR(J52="Student Experience",J52="Campus Life",J52="Campus Facilities",J52="Student Clubs & Organizations",J52="Events",J52="Student Support Services",J52="Diversity & Inclusion",J52="International Students"),"Student Experience & Campus",IF(OR(J52="Academic Programs",J52="Admissions",J52="Scholarships & Financial Aid"),"Academic & Admissions",IF(OR(J52="Career Opportunities",J52="Alumni Success"),"Career & Alumni",IF(J52="Research & Innovation","Research & Innovation",IF(J52="Rankings & Achievements","Institutional Reputation","Other"))))) -> Student Experience & Campus | R52: =IF(K52="Informational","Informational",IF(OR(K52="Promotional",K52="Call-to-Action"),"Promotional/Conversion",IF(K52="Reputation Building","Reputation-focused","Engagement/Relationship"))) -> Engagement/Relationship | S52: =IF(COUNTIF($A$2:$A$181,A52)>1,"Duplicate","OK") -> OK | T52: =IF(COUNTIF($F$2:$F$181,F52)>1,"Duplicate","OK") -> OK | U52: =IF(AND(TEXT(C52,"mmmm")=D52,YEAR(C52)=E52),"OK","Mismatch") -> OK | V52: =IF(OR(M52="NA",N52="NA"),"Likes/comments unavailable",IF(I52=J52,"Primary and secondary themes identical","OK")) -> OK
A53: MAC016 | B53: McMaster University | C53: 45826 | D53: June | E53: 2025 | F53: https://www.instagram.com/reel/DLCxoGWgeL3/?utm_source=ig_web_copy_link&igsh=MzRlODBiNWFlZA== | G53: Reel | H53: Yes | I53: Rankings & Achievements | J53: Research & Innovation | K53: Reputation Building | L53: Yes | M53: 1615 | N53: 17 | O53: McMaster University has been ranked 14th in the world for global impact — a recognition of our community’s hard work in addressing the United Nations Sustainable Development Goals | P53: =IF(OR(I53="Student Experience",I53="Campus Life",I53="Campus Facilities",I53="Student Clubs & Organizations",I53="Events",I53="Student Support Services",I53="Diversity & Inclusion",I53="International Students"),"Student Experience & Campus",IF(OR(I53="Academic Programs",I53="Admissions",I53="Scholarships & Financial Aid"),"Academic & Admissions",IF(OR(I53="Career Opportunities",I53="Alumni Success"),"Career & Alumni",IF(I53="Research & Innovation","Research & Innovation",IF(I53="Rankings & Achievements","Institutional Reputation","Other"))))) -> Institutional Reputation | Q53: =IF(OR(J53="Student Experience",J53="Campus Life",J53="Campus Facilities",J53="Student Clubs & Organizations",J53="Events",J53="Student Support Services",J53="Diversity & Inclusion",J53="International Students"),"Student Experience & Campus",IF(OR(J53="Academic Programs",J53="Admissions",J53="Scholarships & Financial Aid"),"Academic & Admissions",IF(OR(J53="Career Opportunities",J53="Alumni Success"),"Career & Alumni",IF(J53="Research & Innovation","Research & Innovation",IF(J53="Rankings & Achievements","Institutional Reputation","Other"))))) -> Research & Innovation | R53: =IF(K53="Informational","Informational",IF(OR(K53="Promotional",K53="Call-to-Action"),"Promotional/Conversion",IF(K53="Reputation Building","Reputation-focused","Engagement/Relationship"))) -> Reputation-focused | S53: =IF(COUNTIF($A$2:$A$181,A53)>1,"Duplicate","OK") -> OK | T53: =IF(COUNTIF($F$2:$F$181,F53)>1,"Duplicate","OK") -> OK | U53: =IF(AND(TEXT(C53,"mmmm")=D53,YEAR(C53)=E53),"OK","Mismatch") -> OK | V53: =IF(OR(M53="NA",N53="NA"),"Likes/comments unavailable",IF(I53=J53,"Primary and secondary themes identical","OK")) -> OK
A54: MAC017 | B54: McMaster University | C54: 45832 | D54: June | E54: 2025 | F54: https://www.instagram.com/reel/DLSTHthsf9e/?utm_source=ig_web_copy_link&igsh=MzRlODBiNWFlZA== | G54: Reel | H54: Yes | I54: Research & Innovation | J54: Career Opportunities | K54: Reputation Building | L54: Yes | M54: 217 | N54: 1 | O54: McMaster researchers have developed a new material that could accelerate medical research and drug discovery by making it easier to 3D print soft, realistic tissue models. | P54: =IF(OR(I54="Student Experience",I54="Campus Life",I54="Campus Facilities",I54="Student Clubs & Organizations",I54="Events",I54="Student Support Services",I54="Diversity & Inclusion",I54="International Students"),"Student Experience & Campus",IF(OR(I54="Academic Programs",I54="Admissions",I54="Scholarships & Financial Aid"),"Academic & Admissions",IF(OR(I54="Career Opportunities",I54="Alumni Success"),"Career & Alumni",IF(I54="Research & Innovation","Research & Innovation",IF(I54="Rankings & Achievements","Institutional Reputation","Other"))))) -> Research & Innovation | Q54: =IF(OR(J54="Student Experience",J54="Campus Life",J54="Campus Facilities",J54="Student Clubs & Organizations",J54="Events",J54="Student Support Services",J54="Diversity & Inclusion",J54="International Students"),"Student Experience & Campus",IF(OR(J54="Academic Programs",J54="Admissions",J54="Scholarships & Financial Aid"),"Academic & Admissions",IF(OR(J54="Career Opportunities",J54="Alumni Success"),"Career & Alumni",IF(J54="Research & Innovation","Research & Innovation",IF(J54="Rankings & Achievements","Institutional Reputation","Other"))))) -> Career & Alumni | R54: =IF(K54="Informational","Informational",IF(OR(K54="Promotional",K54="Call-to-Action"),"Promotional/Conversion",IF(K54="Reputation Building","Reputation-focused","Engagement/Relationship"))) -> Reputation-focused | S54: =IF(COUNTIF($A$2:$A$181,A54)>1,"Duplicate","OK") -> OK | T54: =IF(COUNTIF($F$2:$F$181,F54)>1,"Duplicate","OK") -> OK | U54: =IF(AND(TEXT(C54,"mmmm")=D54,YEAR(C54)=E54),"OK","Mismatch") -> OK | V54: =IF(OR(M54="NA",N54="NA"),"Likes/comments unavailable",IF(I54=J54,"Primary and secondary themes identical","OK")) -> OK
A55: MAC018 | B55: McMaster University | C55: 45834 | D55: June | E55: 2025 | F55: https://www.instagram.com/reel/DLYB2K-uqH3/?utm_source=ig_web_copy_link&igsh=MzRlODBiNWFlZA== | G55: Reel | H55: Yes | I55: Alumni Success | J55: Student Experience | K55: Inspirational | L55: No | M55: 828 | N55: 7 | O55: Our intern, Josue Reano Navarro, recently became the newest McMaster alumnus in his family—marking three generations of McMaster graduates. Follow him along as he walks across the stage to get his diploma! 🎓 | P55: =IF(OR(I55="Student Experience",I55="Campus Life",I55="Campus Facilities",I55="Student Clubs & Organizations",I55="Events",I55="Student Support Services",I55="Diversity & Inclusion",I55="International Students"),"Student Experience & Campus",IF(OR(I55="Academic Programs",I55="Admissions",I55="Scholarships & Financial Aid"),"Academic & Admissions",IF(OR(I55="Career Opportunities",I55="Alumni Success"),"Career & Alumni",IF(I55="Research & Innovation","Research & Innovation",IF(I55="Rankings & Achievements","Institutional Reputation","Other"))))) -> Career & Alumni | Q55: =IF(OR(J55="Student Experience",J55="Campus Life",J55="Campus Facilities",J55="Student Clubs & Organizations",J55="Events",J55="Student Support Services",J55="Diversity & Inclusion",J55="International Students"),"Student Experience & Campus",IF(OR(J55="Academic Programs",J55="Admissions",J55="Scholarships & Financial Aid"),"Academic & Admissions",IF(OR(J55="Career Opportunities",J55="Alumni Success"),"Career & Alumni",IF(J55="Research & Innovation","Research & Innovation",IF(J55="Rankings & Achievements","Institutional Reputation","Other"))))) -> Student Experience & Campus | R55: =IF(K55="Informational","Informational",IF(OR(K55="Promotional",K55="Call-to-Action"),"Promotional/Conversion",IF(K55="Reputation Building","Reputation-focused","Engagement/Relationship"))) -> Engagement/Relationship | S55: =IF(COUNTIF($A$2:$A$181,A55)>1,"Duplicate","OK") -> OK | T55: =IF(COUNTIF($F$2:$F$181,F55)>1,"Duplicate","OK") -> OK | U55: =IF(AND(TEXT(C55,"mmmm")=D55,YEAR(C55)=E55),"OK","Mismatch") -> OK | V55: =IF(OR(M55="NA",N55="NA"),"Likes/comments unavailable",IF(I55=J55,"Primary and secondary themes identical","OK")) -> OK
A56: MAC019 | B56: McMaster University | C56: 45855 | D56: July | E56: 2025 | F56: https://www.instagram.com/p/DMN-cPSvdrA/?utm_source=ig_web_copy_link&igsh=MzRlODBiNWFlZA== | G56: Carousel | H56: Yes | I56: Alumni Success | J56: Student Experience | K56: Inspirational | L56: Yes | M56: 1620 | N56: 12 | O56: Elizabeth dos Santos and her daughter, Nathalia Reyes, inspired each other to pursue degrees at McMaster, years apart. They got to celebrate together in a surprise moment at the @lanmumcmaster Latin American/Latinx Student Graduate Celebration this year. | P56: =IF(OR(I56="Student Experience",I56="Campus Life",I56="Campus Facilities",I56="Student Clubs & Organizations",I56="Events",I56="Student Support Services",I56="Diversity & Inclusion",I56="International Students"),"Student Experience & Campus",IF(OR(I56="Academic Programs",I56="Admissions",I56="Scholarships & Financial Aid"),"Academic & Admissions",IF(OR(I56="Career Opportunities",I56="Alumni Success"),"Career & Alumni",IF(I56="Research & Innovation","Research & Innovation",IF(I56="Rankings & Achievements","Institutional Reputation","Other"))))) -> Career & Alumni | Q56: =IF(OR(J56="Student Experience",J56="Campus Life",J56="Campus Facilities",J56="Student Clubs & Organizations",J56="Events",J56="Student Support Services",J56="Diversity & Inclusion",J56="International Students"),"Student Experience & Campus",IF(OR(J56="Academic Programs",J56="Admissions",J56="Scholarships & Financial Aid"),"Academic & Admissions",IF(OR(J56="Career Opportunities",J56="Alumni Success"),"Career & Alumni",IF(J56="Research & Innovation","Research & Innovation",IF(J56="Rankings & Achievements","Institutional Reputation","Other"))))) -> Student Experience & Campus | R56: =IF(K56="Informational","Informational",IF(OR(K56="Promotional",K56="Call-to-Action"),"Promotional/Conversion",IF(K56="Reputation Building","Reputation-focused","Engagement/Relationship"))) -> Engagement/Relationship | S56: =IF(COUNTIF($A$2:$A$181,A56)>1,"Duplicate","OK") -> OK | T56: =IF(COUNTIF($F$2:$F$181,F56)>1,"Duplicate","OK") -> OK | U56: =IF(AND(TEXT(C56,"mmmm")=D56,YEAR(C56)=E56),"OK","Mismatch") -> OK | V56: =IF(OR(M56="NA",N56="NA"),"Likes/comments unavailable",IF(I56=J56,"Primary and secondary themes identical","OK")) -> OK
A57: MAC020 | B57: McMaster University | C57: 45862 | D57: July | E57: 2025 | F57: https://www.instagram.com/p/DMflHBuRJKS/?utm_source=ig_web_copy_link&igsh=MzRlODBiNWFlZA== | G57: Carousel | H57: Yes | I57: Career Opportunities | J57: Alumni Success | K57: Emotional Storytelling | L57: Yes | M57: 4323 | N57: 14 | O57: Now, Shobain is a doctor working with some of the biggest names in football, including Cristiano Ronaldo, and he credits his fellowship at McMaster University for helping him on his journey. | P57: =IF(OR(I57="Student Experience",I57="Campus Life",I57="Campus Facilities",I57="Student Clubs & Organizations",I57="Events",I57="Student Support Services",I57="Diversity & Inclusion",I57="International Students"),"Student Experience & Campus",IF(OR(I57="Academic Programs",I57="Admissions",I57="Scholarships & Financial Aid"),"Academic & Admissions",IF(OR(I57="Career Opportunities",I57="Alumni Success"),"Career & Alumni",IF(I57="Research & Innovation","Research & Innovation",IF(I57="Rankings & Achievements","Institutional Reputation","Other"))))) -> Career & Alumni | Q57: =IF(OR(J57="Student Experience",J57="Campus Life",J57="Campus Facilities",J57="Student Clubs & Organizations",J57="Events",J57="Student Support Services",J57="Diversity & Inclusion",J57="International Students"),"Student Experience & Campus",IF(OR(J57="Academic Programs",J57="Admissions",J57="Scholarships & Financial Aid"),"Academic & Admissions",IF(OR(J57="Career Opportunities",J57="Alumni Success"),"Career & Alumni",IF(J57="Research & Innovation","Research & Innovation",IF(J57="Rankings & Achievements","Institutional Reputation","Other"))))) -> Career & Alumni | R57: =IF(K57="Informational","Informational",IF(OR(K57="Promotional",K57="Call-to-Action"),"Promotional/Conversion",IF(K57="Reputation Building","Reputation-focused","Engagement/Relationship"))) -> Engagement/Relationship | S57: =IF(COUNTIF($A$2:$A$181,A57)>1,"Duplicate","OK") -> OK | T57: =IF(COUNTIF($F$2:$F$181,F57)>1,"Duplicate","OK") -> OK | U57: =IF(AND(TEXT(C57,"mmmm")=D57,YEAR(C57)=E57),"OK","Mismatch") -> OK | V57: =IF(OR(M57="NA",N57="NA"),"Likes/comments unavailable",IF(I57=J57,"Primary and secondary themes identical","OK")) -> OK
A58: MAC021 | B58: McMaster University | C58: 45861 | D58: =IF(C58="","",TEXT(C58,"mmmm")) -> July | E58: =IF(C58="","",YEAR(C58)) -> 2025 | F58: https://www.instagram.com/reel/DMdoKLRAnbQ/?utm_source=ig_web_copy_link&igsh=MzRlODBiNWFlZA== | G58: Reel | H58: Yes | I58: Student Experience | J58: Campus Life | K58: Promotional | L58: No | M58: 5615 | N58: 14 | O58: Lights 🎥 Camera 🌸 Beautiful backdrop! McMaster’s campus has served as a filming location for many movies and TV shows over the years. Here’s what a few of those scenes look like 🎬 | P58: =IF(OR(I58="Student Experience",I58="Campus Life",I58="Campus Facilities",I58="Student Clubs & Organizations",I58="Events",I58="Student Support Services",I58="Diversity & Inclusion",I58="International Students"),"Student Experience & Campus",IF(OR(I58="Academic Programs",I58="Admissions",I58="Scholarships & Financial Aid"),"Academic & Admissions",IF(OR(I58="Career Opportunities",I58="Alumni Success"),"Career & Alumni",IF(I58="Research & Innovation","Research & Innovation",IF(I58="Rankings & Achievements","Institutional Reputation","Other"))))) -> Student Experience & Campus | Q58: =IF(OR(J58="Student Experience",J58="Campus Life",J58="Campus Facilities",J58="Student Clubs & Organizations",J58="Events",J58="Student Support Services",J58="Diversity & Inclusion",J58="International Students"),"Student Experience & Campus",IF(OR(J58="Academic Programs",J58="Admissions",J58="Scholarships & Financial Aid"),"Academic & Admissions",IF(OR(J58="Career Opportunities",J58="Alumni Success"),"Career & Alumni",IF(J58="Research & Innovation","Research & Innovation",IF(J58="Rankings & Achievements","Institutional Reputation","Other"))))) -> Student Experience & Campus | R58: =IF(K58="Informational","Informational",IF(OR(K58="Promotional",K58="Call-to-Action"),"Promotional/Conversion",IF(K58="Reputation Building","Reputation-focused","Engagement/Relationship"))) -> Promotional/Conversion | S58: =IF(COUNTIF($A$2:$A$181,A58)>1,"Duplicate","OK") -> OK | T58: =IF(COUNTIF($F$2:$F$181,F58)>1,"Duplicate","OK") -> OK | U58: =IF(AND(TEXT(C58,"mmmm")=D58,YEAR(C58)=E58),"OK","Mismatch") -> OK | V58: =IF(OR(M58="NA",N58="NA"),"Likes/comments unavailable",IF(I58=J58,"Primary and secondary themes identical","OK")) -> OK
A59: MAC022 | B59: McMaster University | C59: 45884 | D59: August | E59: 2025 | F59: https://www.instagram.com/p/DNYkBHlxix6/?utm_source=ig_web_copy_link&igsh=MzRlODBiNWFlZA== | G59: Carousel | H59: Yes | I59: Student Experience | J59: Research & Innovation | K59: Community Engagement | L59: Yes | M59: 1425 | N59: 6 | O59: Myra, a fourth-year biochemistry student and Ryan, a first-year medical student, dedicated to building bridges between students and the communities they hope to serve. The duo has teamed up to secure funding, rally volunteers and assemble 200 kits of high-demand hygiene products for people in need across #Hamilton, #Niagara and #Waterloo. | P59: =IF(OR(I59="Student Experience",I59="Campus Life",I59="Campus Facilities",I59="Student Clubs & Organizations",I59="Events",I59="Student Support Services",I59="Diversity & Inclusion",I59="International Students"),"Student Experience & Campus",IF(OR(I59="Academic Programs",I59="Admissions",I59="Scholarships & Financial Aid"),"Academic & Admissions",IF(OR(I59="Career Opportunities",I59="Alumni Success"),"Career & Alumni",IF(I59="Research & Innovation","Research & Innovation",IF(I59="Rankings & Achievements","Institutional Reputation","Other"))))) -> Student Experience & Campus | Q59: =IF(OR(J59="Student Experience",J59="Campus Life",J59="Campus Facilities",J59="Student Clubs & Organizations",J59="Events",J59="Student Support Services",J59="Diversity & Inclusion",J59="International Students"),"Student Experience & Campus",IF(OR(J59="Academic Programs",J59="Admissions",J59="Scholarships & Financial Aid"),"Academic & Admissions",IF(OR(J59="Career Opportunities",J59="Alumni Success"),"Career & Alumni",IF(J59="Research & Innovation","Research & Innovation",IF(J59="Rankings & Achievements","Institutional Reputation","Other"))))) -> Research & Innovation | R59: =IF(K59="Informational","Informational",IF(OR(K59="Promotional",K59="Call-to-Action"),"Promotional/Conversion",IF(K59="Reputation Building","Reputation-focused","Engagement/Relationship"))) -> Engagement/Relationship | S59: =IF(COUNTIF($A$2:$A$181,A59)>1,"Duplicate","OK") -> OK | T59: =IF(COUNTIF($F$2:$F$181,F59)>1,"Duplicate","OK") -> OK | U59: =IF(AND(TEXT(C59,"mmmm")=D59,YEAR(C59)=E59),"OK","Mismatch") -> OK | V59: =IF(OR(M59="NA",N59="NA"),"Likes/comments unavailable",IF(I59=J59,"Primary and secondary themes identical","OK")) -> OK
A60: MAC023 | B60: McMaster University | C60: 45887 | D60: August | E60: 2025 | F60: https://www.instagram.com/p/DNgWKWXvMcE/?utm_source=ig_web_copy_link&igsh=MzRlODBiNWFlZA== | G60: Carousel | H60: Yes | I60: Campus Life | J60: Career Opportunities | K60: Community Engagement | L60: Yes | M60: 510 | N60: 23 | O60: All summer long, McMaster students have been busy working on campus in a variety of roles. First up in our summer job spotlight series is Sam! | P60: =IF(OR(I60="Student Experience",I60="Campus Life",I60="Campus Facilities",I60="Student Clubs & Organizations",I60="Events",I60="Student Support Services",I60="Diversity & Inclusion",I60="International Students"),"Student Experience & Campus",IF(OR(I60="Academic Programs",I60="Admissions",I60="Scholarships & Financial Aid"),"Academic & Admissions",IF(OR(I60="Career Opportunities",I60="Alumni Success"),"Career & Alumni",IF(I60="Research & Innovation","Research & Innovation",IF(I60="Rankings & Achievements","Institutional Reputation","Other"))))) -> Student Experience & Campus | Q60: =IF(OR(J60="Student Experience",J60="Campus Life",J60="Campus Facilities",J60="Student Clubs & Organizations",J60="Events",J60="Student Support Services",J60="Diversity & Inclusion",J60="International Students"),"Student Experience & Campus",IF(OR(J60="Academic Programs",J60="Admissions",J60="Scholarships & Financial Aid"),"Academic & Admissions",IF(OR(J60="Career Opportunities",J60="Alumni Success"),"Career & Alumni",IF(J60="Research & Innovation","Research & Innovation",IF(J60="Rankings & Achievements","Institutional Reputation","Other"))))) -> Career & Alumni | R60: =IF(K60="Informational","Informational",IF(OR(K60="Promotional",K60="Call-to-Action"),"Promotional/Conversion",IF(K60="Reputation Building","Reputation-focused","Engagement/Relationship"))) -> Engagement/Relationship | S60: =IF(COUNTIF($A$2:$A$181,A60)>1,"Duplicate","OK") -> OK | T60: =IF(COUNTIF($F$2:$F$181,F60)>1,"Duplicate","OK") -> OK | U60: =IF(AND(TEXT(C60,"mmmm")=D60,YEAR(C60)=E60),"OK","Mismatch") -> OK | V60: =IF(OR(M60="NA",N60="NA"),"Likes/comments unavailable",IF(I60=J60,"Primary and secondary themes identical","OK")) -> OK
A61: MAC024 | B61: McMaster University | C61: 45891 | D61: August | E61: 2025 | F61: https://www.instagram.com/p/DNq8uKc4nqO/?utm_source=ig_web_copy_link&igsh=MzRlODBiNWFlZA== | G61: Carousel | H61: Yes | I61: Student Experience | J61: International Students | K61: Community Engagement | L61: Yes | M61: 1635 | N61: 6 | O61: This week, we welcomed international students to McMaster through the Ignite Program. Today marks the last day of Ignite, and these incoming students have had the opportunity to explore campus, residence and downtown Hamiton, as well as learn about on-campus supports, connect with peers and meet faculty members. Swipe for some highlights! | P61: =IF(OR(I61="Student Experience",I61="Campus Life",I61="Campus Facilities",I61="Student Clubs & Organizations",I61="Events",I61="Student Support Services",I61="Diversity & Inclusion",I61="International Students"),"Student Experience & Campus",IF(OR(I61="Academic Programs",I61="Admissions",I61="Scholarships & Financial Aid"),"Academic & Admissions",IF(OR(I61="Career Opportunities",I61="Alumni Success"),"Career & Alumni",IF(I61="Research & Innovation","Research & Innovation",IF(I61="Rankings & Achievements","Institutional Reputation","Other"))))) -> Student Experience & Campus | Q61: =IF(OR(J61="Student Experience",J61="Campus Life",J61="Campus Facilities",J61="Student Clubs & Organizations",J61="Events",J61="Student Support Services",J61="Diversity & Inclusion",J61="International Students"),"Student Experience & Campus",IF(OR(J61="Academic Programs",J61="Admissions",J61="Scholarships & Financial Aid"),"Academic & Admissions",IF(OR(J61="Career Opportunities",J61="Alumni Success"),"Career & Alumni",IF(J61="Research & Innovation","Research & Innovation",IF(J61="Rankings & Achievements","Institutional Reputation","Other"))))) -> Student Experience & Campus | R61: =IF(K61="Informational","Informational",IF(OR(K61="Promotional",K61="Call-to-Action"),"Promotional/Conversion",IF(K61="Reputation Building","Reputation-focused","Engagement/Relationship"))) -> Engagement/Relationship | S61: =IF(COUNTIF($A$2:$A$181,A61)>1,"Duplicate","OK") -> OK | T61: =IF(COUNTIF($F$2:$F$181,F61)>1,"Duplicate","OK") -> OK | U61: =IF(AND(TEXT(C61,"mmmm")=D61,YEAR(C61)=E61),"OK","Mismatch") -> OK | V61: =IF(OR(M61="NA",N61="NA"),"Likes/comments unavailable",IF(I61=J61,"Primary and secondary themes identical","OK")) -> OK
A62: MAC025 | B62: McMaster University | C62: 45544 | D62: =IF(C62="","",TEXT(C62,"mmmm")) -> September | E62: =IF(C62="","",YEAR(C62)) -> 2024 | F62: https://www.instagram.com/reel/C_s3A92xw5z/?utm_source=ig_web_copy_link&igsh=MzRlODBiNWFlZA== | G62: Reel | H62: Yes | I62: Student Experience | J62: Campus Life | K62: Call-to-Action | L62: Yes | M62: 519 | N62: 9 | O62: With all this great energy on campus, we want to know, what are you most excited about this year? ✅ Meeting new people ✅ Exploring student clubs Check our newsletter for opportunities to make both things happen in September. | P62: =IF(OR(I62="Student Experience",I62="Campus Life",I62="Campus Facilities",I62="Student Clubs & Organizations",I62="Events",I62="Student Support Services",I62="Diversity & Inclusion",I62="International Students"),"Student Experience & Campus",IF(OR(I62="Academic Programs",I62="Admissions",I62="Scholarships & Financial Aid"),"Academic & Admissions",IF(OR(I62="Career Opportunities",I62="Alumni Success"),"Career & Alumni",IF(I62="Research & Innovation","Research & Innovation",IF(I62="Rankings & Achievements","Institutional Reputation","Other"))))) -> Student Experience & Campus | Q62: =IF(OR(J62="Student Experience",J62="Campus Life",J62="Campus Facilities",J62="Student Clubs & Organizations",J62="Events",J62="Student Support Services",J62="Diversity & Inclusion",J62="International Students"),"Student Experience & Campus",IF(OR(J62="Academic Programs",J62="Admissions",J62="Scholarships & Financial Aid"),"Academic & Admissions",IF(OR(J62="Career Opportunities",J62="Alumni Success"),"Career & Alumni",IF(J62="Research & Innovation","Research & Innovation",IF(J62="Rankings & Achievements","Institutional Reputation","Other"))))) -> Student Experience & Campus | R62: =IF(K62="Informational","Informational",IF(OR(K62="Promotional",K62="Call-to-Action"),"Promotional/Conversion",IF(K62="Reputation Building","Reputation-focused","Engagement/Relationship"))) -> Promotional/Conversion | S62: =IF(COUNTIF($A$2:$A$181,A62)>1,"Duplicate","OK") -> OK | T62: =IF(COUNTIF($F$2:$F$181,F62)>1,"Duplicate","OK") -> OK | U62: =IF(AND(TEXT(C62,"mmmm")=D62,YEAR(C62)=E62),"OK","Mismatch") -> OK | V62: =IF(OR(M62="NA",N62="NA"),"Likes/comments unavailable",IF(I62=J62,"Primary and secondary themes identical","OK")) -> OK
A63: MAC026 | B63: McMaster University | C63: 45538 | D63: September | E63: 2024 | F63: https://www.instagram.com/reel/C_dQMl4Oy3u/?utm_source=ig_web_copy_link&igsh=MzRlODBiNWFlZA== | G63: Reel | H63: Yes | I63: Student Experience | J63: Campus Life | K63: Inspirational | L63: No | M63: 2486 | N63: 10 | O63: It’s your time now. Welcome to Mac! Fashions change, filters change, campus sure has changed. But one rock-solid fact stands the test of time: Our students are the best! Welcome to the new school year. We’re proud to be part of your journey. | P63: =IF(OR(I63="Student Experience",I63="Campus Life",I63="Campus Facilities",I63="Student Clubs & Organizations",I63="Events",I63="Student Support Services",I63="Diversity & Inclusion",I63="International Students"),"Student Experience & Campus",IF(OR(I63="Academic Programs",I63="Admissions",I63="Scholarships & Financial Aid"),"Academic & Admissions",IF(OR(I63="Career Opportunities",I63="Alumni Success"),"Career & Alumni",IF(I63="Research & Innovation","Research & Innovation",IF(I63="Rankings & Achievements","Institutional Reputation","Other"))))) -> Student Experience & Campus | Q63: =IF(OR(J63="Student Experience",J63="Campus Life",J63="Campus Facilities",J63="Student Clubs & Organizations",J63="Events",J63="Student Support Services",J63="Diversity & Inclusion",J63="International Students"),"Student Experience & Campus",IF(OR(J63="Academic Programs",J63="Admissions",J63="Scholarships & Financial Aid"),"Academic & Admissions",IF(OR(J63="Career Opportunities",J63="Alumni Success"),"Career & Alumni",IF(J63="Research & Innovation","Research & Innovation",IF(J63="Rankings & Achievements","Institutional Reputation","Other"))))) -> Student Experience & Campus | R63: =IF(K63="Informational","Informational",IF(OR(K63="Promotional",K63="Call-to-Action"),"Promotional/Conversion",IF(K63="Reputation Building","Reputation-focused","Engagement/Relationship"))) -> Engagement/Relationship | S63: =IF(COUNTIF($A$2:$A$181,A63)>1,"Duplicate","OK") -> OK | T63: =IF(COUNTIF($F$2:$F$181,F63)>1,"Duplicate","OK") -> OK | U63: =IF(AND(TEXT(C63,"mmmm")=D63,YEAR(C63)=E63),"OK","Mismatch") -> OK | V63: =IF(OR(M63="NA",N63="NA"),"Likes/comments unavailable",IF(I63=J63,"Primary and secondary themes identical","OK")) -> OK
A64: MAC027 | B64: McMaster University | C64: 45558 | D64: =IF(C64="","",TEXT(C64,"mmmm")) -> September | E64: =IF(C64="","",YEAR(C64)) -> 2024 | F64: https://www.instagram.com/reel/DARTKNIvN3P/?utm_source=ig_web_copy_link&igsh=MzRlODBiNWFlZA== | G64: Reel | H64: Yes | I64: Student Experience | J64: Campus Life | K64: Call-to-Action | L64: Yes | M64: 1832 | N64: 15 | O64: Marauders, it’s nearly Homecoming time! Have an amazing day enjoying the football and festivities on campus. Please take care of yourselves, avoid fines and keep the celebrations safe and respectful. Link in bio for more information | P64: =IF(OR(I64="Student Experience",I64="Campus Life",I64="Campus Facilities",I64="Student Clubs & Organizations",I64="Events",I64="Student Support Services",I64="Diversity & Inclusion",I64="International Students"),"Student Experience & Campus",IF(OR(I64="Academic Programs",I64="Admissions",I64="Scholarships & Financial Aid"),"Academic & Admissions",IF(OR(I64="Career Opportunities",I64="Alumni Success"),"Career & Alumni",IF(I64="Research & Innovation","Research & Innovation",IF(I64="Rankings & Achievements","Institutional Reputation","Other"))))) -> Student Experience & Campus | Q64: =IF(OR(J64="Student Experience",J64="Campus Life",J64="Campus Facilities",J64="Student Clubs & Organizations",J64="Events",J64="Student Support Services",J64="Diversity & Inclusion",J64="International Students"),"Student Experience & Campus",IF(OR(J64="Academic Programs",J64="Admissions",J64="Scholarships & Financial Aid"),"Academic & Admissions",IF(OR(J64="Career Opportunities",J64="Alumni Success"),"Career & Alumni",IF(J64="Research & Innovation","Research & Innovation",IF(J64="Rankings & Achievements","Institutional Reputation","Other"))))) -> Student Experience & Campus | R64: =IF(K64="Informational","Informational",IF(OR(K64="Promotional",K64="Call-to-Action"),"Promotional/Conversion",IF(K64="Reputation Building","Reputation-focused","Engagement/Relationship"))) -> Promotional/Conversion | S64: =IF(COUNTIF($A$2:$A$181,A64)>1,"Duplicate","OK") -> OK | T64: =IF(COUNTIF($F$2:$F$181,F64)>1,"Duplicate","OK") -> OK | U64: =IF(AND(TEXT(C64,"mmmm")=D64,YEAR(C64)=E64),"OK","Mismatch") -> OK | V64: =IF(OR(M64="NA",N64="NA"),"Likes/comments unavailable",IF(I64=J64,"Primary and secondary themes identical","OK")) -> OK
A65: MAC028 | B65: McMaster University | C65: 45586 | D65: October | E65: 2024 | F65: https://www.instagram.com/p/DBZdBxFyxwp/?utm_source=ig_web_copy_link&igsh=MzRlODBiNWFlZA== | G65: Carousel | H65: Yes | I65: Student Experience | J65: Student Support Services | K65: Community Engagement | L65: No | M65: 898 | N65: 5 | O65: Milo and seven other undergraduate students had the opportunity to take their knowledge out into the field in Bamfield, British Columbia, studying coastal invasive species and how to reduce negative impacts on local ecosystems. This two-week experiential learning opportunity, supported by the Student Success Centre an | P65: =IF(OR(I65="Student Experience",I65="Campus Life",I65="Campus Facilities",I65="Student Clubs & Organizations",I65="Events",I65="Student Support Services",I65="Diversity & Inclusion",I65="International Students"),"Student Experience & Campus",IF(OR(I65="Academic Programs",I65="Admissions",I65="Scholarships & Financial Aid"),"Academic & Admissions",IF(OR(I65="Career Opportunities",I65="Alumni Success"),"Career & Alumni",IF(I65="Research & Innovation","Research & Innovation",IF(I65="Rankings & Achievements","Institutional Reputation","Other"))))) -> Student Experience & Campus | Q65: =IF(OR(J65="Student Experience",J65="Campus Life",J65="Campus Facilities",J65="Student Clubs & Organizations",J65="Events",J65="Student Support Services",J65="Diversity & Inclusion",J65="International Students"),"Student Experience & Campus",IF(OR(J65="Academic Programs",J65="Admissions",J65="Scholarships & Financial Aid"),"Academic & Admissions",IF(OR(J65="Career Opportunities",J65="Alumni Success"),"Career & Alumni",IF(J65="Research & Innovation","Research & Innovation",IF(J65="Rankings & Achievements","Institutional Reputation","Other"))))) -> Student Experience & Campus | R65: =IF(K65="Informational","Informational",IF(OR(K65="Promotional",K65="Call-to-Action"),"Promotional/Conversion",IF(K65="Reputation Building","Reputation-focused","Engagement/Relationship"))) -> Engagement/Relationship | S65: =IF(COUNTIF($A$2:$A$181,A65)>1,"Duplicate","OK") -> OK | T65: =IF(COUNTIF($F$2:$F$181,F65)>1,"Duplicate","OK") -> OK | U65: =IF(AND(TEXT(C65,"mmmm")=D65,YEAR(C65)=E65),"OK","Mismatch") -> OK | V65: =IF(OR(M65="NA",N65="NA"),"Likes/comments unavailable",IF(I65=J65,"Primary and secondary themes identical","OK")) -> OK
A66: MAC029 | B66: McMaster University | C66: 45588 | D66: =IF(C66="","",TEXT(C66,"mmmm")) -> October | E66: =IF(C66="","",YEAR(C66)) -> 2024 | F66: https://www.instagram.com/reel/DBeV-6PRrjS/?utm_source=ig_web_copy_link&igsh=MzRlODBiNWFlZA== | G66: Reel | H66: Yes | I66: Admissions | J66: Events | K66: Call-to-Action | L66: Yes | M66: 330 | N66: 1 | O66: McMaster’s Fall Preview Open House is THIS Saturday! Join us this Saturday, October 26 from 10:00am - 4:00pm to explore our campus, learn about our programs, and discover what it’s like to live and learn at Mac. It’s basically your all access pass to the university to get all your questions answered! | P66: =IF(OR(I66="Student Experience",I66="Campus Life",I66="Campus Facilities",I66="Student Clubs & Organizations",I66="Events",I66="Student Support Services",I66="Diversity & Inclusion",I66="International Students"),"Student Experience & Campus",IF(OR(I66="Academic Programs",I66="Admissions",I66="Scholarships & Financial Aid"),"Academic & Admissions",IF(OR(I66="Career Opportunities",I66="Alumni Success"),"Career & Alumni",IF(I66="Research & Innovation","Research & Innovation",IF(I66="Rankings & Achievements","Institutional Reputation","Other"))))) -> Academic & Admissions | Q66: =IF(OR(J66="Student Experience",J66="Campus Life",J66="Campus Facilities",J66="Student Clubs & Organizations",J66="Events",J66="Student Support Services",J66="Diversity & Inclusion",J66="International Students"),"Student Experience & Campus",IF(OR(J66="Academic Programs",J66="Admissions",J66="Scholarships & Financial Aid"),"Academic & Admissions",IF(OR(J66="Career Opportunities",J66="Alumni Success"),"Career & Alumni",IF(J66="Research & Innovation","Research & Innovation",IF(J66="Rankings & Achievements","Institutional Reputation","Other"))))) -> Student Experience & Campus | R66: =IF(K66="Informational","Informational",IF(OR(K66="Promotional",K66="Call-to-Action"),"Promotional/Conversion",IF(K66="Reputation Building","Reputation-focused","Engagement/Relationship"))) -> Promotional/Conversion | S66: =IF(COUNTIF($A$2:$A$181,A66)>1,"Duplicate","OK") -> OK | T66: =IF(COUNTIF($F$2:$F$181,F66)>1,"Duplicate","OK") -> OK | U66: =IF(AND(TEXT(C66,"mmmm")=D66,YEAR(C66)=E66),"OK","Mismatch") -> OK | V66: =IF(OR(M66="NA",N66="NA"),"Likes/comments unavailable",IF(I66=J66,"Primary and secondary themes identical","OK")) -> OK
A67: MAC030 | B67: McMaster University | C67: 45596 | D67: =IF(C67="","",TEXT(C67,"mmmm")) -> October | E67: =IF(C67="","",YEAR(C67)) -> 2024 | F67: https://www.instagram.com/reel/DBy8SArxam0/?utm_source=ig_web_copy_link&igsh=MzRlODBiNWFlZA== | G67: Reel | H67: Yes | I67: Academic Programs | J67: International Students | K67: Emotional Storytelling | L67: Yes | M67: 245 | N67: 2 | O67: From Rio de Janeiro, Brazil ➡️ Hamilton, Ontario; Carolinna chose McMaster as the next step on her educational journey, joining us this past September 2024 in our Integrated Science program. | P67: =IF(OR(I67="Student Experience",I67="Campus Life",I67="Campus Facilities",I67="Student Clubs & Organizations",I67="Events",I67="Student Support Services",I67="Diversity & Inclusion",I67="International Students"),"Student Experience & Campus",IF(OR(I67="Academic Programs",I67="Admissions",I67="Scholarships & Financial Aid"),"Academic & Admissions",IF(OR(I67="Career Opportunities",I67="Alumni Success"),"Career & Alumni",IF(I67="Research & Innovation","Research & Innovation",IF(I67="Rankings & Achievements","Institutional Reputation","Other"))))) -> Academic & Admissions | Q67: =IF(OR(J67="Student Experience",J67="Campus Life",J67="Campus Facilities",J67="Student Clubs & Organizations",J67="Events",J67="Student Support Services",J67="Diversity & Inclusion",J67="International Students"),"Student Experience & Campus",IF(OR(J67="Academic Programs",J67="Admissions",J67="Scholarships & Financial Aid"),"Academic & Admissions",IF(OR(J67="Career Opportunities",J67="Alumni Success"),"Career & Alumni",IF(J67="Research & Innovation","Research & Innovation",IF(J67="Rankings & Achievements","Institutional Reputation","Other"))))) -> Student Experience & Campus | R67: =IF(K67="Informational","Informational",IF(OR(K67="Promotional",K67="Call-to-Action"),"Promotional/Conversion",IF(K67="Reputation Building","Reputation-focused","Engagement/Relationship"))) -> Engagement/Relationship | S67: =IF(COUNTIF($A$2:$A$181,A67)>1,"Duplicate","OK") -> OK | T67: =IF(COUNTIF($F$2:$F$181,F67)>1,"Duplicate","OK") -> OK | U67: =IF(AND(TEXT(C67,"mmmm")=D67,YEAR(C67)=E67),"OK","Mismatch") -> OK | V67: =IF(OR(M67="NA",N67="NA"),"Likes/comments unavailable",IF(I67=J67,"Primary and secondary themes identical","OK")) -> OK
A68: MAC031 | B68: McMaster University | C68: 45611 | D68: November | E68: 2024 | F68: https://www.instagram.com/reel/DCZqe3LyXup/?utm_source=ig_web_copy_link&igsh=MzRlODBiNWFlZA== | G68: Reel | H68: Yes | I68: Admissions | J68: Events | K68: Call-to-Action | L68: Yes | M68: 191 | N68: 0 | O68: 5 Things to Know for our Fall Preview Open House happening TOMORROW!🎉 We are so excited to welcome you to our second Fall Preview Open House. You’ll have the opportunity to learn more about our programs, tour classrooms and residences, meet students, faculty, and staff, and get all your questions answered. | P68: =IF(OR(I68="Student Experience",I68="Campus Life",I68="Campus Facilities",I68="Student Clubs & Organizations",I68="Events",I68="Student Support Services",I68="Diversity & Inclusion",I68="International Students"),"Student Experience & Campus",IF(OR(I68="Academic Programs",I68="Admissions",I68="Scholarships & Financial Aid"),"Academic & Admissions",IF(OR(I68="Career Opportunities",I68="Alumni Success"),"Career & Alumni",IF(I68="Research & Innovation","Research & Innovation",IF(I68="Rankings & Achievements","Institutional Reputation","Other"))))) -> Academic & Admissions | Q68: =IF(OR(J68="Student Experience",J68="Campus Life",J68="Campus Facilities",J68="Student Clubs & Organizations",J68="Events",J68="Student Support Services",J68="Diversity & Inclusion",J68="International Students"),"Student Experience & Campus",IF(OR(J68="Academic Programs",J68="Admissions",J68="Scholarships & Financial Aid"),"Academic & Admissions",IF(OR(J68="Career Opportunities",J68="Alumni Success"),"Career & Alumni",IF(J68="Research & Innovation","Research & Innovation",IF(J68="Rankings & Achievements","Institutional Reputation","Other"))))) -> Student Experience & Campus | R68: =IF(K68="Informational","Informational",IF(OR(K68="Promotional",K68="Call-to-Action"),"Promotional/Conversion",IF(K68="Reputation Building","Reputation-focused","Engagement/Relationship"))) -> Promotional/Conversion | S68: =IF(COUNTIF($A$2:$A$181,A68)>1,"Duplicate","OK") -> OK | T68: =IF(COUNTIF($F$2:$F$181,F68)>1,"Duplicate","OK") -> OK | U68: =IF(AND(TEXT(C68,"mmmm")=D68,YEAR(C68)=E68),"OK","Mismatch") -> OK | V68: =IF(OR(M68="NA",N68="NA"),"Likes/comments unavailable",IF(I68=J68,"Primary and secondary themes identical","OK")) -> OK
A69: MAC032 | B69: McMaster University | C69: 45615 | D69: =IF(C69="","",TEXT(C69,"mmmm")) -> November | E69: =IF(C69="","",YEAR(C69)) -> 2024 | F69: https://www.instagram.com/reel/DCjz2lxPHH6/?utm_source=ig_web_copy_link&igsh=MzRlODBiNWFlZA== | G69: Reel | H69: Yes | I69: Admissions | J69: Student Experience | K69: Student Testimonial | L69: Yes | M69: 833 | N69: 14 | O69: Join me for a glimpse into my life as a psychology student, where Wednesdays are my busiest and most exciting days! -Aditi, your McMaster Content Creator | P69: =IF(OR(I69="Student Experience",I69="Campus Life",I69="Campus Facilities",I69="Student Clubs & Organizations",I69="Events",I69="Student Support Services",I69="Diversity & Inclusion",I69="International Students"),"Student Experience & Campus",IF(OR(I69="Academic Programs",I69="Admissions",I69="Scholarships & Financial Aid"),"Academic & Admissions",IF(OR(I69="Career Opportunities",I69="Alumni Success"),"Career & Alumni",IF(I69="Research & Innovation","Research & Innovation",IF(I69="Rankings & Achievements","Institutional Reputation","Other"))))) -> Academic & Admissions | Q69: =IF(OR(J69="Student Experience",J69="Campus Life",J69="Campus Facilities",J69="Student Clubs & Organizations",J69="Events",J69="Student Support Services",J69="Diversity & Inclusion",J69="International Students"),"Student Experience & Campus",IF(OR(J69="Academic Programs",J69="Admissions",J69="Scholarships & Financial Aid"),"Academic & Admissions",IF(OR(J69="Career Opportunities",J69="Alumni Success"),"Career & Alumni",IF(J69="Research & Innovation","Research & Innovation",IF(J69="Rankings & Achievements","Institutional Reputation","Other"))))) -> Student Experience & Campus | R69: =IF(K69="Informational","Informational",IF(OR(K69="Promotional",K69="Call-to-Action"),"Promotional/Conversion",IF(K69="Reputation Building","Reputation-focused","Engagement/Relationship"))) -> Engagement/Relationship | S69: =IF(COUNTIF($A$2:$A$181,A69)>1,"Duplicate","OK") -> OK | T69: =IF(COUNTIF($F$2:$F$181,F69)>1,"Duplicate","OK") -> OK | U69: =IF(AND(TEXT(C69,"mmmm")=D69,YEAR(C69)=E69),"OK","Mismatch") -> OK | V69: =IF(OR(M69="NA",N69="NA"),"Likes/comments unavailable",IF(I69=J69,"Primary and secondary themes identical","OK")) -> OK
A70: MAC033 | B70: McMaster University | C70: 45618 | D70: =IF(C70="","",TEXT(C70,"mmmm")) -> November | E70: =IF(C70="","",YEAR(C70)) -> 2024 | F70: https://www.instagram.com/p/DCr4djdvi-B/?utm_source=ig_web_copy_link&igsh=MzRlODBiNWFlZA== | G70: Carousel | H70: Yes | I70: Student Experience | J70: Events | K70: Inspirational | L70: No | M70: 2742 | N70: 70 | O70: Congratulations, Marauders! You did it!🎉 We were so delighted to celebrate your hard work and accomplishments at fall Convocation this week. | P70: =IF(OR(I70="Student Experience",I70="Campus Life",I70="Campus Facilities",I70="Student Clubs & Organizations",I70="Events",I70="Student Support Services",I70="Diversity & Inclusion",I70="International Students"),"Student Experience & Campus",IF(OR(I70="Academic Programs",I70="Admissions",I70="Scholarships & Financial Aid"),"Academic & Admissions",IF(OR(I70="Career Opportunities",I70="Alumni Success"),"Career & Alumni",IF(I70="Research & Innovation","Research & Innovation",IF(I70="Rankings & Achievements","Institutional Reputation","Other"))))) -> Student Experience & Campus | Q70: =IF(OR(J70="Student Experience",J70="Campus Life",J70="Campus Facilities",J70="Student Clubs & Organizations",J70="Events",J70="Student Support Services",J70="Diversity & Inclusion",J70="International Students"),"Student Experience & Campus",IF(OR(J70="Academic Programs",J70="Admissions",J70="Scholarships & Financial Aid"),"Academic & Admissions",IF(OR(J70="Career Opportunities",J70="Alumni Success"),"Career & Alumni",IF(J70="Research & Innovation","Research & Innovation",IF(J70="Rankings & Achievements","Institutional Reputation","Other"))))) -> Student Experience & Campus | R70: =IF(K70="Informational","Informational",IF(OR(K70="Promotional",K70="Call-to-Action"),"Promotional/Conversion",IF(K70="Reputation Building","Reputation-focused","Engagement/Relationship"))) -> Engagement/Relationship | S70: =IF(COUNTIF($A$2:$A$181,A70)>1,"Duplicate","OK") -> OK | T70: =IF(COUNTIF($F$2:$F$181,F70)>1,"Duplicate","OK") -> OK | U70: =IF(AND(TEXT(C70,"mmmm")=D70,YEAR(C70)=E70),"OK","Mismatch") -> OK | V70: =IF(OR(M70="NA",N70="NA"),"Likes/comments unavailable",IF(I70=J70,"Primary and secondary themes identical","OK")) -> OK
A71: MAC034 | B71: McMaster University | C71: 45636 | D71: December | E71: 2024 | F71: https://www.instagram.com/reel/DDZxB4ev4au/?utm_source=ig_web_copy_link&igsh=MzRlODBiNWFlZA== | G71: Reel | H71: Yes | I71: Student Experience | J71: Academic Programs | K71: Inspirational | L71: No | M71: 407 | N71: 12 | O71: For me, my first year at McMaster was all about figuring out the direction I wanted to take. Here’s how some of my favourite academic experiences helped me figure which courses to take, and which path to pursue. | P71: =IF(OR(I71="Student Experience",I71="Campus Life",I71="Campus Facilities",I71="Student Clubs & Organizations",I71="Events",I71="Student Support Services",I71="Diversity & Inclusion",I71="International Students"),"Student Experience & Campus",IF(OR(I71="Academic Programs",I71="Admissions",I71="Scholarships & Financial Aid"),"Academic & Admissions",IF(OR(I71="Career Opportunities",I71="Alumni Success"),"Career & Alumni",IF(I71="Research & Innovation","Research & Innovation",IF(I71="Rankings & Achievements","Institutional Reputation","Other"))))) -> Student Experience & Campus | Q71: =IF(OR(J71="Student Experience",J71="Campus Life",J71="Campus Facilities",J71="Student Clubs & Organizations",J71="Events",J71="Student Support Services",J71="Diversity & Inclusion",J71="International Students"),"Student Experience & Campus",IF(OR(J71="Academic Programs",J71="Admissions",J71="Scholarships & Financial Aid"),"Academic & Admissions",IF(OR(J71="Career Opportunities",J71="Alumni Success"),"Career & Alumni",IF(J71="Research & Innovation","Research & Innovation",IF(J71="Rankings & Achievements","Institutional Reputation","Other"))))) -> Academic & Admissions | R71: =IF(K71="Informational","Informational",IF(OR(K71="Promotional",K71="Call-to-Action"),"Promotional/Conversion",IF(K71="Reputation Building","Reputation-focused","Engagement/Relationship"))) -> Engagement/Relationship | S71: =IF(COUNTIF($A$2:$A$181,A71)>1,"Duplicate","OK") -> OK | T71: =IF(COUNTIF($F$2:$F$181,F71)>1,"Duplicate","OK") -> OK | U71: =IF(AND(TEXT(C71,"mmmm")=D71,YEAR(C71)=E71),"OK","Mismatch") -> OK | V71: =IF(OR(M71="NA",N71="NA"),"Likes/comments unavailable",IF(I71=J71,"Primary and secondary themes identical","OK")) -> OK
